Workbook

Sheet Profile and Overview
B2: A Term Paper on "The Application of the Dynamic Asset Allocation Strategy and Comparisons with Other Alternative Investment Strategies"
B7: Course: F-503: Financial Derivatives
B9: Name: Ifta Hider Rahman
B11: MBA Batch
B12: Department of Finance
B13: Faculty of Business Studies (FBS)
B14: University of Dhaka, Dhaka-1000
B17: Project Overview: This Excel model analyzes Dynamic Asset Allocation strategies for a portfolio of eight DSE stocks and a risk-free asset. Utilizing actual price/dividend data and binomial option modeling, it demonstrates dynamic rebalancing, portfolio insurance, and risk-return tradeoffs versus alternative strategies.
B23: Main Features: - Data-driven delta hedging and portfolio insurance modeling - Dynamic vs. static (rebalanced/unrebalanced) portfolio analysis - Stepwise portfolio adjustment using real market prices - Comprehensive risk and return output tables
B30: Instructions: - Explore each tab for calculations, figures, and explanatory notes. - All steps are labeled for clarity; summary results are found at the end.

Sheet Assumptions
B2: Assumptions: | C2: Amount | E2: Notes
B3: Period: 2024 Q1 to 2025 Q3
B4: 1. Amount of Investment | C4: 1000000
B5: 2. Risk Free Rate | E5: Weighted average cut off yield of 91 day t-bill
B6: 3. Strike Price | C6: =C4*(1+0.05) -> 1050000 | E6: 5% higher than initial investment
B7: 4. Investment will be made in equal weight among 8 securities
B8: 5. Continuous compounding of risk free rate will be used
B9: 7. Call and put strike prices are assumed to be equal at expiration time

Sheet Stock Selection
B2: Stock Selection
B4: Firm | C4: Trading Code | D4: Sector | E4: Market Capitalization | F4: P/E Multiple | G4: Dividend Yield | H4: Net Asset Value Per Share
B5: United Commercial Bank Ltd | C5: UCB | D5: Bank | E5: 15658.797 | F5: 23.67 | H5: 26.42
B6: IDLC Finance Ltd | C6: IDLC | D6: Financial Institutions | E6: 15364.216 | F6: 6.79 | G6: 0.0459 | H6: 48.26
B7: Grameenphone Ltd | C7: GP | D7: Telecommunication | E7: 374978.32 | F7: 12.02 | G7: 0.1021 | H7: 47.95
B8: Bata Shoe Company Bangladesh Ltd | C8: BATASHOE | D8: Tannery Industries | E8: 11617.056 | F8: 41.88 | G8: 0.0491 | H8: 220.22
B9: Renata Ltd | C9: RENATA | D9: Pharmaceuticals & Chemicals | E9: 44823.388 | F9: 24.43 | G9: 0.0119 | H9: 295.56
B10: Walton Hi-Tech Industries Ltd | C10: WALTONHIL | D10: Engineering | E10: 121259.19 | F10: 11.87 | G10: 0.0431 | H10: 399.74
B11: Rak Ceramics Bangladesh Ltd | C11: RAKC | D11: Ceramics Sector | E11: 9115.733 | F11: 11.88 | G11: 0.0391 | H11: 78.28
B12: Olympic Industries Ltd | C12: OLYMPIC | D12: Food & Allied | E12: 28071.42 | F12: 14.43 | G12: 0.0076 | H12: 53.29

Sheet Data
C1: United Commercial Bank Ltd (UCBL) | K1: IDLC Finance Ltd (IDLC) | S1: Grameenphone Ltd (GP) | AA1: Bata Shoe Company Bangladesh Ltd (BATA) | AI1: Renata Ltd (RNTL) | AQ1: Walton Hi-Tech Industries Ltd (WALT) | AY1: Rak Ceramics Bangladesh Ltd (RAKC) | BG1: Olympic Industries Ltd (OLIS)
B2: Date | C2: Price | D2: Stock Dividend (%) | E2: Right Ratio (%) | F2: Right Offer Price (TK.) | G2: Stock Dividend and Righ Share Adjusted Price | H2: Cash Dividend (TK.) | I2: Total Return (%) | J2: Date | K2: =C2 -> Price | L2: =D2 -> Stock Dividend (%) | M2: =E2 -> Right Ratio (%) | N2: =F2 -> Right Offer Price (TK.) | O2: =G2 -> Stock Dividend and Righ Share Adjusted Price | P2: =H2 -> Cash Dividend (TK.) | Q2: =I2 -> Total Return (%) | R2: Date | S2: =C2 -> Price | T2: =D2 -> Stock Dividend (%) | U2: =E2 -> Right Ratio (%) | V2: =F2 -> Right Offer Price (TK.) | W2: =G2 -> Stock Dividend and Righ Share Adjusted Price | X2: =H2 -> Cash Dividend (TK.) | Y2: =I2 -> Total Return (%) | Z2: Date | AA2: =C2 -> Price | AB2: =D2 -> Stock Dividend (%) | AC2: =E2 -> Right Ratio (%) | AD2: =F2 -> Right Offer Price (TK.) | AE2: =G2 -> Stock Dividend and Righ Share Adjusted Price | AF2: =H2 -> Cash Dividend (TK.) | AG2: =I2 -> Total Return (%) | AH2: Date | AI2: =AA2 -> Price | AJ2: =AB2 -> Stock Dividend (%) | AK2: =AC2 -> Right Ratio (%) | AL2: =AD2 -> Right Offer Price (TK.) | AM2: =AE2 -> Stock Dividend and Righ Share Adjusted Price | AN2: =AF2 -> Cash Dividend (TK.) | AO2: =AG2 -> Total Return (%) | AP2: Date | AQ2: =C2 -> Price | AR2: =D2 -> Stock Dividend (%) | AS2: =E2 -> Right Ratio (%) | AT2: =F2 -> Right Offer Price (TK.) | AU2: =G2 -> Stock Dividend and Righ Share Adjusted Price | AV2: =H2 -> Cash Dividend (TK.) | AW2: =I2 -> Total Return (%) | AX2: Date | AY2: =C2 -> Price | AZ2: =D2 -> Stock Dividend (%) | BA2: =E2 -> Right Ratio (%) | BB2: =F2 -> Right Offer Price (TK.) | BC2: =G2 -> Stock Dividend and Righ Share Adjusted Price | BD2: =H2 -> Cash Dividend (TK.) | BE2: =I2 -> Total Return (%) | BF2: Date | BG2: =C2 -> Price | BH2: =D2 -> Stock Dividend (%) | BI2: =E2 -> Right Ratio (%) | BJ2: =F2 -> Right Offer Price (TK.) | BK2: =G2 -> Stock Dividend and Righ Share Adjusted Price | BL2: =H2 -> Cash Dividend (TK.) | BM2: =I2 -> Total Return (%)
A3: 2024 Q1 | B3: 45292 | C3: 12.4 | G3: =C3+C3*D3+C3*E3-F3*E3 -> 12.4 | J3: 45292 | K3: 46.5 | O3: =K3+K3*L3+K3*M3-N3*M3 -> 46.5 | R3: 45292 | S3: 286.6 | W3: =S3+S3*T3+S3*U3-V3*U3 -> 286.6 | Z3: 45292 | AA3: 966.6 | AE3: =AA3+AA3*AB3+AA3*AC3-AD3*AC3 -> 966.6 | AH3: 45292 | AI3: 1217.9 | AM3: =AI3+AI3*AJ3+AI3*AK3-AL3*AK3 -> 1217.9 | AP3: 45292 | AQ3: 1047.7 | AU3: =AQ3+AQ3*AR3+AQ3*AS3-AT3*AS3 -> 1047.7 | AX3: 45292 | AY3: 42.9 | BC3: =AY3+AY3*AZ3+AY3*BA3-BB3*BA3 -> 42.9 | BF3: 45292 | BG3: 151.2 | BK3: =BG3+BG3*BH3+BG3*BI3-BJ3*BI3 -> 151.2
B4: 45293 | C4: 12.4 | G4: =C4+C4*D4+C4*E4-F4*E4 -> 12.4 | I4: =LN((G4+H4)/G3) -> 0 | J4: 45293 | K4: 46.5 | O4: =K4+K4*L4+K4*M4-N4*M4 -> 46.5 | Q4: =LN((O4+P4)/O3) -> 0 | R4: 45293 | S4: 286.6 | W4: =S4+S4*T4+S4*U4-V4*U4 -> 286.6 | Y4: =LN((W4+X4)/W3) -> 0 | Z4: 45293 | AA4: 961.3 | AE4: =AA4+AA4*AB4+AA4*AC4-AD4*AC4 -> 961.3 | AG4: =LN((AE4+AF4)/AE3) -> -0.0054982243 | AH4: 45293 | AI4: 1217.9 | AM4: =AI4+AI4*AJ4+AI4*AK4-AL4*AK4 -> 1217.9 | AO4: =LN((AM4+AN4)/AM3) -> 0 | AP4: 45293 | AQ4: 1047.7 | AU4: =AQ4+AQ4*AR4+AQ4*AS4-AT4*AS4 -> 1047.7 | AW4: =LN((AU4+AV4)/AU3) -> 0 | AX4: 45293 | AY4: 42.9 | BC4: =AY4+AY4*AZ4+AY4*BA4-BB4*BA4 -> 42.9 | BE4: =LN((BC4+BD4)/BC3) -> 0 | BF4: 45293 | BG4: 152 | BK4: =BG4+BG4*BH4+BG4*BI4-BJ4*BI4 -> 152 | BM4: =LN((BK4+BL4)/BK3) -> 0.0052770571
B5: 45294 | C5: 12.4 | G5: =C5+C5*D5+C5*E5-F5*E5 -> 12.4 | I5: =LN((G5+H5)/G4) -> 0 | J5: 45294 | K5: 46.5 | O5: =K5+K5*L5+K5*M5-N5*M5 -> 46.5 | Q5: =LN((O5+P5)/O4) -> 0 | R5: 45294 | S5: 286.6 | W5: =S5+S5*T5+S5*U5-V5*U5 -> 286.6 | Y5: =LN((W5+X5)/W4) -> 0 | Z5: 45294 | AA5: 961.2 | AE5: =AA5+AA5*AB5+AA5*AC5-AD5*AC5 -> 961.2 | AG5: =LN((AE5+AF5)/AE4) -> -0.00010403121 | AH5: 45294 | AI5: 1217.9 | AM5: =AI5+AI5*AJ5+AI5*AK5-AL5*AK5 -> 1217.9 | AO5: =LN((AM5+AN5)/AM4) -> 0 | AP5: 45294 | AQ5: 1047.7 | AU5: =AQ5+AQ5*AR5+AQ5*AS5-AT5*AS5 -> 1047.7 | AW5: =LN((AU5+AV5)/AU4) -> 0 | AX5: 45294 | AY5: 42.9 | BC5: =AY5+AY5*AZ5+AY5*BA5-BB5*BA5 -> 42.9 | BE5: =LN((BC5+BD5)/BC4) -> 0 | BF5: 45294 | BG5: 154.3 | BK5: =BG5+BG5*BH5+BG5*BI5-BJ5*BI5 -> 154.3 | BM5: =LN((BK5+BL5)/BK4) -> 0.015018239
B6: 45295 | C6: 12.4 | G6: =C6+C6*D6+C6*E6-F6*E6 -> 12.4 | I6: =LN((G6+H6)/G5) -> 0 | J6: 45295 | K6: 46.5 | O6: =K6+K6*L6+K6*M6-N6*M6 -> 46.5 | Q6: =LN((O6+P6)/O5) -> 0 | R6: 45295 | S6: 286.6 | W6: =S6+S6*T6+S6*U6-V6*U6 -> 286.6 | Y6: =LN((W6+X6)/W5) -> 0 | Z6: 45295 | AA6: 968.6 | AE6: =AA6+AA6*AB6+AA6*AC6-AD6*AC6 -> 968.6 | AG6: =LN((AE6+AF6)/AE5) -> 0.0076692261 | AH6: 45295 | AI6: 1217.9 | AM6: =AI6+AI6*AJ6+AI6*AK6-AL6*AK6 -> 1217.9 | AO6: =LN((AM6+AN6)/AM5) -> 0 | AP6: 45295 | AQ6: 1047.7 | AU6: =AQ6+AQ6*AR6+AQ6*AS6-AT6*AS6 -> 1047.7 | AW6: =LN((AU6+AV6)/AU5) -> 0 | AX6: 45295 | AY6: 42.9 | BC6: =AY6+AY6*AZ6+AY6*BA6-BB6*BA6 -> 42.9 | BE6: =LN((BC6+BD6)/BC5) -> 0 | BF6: 45295 | BG6: 156.3 | BK6: =BG6+BG6*BH6+BG6*BI6-BJ6*BI6 -> 156.3 | BM6: =LN((BK6+BL6)/BK5) -> 0.012878478
B7: 45299 | C7: 12.4 | G7: =C7+C7*D7+C7*E7-F7*E7 -> 12.4 | I7: =LN((G7+H7)/G6) -> 0 | J7: 45299 | K7: 46.5 | O7: =K7+K7*L7+K7*M7-N7*M7 -> 46.5 | Q7: =LN((O7+P7)/O6) -> 0 | R7: 45299 | S7: 286.6 | W7: =S7+S7*T7+S7*U7-V7*U7 -> 286.6 | Y7: =LN((W7+X7)/W6) -> 0 | Z7: 45299 | AA7: 969.4 | AE7: =AA7+AA7*AB7+AA7*AC7-AD7*AC7 -> 969.4 | AG7: =LN((AE7+AF7)/AE6) -> 0.00082559344 | AH7: 45299 | AI7: 1217.9 | AM7: =AI7+AI7*AJ7+AI7*AK7-AL7*AK7 -> 1217.9 | AO7: =LN((AM7+AN7)/AM6) -> 0 | AP7: 45299 | AQ7: 1047.7 | AU7: =AQ7+AQ7*AR7+AQ7*AS7-AT7*AS7 -> 1047.7 | AW7: =LN((AU7+AV7)/AU6) -> 0 | AX7: 45299 | AY7: 42.9 | BC7: =AY7+AY7*AZ7+AY7*BA7-BB7*BA7 -> 42.9 | BE7: =LN((BC7+BD7)/BC6) -> 0 | BF7: 45299 | BG7: 155.5 | BK7: =BG7+BG7*BH7+BG7*BI7-BJ7*BI7 -> 155.5 | BM7: =LN((BK7+BL7)/BK6) -> -0.0051315058
B8: 45300 | C8: 12.4 | G8: =C8+C8*D8+C8*E8-F8*E8 -> 12.4 | I8: =LN((G8+H8)/G7) -> 0 | J8: 45300 | K8: 46.5 | O8: =K8+K8*L8+K8*M8-N8*M8 -> 46.5 | Q8: =LN((O8+P8)/O7) -> 0 | R8: 45300 | S8: 286.6 | W8: =S8+S8*T8+S8*U8-V8*U8 -> 286.6 | Y8: =LN((W8+X8)/W7) -> 0 | Z8: 45300 | AA8: 963 | AE8: =AA8+AA8*AB8+AA8*AC8-AD8*AC8 -> 963 | AG8: =LN((AE8+AF8)/AE7) -> -0.0066239116 | AH8: 45300 | AI8: 1217.9 | AM8: =AI8+AI8*AJ8+AI8*AK8-AL8*AK8 -> 1217.9 | AO8: =LN((AM8+AN8)/AM7) -> 0 | AP8: 45300 | AQ8: 1047.7 | AU8: =AQ8+AQ8*AR8+AQ8*AS8-AT8*AS8 -> 1047.7 | AW8: =LN((AU8+AV8)/AU7) -> 0 | AX8: 45300 | AY8: 42.9 | BC8: =AY8+AY8*AZ8+AY8*BA8-BB8*BA8 -> 42.9 | BE8: =LN((BC8+BD8)/BC7) -> 0 | BF8: 45300 | BG8: 155.2 | BK8: =BG8+BG8*BH8+BG8*BI8-BJ8*BI8 -> 155.2 | BM8: =LN((BK8+BL8)/BK7) -> -0.0019311239
B9: 45301 | C9: 12.4 | G9: =C9+C9*D9+C9*E9-F9*E9 -> 12.4 | I9: =LN((G9+H9)/G8) -> 0 | J9: 45301 | K9: 46.5 | O9: =K9+K9*L9+K9*M9-N9*M9 -> 46.5 | Q9: =LN((O9+P9)/O8) -> 0 | R9: 45301 | S9: 286.6 | W9: =S9+S9*T9+S9*U9-V9*U9 -> 286.6 | Y9: =LN((W9+X9)/W8) -> 0 | Z9: 45301 | AA9: 975 | AE9: =AA9+AA9*AB9+AA9*AC9-AD9*AC9 -> 975 | AG9: =LN((AE9+AF9)/AE8) -> 0.012384059 | AH9: 45301 | AI9: 1217.9 | AM9: =AI9+AI9*AJ9+AI9*AK9-AL9*AK9 -> 1217.9 | AO9: =LN((AM9+AN9)/AM8) -> 0 | AP9: 45301 | AQ9: 1047.7 | AU9: =AQ9+AQ9*AR9+AQ9*AS9-AT9*AS9 -> 1047.7 | AW9: =LN((AU9+AV9)/AU8) -> 0 | AX9: 45301 | AY9: 42.9 | BC9: =AY9+AY9*AZ9+AY9*BA9-BB9*BA9 -> 42.9 | BE9: =LN((BC9+BD9)/BC8) -> 0 | BF9: 45301 | BG9: 155.4 | BK9: =BG9+BG9*BH9+BG9*BI9-BJ9*BI9 -> 155.4 | BM9: =LN((BK9+BL9)/BK8) -> 0.0012878302
B10: 45302 | C10: 12.4 | G10: =C10+C10*D10+C10*E10-F10*E10 -> 12.4 | I10: =LN((G10+H10)/G9) -> 0 | J10: 45302 | K10: 46.5 | O10: =K10+K10*L10+K10*M10-N10*M10 -> 46.5 | Q10: =LN((O10+P10)/O9) -> 0 | R10: 45302 | S10: 286.6 | W10: =S10+S10*T10+S10*U10-V10*U10 -> 286.6 | Y10: =LN((W10+X10)/W9) -> 0 | Z10: 45302 | AA10: 969.1 | AE10: =AA10+AA10*AB10+AA10*AC10-AD10*AC10 -> 969.1 | AG10: =LN((AE10+AF10)/AE9) -> -0.0060696653 | AH10: 45302 | AI10: 1217.9 | AM10: =AI10+AI10*AJ10+AI10*AK10-AL10*AK10 -> 1217.9 | AO10: =LN((AM10+AN10)/AM9) -> 0 | AP10: 45302 | AQ10: 1047.7 | AU10: =AQ10+AQ10*AR10+AQ10*AS10-AT10*AS10 -> 1047.7 | AW10: =LN((AU10+AV10)/AU9) -> 0 | AX10: 45302 | AY10: 42.9 | BC10: =AY10+AY10*AZ10+AY10*BA10-BB10*BA10 -> 42.9 | BE10: =LN((BC10+BD10)/BC9) -> 0 | BF10: 45302 | BG10: 154.8 | BK10: =BG10+BG10*BH10+BG10*BI10-BJ10*BI10 -> 154.8 | BM10: =LN((BK10+BL10)/BK9) -> -0.0038684768
B11: 45305 | C11: 12.4 | G11: =C11+C11*D11+C11*E11-F11*E11 -> 12.4 | I11: =LN((G11+H11)/G10) -> 0 | J11: 45305 | K11: 46.5 | O11: =K11+K11*L11+K11*M11-N11*M11 -> 46.5 | Q11: =LN((O11+P11)/O10) -> 0 | R11: 45305 | S11: 286.6 | W11: =S11+S11*T11+S11*U11-V11*U11 -> 286.6 | Y11: =LN((W11+X11)/W10) -> 0 | Z11: 45305 | AA11: 978.8 | AE11: =AA11+AA11*AB11+AA11*AC11-AD11*AC11 -> 978.8 | AG11: =LN((AE11+AF11)/AE10) -> 0.0099595258 | AH11: 45305 | AI11: 1217.9 | AM11: =AI11+AI11*AJ11+AI11*AK11-AL11*AK11 -> 1217.9 | AO11: =LN((AM11+AN11)/AM10) -> 0 | AP11: 45305 | AQ11: 1047.7 | AU11: =AQ11+AQ11*AR11+AQ11*AS11-AT11*AS11 -> 1047.7 | AW11: =LN((AU11+AV11)/AU10) -> 0 | AX11: 45305 | AY11: 42.9 | BC11: =AY11+AY11*AZ11+AY11*BA11-BB11*BA11 -> 42.9 | BE11: =LN((BC11+BD11)/BC10) -> 0 | BF11: 45305 | BG11: 155.2 | BK11: =BG11+BG11*BH11+BG11*BI11-BJ11*BI11 -> 155.2 | BM11: =LN((BK11+BL11)/BK10) -> 0.0025806466
B12: 45306 | C12: 12.4 | G12: =C12+C12*D12+C12*E12-F12*E12 -> 12.4 | I12: =LN((G12+H12)/G11) -> 0 | J12: 45306 | K12: 46.5 | O12: =K12+K12*L12+K12*M12-N12*M12 -> 46.5 | Q12: =LN((O12+P12)/O11) -> 0 | R12: 45306 | S12: 286.6 | W12: =S12+S12*T12+S12*U12-V12*U12 -> 286.6 | Y12: =LN((W12+X12)/W11) -> 0 | Z12: 45306 | AA12: 983.5 | AE12: =AA12+AA12*AB12+AA12*AC12-AD12*AC12 -> 983.5 | AG12: =LN((AE12+AF12)/AE11) -> 0.0047903063 | AH12: 45306 | AI12: 1217.9 | AM12: =AI12+AI12*AJ12+AI12*AK12-AL12*AK12 -> 1217.9 | AO12: =LN((AM12+AN12)/AM11) -> 0 | AP12: 45306 | AQ12: 1047.7 | AU12: =AQ12+AQ12*AR12+AQ12*AS12-AT12*AS12 -> 1047.7 | AW12: =LN((AU12+AV12)/AU11) -> 0 | AX12: 45306 | AY12: 42.9 | BC12: =AY12+AY12*AZ12+AY12*BA12-BB12*BA12 -> 42.9 | BE12: =LN((BC12+BD12)/BC11) -> 0 | BF12: 45306 | BG12: 156.8 | BK12: =BG12+BG12*BH12+BG12*BI12-BJ12*BI12 -> 156.8 | BM12: =LN((BK12+BL12)/BK11) -> 0.0102565
B13: 45307 | C13: 12.4 | G13: =C13+C13*D13+C13*E13-F13*E13 -> 12.4 | I13: =LN((G13+H13)/G12) -> 0 | J13: 45307 | K13: 46.5 | O13: =K13+K13*L13+K13*M13-N13*M13 -> 46.5 | Q13: =LN((O13+P13)/O12) -> 0 | R13: 45307 | S13: 286.6 | W13: =S13+S13*T13+S13*U13-V13*U13 -> 286.6 | Y13: =LN((W13+X13)/W12) -> 0 | Z13: 45307 | AA13: 983 | AE13: =AA13+AA13*AB13+AA13*AC13-AD13*AC13 -> 983 | AG13: =LN((AE13+AF13)/AE12) -> -0.00050851768 | AH13: 45307 | AI13: 1217.9 | AM13: =AI13+AI13*AJ13+AI13*AK13-AL13*AK13 -> 1217.9 | AO13: =LN((AM13+AN13)/AM12) -> 0 | AP13: 45307 | AQ13: 1047.7 | AU13: =AQ13+AQ13*AR13+AQ13*AS13-AT13*AS13 -> 1047.7 | AW13: =LN((AU13+AV13)/AU12) -> 0 | AX13: 45307 | AY13: 42.9 | BC13: =AY13+AY13*AZ13+AY13*BA13-BB13*BA13 -> 42.9 | BE13: =LN((BC13+BD13)/BC12) -> 0 | BF13: 45307 | BG13: 156.3 | BK13: =BG13+BG13*BH13+BG13*BI13-BJ13*BI13 -> 156.3 | BM13: =LN((BK13+BL13)/BK12) -> -0.0031938705
B14: 45308 | C14: 12.4 | G14: =C14+C14*D14+C14*E14-F14*E14 -> 12.4 | I14: =LN((G14+H14)/G13) -> 0 | J14: 45308 | K14: 46.5 | O14: =K14+K14*L14+K14*M14-N14*M14 -> 46.5 | Q14: =LN((O14+P14)/O13) -> 0 | R14: 45308 | S14: 286.6 | W14: =S14+S14*T14+S14*U14-V14*U14 -> 286.6 | Y14: =LN((W14+X14)/W13) -> 0 | Z14: 45308 | AA14: 994.8 | AE14: =AA14+AA14*AB14+AA14*AC14-AD14*AC14 -> 994.8 | AG14: =LN((AE14+AF14)/AE13) -> 0.011932592 | AH14: 45308 | AI14: 1217.9 | AM14: =AI14+AI14*AJ14+AI14*AK14-AL14*AK14 -> 1217.9 | AO14: =LN((AM14+AN14)/AM13) -> 0 | AP14: 45308 | AQ14: 1047.7 | AU14: =AQ14+AQ14*AR14+AQ14*AS14-AT14*AS14 -> 1047.7 | AW14: =LN((AU14+AV14)/AU13) -> 0 | AX14: 45308 | AY14: 42.9 | BC14: =AY14+AY14*AZ14+AY14*BA14-BB14*BA14 -> 42.9 | BE14: =LN((BC14+BD14)/BC13) -> 0 | BF14: 45308 | BG14: 155.2 | BK14: =BG14+BG14*BH14+BG14*BI14-BJ14*BI14 -> 155.2 | BM14: =LN((BK14+BL14)/BK13) -> -0.0070626297
B15: 45309 | C15: 12.4 | G15: =C15+C15*D15+C15*E15-F15*E15 -> 12.4 | I15: =LN((G15+H15)/G14) -> 0 | J15: 45309 | K15: 46.5 | O15: =K15+K15*L15+K15*M15-N15*M15 -> 46.5 | Q15: =LN((O15+P15)/O14) -> 0 | R15: 45309 | S15: 286.6 | W15: =S15+S15*T15+S15*U15-V15*U15 -> 286.6 | Y15: =LN((W15+X15)/W14) -> 0 | Z15: 45309 | AA15: 987.6 | AE15: =AA15+AA15*AB15+AA15*AC15-AD15*AC15 -> 987.6 | AG15: =LN((AE15+AF15)/AE14) -> -0.0072639545 | AH15: 45309 | AI15: 1217.9 | AM15: =AI15+AI15*AJ15+AI15*AK15-AL15*AK15 -> 1217.9 | AO15: =LN((AM15+AN15)/AM14) -> 0 | AP15: 45309 | AQ15: 1047.7 | AU15: =AQ15+AQ15*AR15+AQ15*AS15-AT15*AS15 -> 1047.7 | AW15: =LN((AU15+AV15)/AU14) -> 0 | AX15: 45309 | AY15: 42.9 | BC15: =AY15+AY15*AZ15+AY15*BA15-BB15*BA15 -> 42.9 | BE15: =LN((BC15+BD15)/BC14) -> 0 | BF15: 45309 | BG15: 154.2 | BK15: =BG15+BG15*BH15+BG15*BI15-BJ15*BI15 -> 154.2 | BM15: =LN((BK15+BL15)/BK14) -> -0.0064641466
B16: 45312 | C16: 11.3 | G16: =C16+C16*D16+C16*E16-F16*E16 -> 11.3 | I16: =LN((G16+H16)/G15) -> -0.092893747 | J16: 45312 | K16: 46.5 | O16: =K16+K16*L16+K16*M16-N16*M16 -> 46.5 | Q16: =LN((O16+P16)/O15) -> 0 | R16: 45312 | S16: 286.6 | W16: =S16+S16*T16+S16*U16-V16*U16 -> 286.6 | Y16: =LN((W16+X16)/W15) -> 0 | Z16: 45312 | AA16: 991 | AE16: =AA16+AA16*AB16+AA16*AC16-AD16*AC16 -> 991 | AG16: =LN((AE16+AF16)/AE15) -> 0.0034367769 | AH16: 45312 | AI16: 1217.9 | AM16: =AI16+AI16*AJ16+AI16*AK16-AL16*AK16 -> 1217.9 | AO16: =LN((AM16+AN16)/AM15) -> 0 | AP16: 45312 | AQ16: 982.3 | AU16: =AQ16+AQ16*AR16+AQ16*AS16-AT16*AS16 -> 982.3 | AW16: =LN((AU16+AV16)/AU15) -> -0.064455804 | AX16: 45312 | AY16: 38.7 | BC16: =AY16+AY16*AZ16+AY16*BA16-BB16*BA16 -> 38.7 | BE16: =LN((BC16+BD16)/BC15) -> -0.10303223 | BF16: 45312 | BG16: 154.6 | BK16: =BG16+BG16*BH16+BG16*BI16-BJ16*BI16 -> 154.6 | BM16: =LN((BK16+BL16)/BK15) -> 0.002590675
B17: 45313 | C17: 11.6 | G17: =C17+C17*D17+C17*E17-F17*E17 -> 11.6 | I17: =LN((G17+H17)/G16) -> 0.026202372 | J17: 45313 | K17: 46.5 | O17: =K17+K17*L17+K17*M17-N17*M17 -> 46.5 | Q17: =LN((O17+P17)/O16) -> 0 | R17: 45313 | S17: 286.6 | W17: =S17+S17*T17+S17*U17-V17*U17 -> 286.6 | Y17: =LN((W17+X17)/W16) -> 0 | Z17: 45313 | AA17: 999.2 | AE17: =AA17+AA17*AB17+AA17*AC17-AD17*AC17 -> 999.2 | AG17: =LN((AE17+AF17)/AE16) -> 0.0082404245 | AH17: 45313 | AI17: 1217.9 | AM17: =AI17+AI17*AJ17+AI17*AK17-AL17*AK17 -> 1217.9 | AO17: =LN((AM17+AN17)/AM16) -> 0 | AP17: 45313 | AQ17: 908.7 | AU17: =AQ17+AQ17*AR17+AQ17*AS17-AT17*AS17 -> 908.7 | AW17: =LN((AU17+AV17)/AU16) -> -0.077881754 | AX17: 45313 | AY17: 36.6 | BC17: =AY17+AY17*AZ17+AY17*BA17-BB17*BA17 -> 36.6 | BE17: =LN((BC17+BD17)/BC16) -> -0.05579136 | BF17: 45313 | BG17: 156.8 | BK17: =BG17+BG17*BH17+BG17*BI17-BJ17*BI17 -> 156.8 | BL17: 6 | BM17: =LN((BK17+BL17)/BK16) -> 0.051681317
B18: 45314 | C18: 12.4 | G18: =C18+C18*D18+C18*E18-F18*E18 -> 12.4 | I18: =LN((G18+H18)/G17) -> 0.066691374 | J18: 45314 | K18: 43.9 | O18: =K18+K18*L18+K18*M18-N18*M18 -> 43.9 | Q18: =LN((O18+P18)/O17) -> -0.057537993 | R18: 45314 | S18: 286.6 | W18: =S18+S18*T18+S18*U18-V18*U18 -> 286.6 | Y18: =LN((W18+X18)/W17) -> 0 | Z18: 45314 | AA18: 1009.6 | AE18: =AA18+AA18*AB18+AA18*AC18-AD18*AC18 -> 1009.6 | AG18: =LN((AE18+AF18)/AE17) -> 0.010354533 | AH18: 45314 | AI18: 1217.9 | AM18: =AI18+AI18*AJ18+AI18*AK18-AL18*AK18 -> 1217.9 | AO18: =LN((AM18+AN18)/AM17) -> 0 | AP18: 45314 | AQ18: 840.6 | AU18: =AQ18+AQ18*AR18+AQ18*AS18-AT18*AS18 -> 840.6 | AW18: =LN((AU18+AV18)/AU17) -> -0.077899084 | AX18: 45314 | AY18: 36.6 | BC18: =AY18+AY18*AZ18+AY18*BA18-BB18*BA18 -> 36.6 | BE18: =LN((BC18+BD18)/BC17) -> 0 | BF18: 45314 | BG18: 155.3 | BK18: =BG18+BG18*BH18+BG18*BI18-BJ18*BI18 -> 155.3 | BM18: =LN((BK18+BL18)/BK17) -> -0.0096123778
B19: 45315 | C19: 12.2 | G19: =C19+C19*D19+C19*E19-F19*E19 -> 12.2 | I19: =LN((G19+H19)/G18) -> -0.016260521 | J19: 45315 | K19: 42.4 | O19: =K19+K19*L19+K19*M19-N19*M19 -> 42.4 | Q19: =LN((O19+P19)/O18) -> -0.034765958 | R19: 45315 | S19: 286.6 | W19: =S19+S19*T19+S19*U19-V19*U19 -> 286.6 | Y19: =LN((W19+X19)/W18) -> 0 | Z19: 45315 | AA19: 1009.4 | AE19: =AA19+AA19*AB19+AA19*AC19-AD19*AC19 -> 1009.4 | AG19: =LN((AE19+AF19)/AE18) -> -0.00019811788 | AH19: 45315 | AI19: 1217.9 | AM19: =AI19+AI19*AJ19+AI19*AK19-AL19*AK19 -> 1217.9 | AO19: =LN((AM19+AN19)/AM18) -> 0 | AP19: 45315 | AQ19: 781.6 | AU19: =AQ19+AQ19*AR19+AQ19*AS19-AT19*AS19 -> 781.6 | AW19: =LN((AU19+AV19)/AU18) -> -0.072772822 | AX19: 45315 | AY19: 35.1 | BC19: =AY19+AY19*AZ19+AY19*BA19-BB19*BA19 -> 35.1 | BE19: =LN((BC19+BD19)/BC18) -> -0.04184711 | BF19: 45315 | BG19: 155 | BK19: =BG19+BG19*BH19+BG19*BI19-BJ19*BI19 -> 155 | BM19: =LN((BK19+BL19)/BK18) -> -0.0019336132
B20: 45316 | C20: 11.9 | G20: =C20+C20*D20+C20*E20-F20*E20 -> 11.9 | I20: =LN((G20+H20)/G19) -> -0.024897552 | J20: 45316 | K20: 40.6 | O20: =K20+K20*L20+K20*M20-N20*M20 -> 40.6 | Q20: =LN((O20+P20)/O19) -> -0.043380296 | R20: 45316 | S20: 286.6 | W20: =S20+S20*T20+S20*U20-V20*U20 -> 286.6 | Y20: =LN((W20+X20)/W19) -> 0 | Z20: 45316 | AA20: 1007.7 | AE20: =AA20+AA20*AB20+AA20*AC20-AD20*AC20 -> 1007.7 | AG20: =LN((AE20+AF20)/AE19) -> -0.0016855886 | AH20: 45316 | AI20: 1217.9 | AM20: =AI20+AI20*AJ20+AI20*AK20-AL20*AK20 -> 1217.9 | AO20: =LN((AM20+AN20)/AM19) -> 0 | AP20: 45316 | AQ20: 764.9 | AU20: =AQ20+AQ20*AR20+AQ20*AS20-AT20*AS20 -> 764.9 | AW20: =LN((AU20+AV20)/AU19) -> -0.021597994 | AX20: 45316 | AY20: 35.1 | BC20: =AY20+AY20*AZ20+AY20*BA20-BB20*BA20 -> 35.1 | BE20: =LN((BC20+BD20)/BC19) -> 0 | BF20: 45316 | BG20: 154.7 | BK20: =BG20+BG20*BH20+BG20*BI20-BJ20*BI20 -> 154.7 | BM20: =LN((BK20+BL20)/BK19) -> -0.0019373593
B21: 45319 | C21: 11.9 | G21: =C21+C21*D21+C21*E21-F21*E21 -> 11.9 | I21: =LN((G21+H21)/G20) -> 0 | J21: 45319 | K21: 38.4 | O21: =K21+K21*L21+K21*M21-N21*M21 -> 38.4 | Q21: =LN((O21+P21)/O20) -> -0.055710607 | R21: 45319 | S21: 286.6 | W21: =S21+S21*T21+S21*U21-V21*U21 -> 286.6 | Y21: =LN((W21+X21)/W20) -> 0 | Z21: 45319 | AA21: 1000.4 | AE21: =AA21+AA21*AB21+AA21*AC21-AD21*AC21 -> 1000.4 | AG21: =LN((AE21+AF21)/AE20) -> -0.0072705863 | AH21: 45319 | AI21: 1217.9 | AM21: =AI21+AI21*AJ21+AI21*AK21-AL21*AK21 -> 1217.9 | AO21: =LN((AM21+AN21)/AM20) -> 0 | AP21: 45319 | AQ21: 713.3 | AU21: =AQ21+AQ21*AR21+AQ21*AS21-AT21*AS21 -> 713.3 | AW21: =LN((AU21+AV21)/AU20) -> -0.069843017 | AX21: 45319 | AY21: 32.6 | BC21: =AY21+AY21*AZ21+AY21*BA21-BB21*BA21 -> 32.6 | BE21: =LN((BC21+BD21)/BC20) -> -0.073888842 | BF21: 45319 | BG21: 155.1 | BK21: =BG21+BG21*BH21+BG21*BI21-BJ21*BI21 -> 155.1 | BM21: =LN((BK21+BL21)/BK20) -> 0.0025823126
B22: 45320 | C22: 12.1 | G22: =C22+C22*D22+C22*E22-F22*E22 -> 12.1 | I22: =LN((G22+H22)/G21) -> 0.016667052 | J22: 45320 | K22: 38 | O22: =K22+K22*L22+K22*M22-N22*M22 -> 38 | Q22: =LN((O22+P22)/O21) -> -0.0104713 | R22: 45320 | S22: 286.6 | W22: =S22+S22*T22+S22*U22-V22*U22 -> 286.6 | Y22: =LN((W22+X22)/W21) -> 0 | Z22: 45320 | AA22: 1000.4 | AE22: =AA22+AA22*AB22+AA22*AC22-AD22*AC22 -> 1000.4 | AG22: =LN((AE22+AF22)/AE21) -> 0 | AH22: 45320 | AI22: 1217.9 | AM22: =AI22+AI22*AJ22+AI22*AK22-AL22*AK22 -> 1217.9 | AO22: =LN((AM22+AN22)/AM21) -> 0 | AP22: 45320 | AQ22: 702.2 | AU22: =AQ22+AQ22*AR22+AQ22*AS22-AT22*AS22 -> 702.2 | AW22: =LN((AU22+AV22)/AU21) -> -0.015683826 | AX22: 45320 | AY22: 33 | BC22: =AY22+AY22*AZ22+AY22*BA22-BB22*BA22 -> 33 | BE22: =LN((BC22+BD22)/BC21) -> 0.012195273 | BF22: 45320 | BG22: 153.8 | BK22: =BG22+BG22*BH22+BG22*BI22-BJ22*BI22 -> 153.8 | BM22: =LN((BK22+BL22)/BK21) -> -0.0084170131
B23: 45321 | C23: 12 | G23: =C23+C23*D23+C23*E23-F23*E23 -> 12 | I23: =LN((G23+H23)/G22) -> -0.0082988028 | J23: 45321 | K23: 38.9 | O23: =K23+K23*L23+K23*M23-N23*M23 -> 38.9 | Q23: =LN((O23+P23)/O22) -> 0.023408091 | R23: 45321 | S23: 286.6 | W23: =S23+S23*T23+S23*U23-V23*U23 -> 286.6 | Y23: =LN((W23+X23)/W22) -> 0 | Z23: 45321 | AA23: 992 | AE23: =AA23+AA23*AB23+AA23*AC23-AD23*AC23 -> 992 | AG23: =LN((AE23+AF23)/AE22) -> -0.0084320917 | AH23: 45321 | AI23: 1217.9 | AM23: =AI23+AI23*AJ23+AI23*AK23-AL23*AK23 -> 1217.9 | AO23: =LN((AM23+AN23)/AM22) -> 0 | AP23: 45321 | AQ23: 754.8 | AU23: =AQ23+AQ23*AR23+AQ23*AS23-AT23*AS23 -> 754.8 | AW23: =LN((AU23+AV23)/AU22) -> 0.07223455 | AX23: 45321 | AY23: 34.1 | BC23: =AY23+AY23*AZ23+AY23*BA23-BB23*BA23 -> 34.1 | BE23: =LN((BC23+BD23)/BC22) -> 0.032789823 | BF23: 45321 | BG23: 154 | BK23: =BG23+BG23*BH23+BG23*BI23-BJ23*BI23 -> 154 | BM23: =LN((BK23+BL23)/BK22) -> 0.0012995453
B24: 45322 | C24: 11.9 | G24: =C24+C24*D24+C24*E24-F24*E24 -> 11.9 | I24: =LN((G24+H24)/G23) -> -0.0083682497 | J24: 45322 | K24: 38.7 | O24: =K24+K24*L24+K24*M24-N24*M24 -> 38.7 | Q24: =LN((O24+P24)/O23) -> -0.0051546506 | R24: 45322 | S24: 286.6 | W24: =S24+S24*T24+S24*U24-V24*U24 -> 286.6 | Y24: =LN((W24+X24)/W23) -> 0 | Z24: 45322 | AA24: 986.2 | AE24: =AA24+AA24*AB24+AA24*AC24-AD24*AC24 -> 986.2 | AG24: =LN((AE24+AF24)/AE23) -> -0.0058639335 | AH24: 45322 | AI24: 1217.9 | AM24: =AI24+AI24*AJ24+AI24*AK24-AL24*AK24 -> 1217.9 | AO24: =LN((AM24+AN24)/AM23) -> 0 | AP24: 45322 | AQ24: 752.8 | AU24: =AQ24+AQ24*AR24+AQ24*AS24-AT24*AS24 -> 752.8 | AW24: =LN((AU24+AV24)/AU23) -> -0.0026532252 | AX24: 45322 | AY24: 33.5 | BC24: =AY24+AY24*AZ24+AY24*BA24-BB24*BA24 -> 33.5 | BE24: =LN((BC24+BD24)/BC23) -> -0.017751945 | BF24: 45322 | BG24: 152.7 | BK24: =BG24+BG24*BH24+BG24*BI24-BJ24*BI24 -> 152.7 | BM24: =LN((BK24+BL24)/BK23) -> -0.0084773902
B25: 45323 | C25: 12 | G25: =C25+C25*D25+C25*E25-F25*E25 -> 12 | I25: =LN((G25+H25)/G24) -> 0.0083682497 | J25: 45323 | K25: 41.4 | O25: =K25+K25*L25+K25*M25-N25*M25 -> 41.4 | Q25: =LN((O25+P25)/O24) -> 0.067441281 | R25: 45323 | S25: 286.6 | W25: =S25+S25*T25+S25*U25-V25*U25 -> 286.6 | Y25: =LN((W25+X25)/W24) -> 0 | Z25: 45323 | AA25: 991.9 | AE25: =AA25+AA25*AB25+AA25*AC25-AD25*AC25 -> 991.9 | AG25: =LN((AE25+AF25)/AE24) -> 0.005763122 | AH25: 45323 | AI25: 1217.9 | AM25: =AI25+AI25*AJ25+AI25*AK25-AL25*AK25 -> 1217.9 | AO25: =LN((AM25+AN25)/AM24) -> 0 | AP25: 45323 | AQ25: 757.3 | AU25: =AQ25+AQ25*AR25+AQ25*AS25-AT25*AS25 -> 757.3 | AW25: =LN((AU25+AV25)/AU24) -> 0.0059598878 | AX25: 45323 | AY25: 34.9 | BC25: =AY25+AY25*AZ25+AY25*BA25-BB25*BA25 -> 34.9 | BE25: =LN((BC25+BD25)/BC24) -> 0.04094139 | BF25: 45323 | BG25: 152 | BK25: =BG25+BG25*BH25+BG25*BI25-BJ25*BI25 -> 152 | BM25: =LN((BK25+BL25)/BK24) -> -0.0045946914
B26: 45326 | C26: 12.1 | G26: =C26+C26*D26+C26*E26-F26*E26 -> 12.1 | I26: =LN((G26+H26)/G25) -> 0.0082988028 | J26: 45326 | K26: 42.3 | O26: =K26+K26*L26+K26*M26-N26*M26 -> 42.3 | Q26: =LN((O26+P26)/O25) -> 0.021506205 | R26: 45326 | S26: 286.6 | W26: =S26+S26*T26+S26*U26-V26*U26 -> 286.6 | Y26: =LN((W26+X26)/W25) -> 0 | Z26: 45326 | AA26: 999.5 | AE26: =AA26+AA26*AB26+AA26*AC26-AD26*AC26 -> 999.5 | AG26: =LN((AE26+AF26)/AE25) -> 0.0076328582 | AH26: 45326 | AI26: 1217.9 | AM26: =AI26+AI26*AJ26+AI26*AK26-AL26*AK26 -> 1217.9 | AO26: =LN((AM26+AN26)/AM25) -> 0 | AP26: 45326 | AQ26: 801.4 | AU26: =AQ26+AQ26*AR26+AQ26*AS26-AT26*AS26 -> 801.4 | AW26: =LN((AU26+AV26)/AU25) -> 0.056600722 | AX26: 45326 | AY26: 36.8 | BC26: =AY26+AY26*AZ26+AY26*BA26-BB26*BA26 -> 36.8 | BE26: =LN((BC26+BD26)/BC25) -> 0.053011016 | BF26: 45326 | BG26: 152.8 | BK26: =BG26+BG26*BH26+BG26*BI26-BJ26*BI26 -> 152.8 | BM26: =LN((BK26+BL26)/BK25) -> 0.0052493559
B27: 45327 | C27: 12.4 | G27: =C27+C27*D27+C27*E27-F27*E27 -> 12.4 | I27: =LN((G27+H27)/G26) -> 0.02449102 | J27: 45327 | K27: 43.5 | O27: =K27+K27*L27+K27*M27-N27*M27 -> 43.5 | Q27: =LN((O27+P27)/O26) -> 0.027973852 | R27: 45327 | S27: 286.6 | W27: =S27+S27*T27+S27*U27-V27*U27 -> 286.6 | Y27: =LN((W27+X27)/W26) -> 0 | Z27: 45327 | AA27: 1001.7 | AE27: =AA27+AA27*AB27+AA27*AC27-AD27*AC27 -> 1001.7 | AG27: =LN((AE27+AF27)/AE26) -> 0.0021986817 | AH27: 45327 | AI27: 1217.9 | AM27: =AI27+AI27*AJ27+AI27*AK27-AL27*AK27 -> 1217.9 | AO27: =LN((AM27+AN27)/AM26) -> 0 | AP27: 45327 | AQ27: 844.9 | AU27: =AQ27+AQ27*AR27+AQ27*AS27-AT27*AS27 -> 844.9 | AW27: =LN((AU27+AV27)/AU26) -> 0.052858079 | AX27: 45327 | AY27: 36.7 | BC27: =AY27+AY27*AZ27+AY27*BA27-BB27*BA27 -> 36.7 | BE27: =LN((BC27+BD27)/BC26) -> -0.0027210901 | BF27: 45327 | BG27: 153.4 | BK27: =BG27+BG27*BH27+BG27*BI27-BJ27*BI27 -> 153.4 | BM27: =LN((BK27+BL27)/BK26) -> 0.0039190122
B28: 45328 | C28: 12.2 | G28: =C28+C28*D28+C28*E28-F28*E28 -> 12.2 | I28: =LN((G28+H28)/G27) -> -0.016260521 | J28: 45328 | K28: 42.7 | O28: =K28+K28*L28+K28*M28-N28*M28 -> 42.7 | Q28: =LN((O28+P28)/O27) -> -0.018562018 | R28: 45328 | S28: 286.6 | W28: =S28+S28*T28+S28*U28-V28*U28 -> 286.6 | Y28: =LN((W28+X28)/W27) -> 0 | Z28: 45328 | AA28: 999.8 | AE28: =AA28+AA28*AB28+AA28*AC28-AD28*AC28 -> 999.8 | AG28: =LN((AE28+AF28)/AE27) -> -0.0018985766 | AH28: 45328 | AI28: 1217.9 | AM28: =AI28+AI28*AJ28+AI28*AK28-AL28*AK28 -> 1217.9 | AO28: =LN((AM28+AN28)/AM27) -> 0 | AP28: 45328 | AQ28: 843.5 | AU28: =AQ28+AQ28*AR28+AQ28*AS28-AT28*AS28 -> 843.5 | AW28: =LN((AU28+AV28)/AU27) -> -0.0016583752 | AX28: 45328 | AY28: 37.3 | BC28: =AY28+AY28*AZ28+AY28*BA28-BB28*BA28 -> 37.3 | BE28: =LN((BC28+BD28)/BC27) -> 0.016216572 | BF28: 45328 | BG28: 152.4 | BK28: =BG28+BG28*BH28+BG28*BI28-BJ28*BI28 -> 152.4 | BM28: =LN((BK28+BL28)/BK27) -> -0.0065402457
B29: 45329 | C29: 12.2 | G29: =C29+C29*D29+C29*E29-F29*E29 -> 12.2 | I29: =LN((G29+H29)/G28) -> 0 | J29: 45329 | K29: 42.6 | O29: =K29+K29*L29+K29*M29-N29*M29 -> 42.6 | Q29: =LN((O29+P29)/O28) -> -0.002344667 | R29: 45329 | S29: 286.6 | W29: =S29+S29*T29+S29*U29-V29*U29 -> 286.6 | Y29: =LN((W29+X29)/W28) -> 0 | Z29: 45329 | AA29: 989.8 | AE29: =AA29+AA29*AB29+AA29*AC29-AD29*AC29 -> 989.8 | AG29: =LN((AE29+AF29)/AE28) -> -0.010052356 | AH29: 45329 | AI29: 1141.8 | AM29: =AI29+AI29*AJ29+AI29*AK29-AL29*AK29 -> 1141.8 | AO29: =LN((AM29+AN29)/AM28) -> -0.0645221 | AP29: 45329 | AQ29: 822.5 | AU29: =AQ29+AQ29*AR29+AQ29*AS29-AT29*AS29 -> 822.5 | AW29: =LN((AU29+AV29)/AU28) -> -0.025211419 | AX29: 45329 | AY29: 41 | BC29: =AY29+AY29*AZ29+AY29*BA29-BB29*BA29 -> 41 | BE29: =LN((BC29+BD29)/BC28) -> 0.09457874 | BF29: 45329 | BG29: 152 | BK29: =BG29+BG29*BH29+BG29*BI29-BJ29*BI29 -> 152 | BM29: =LN((BK29+BL29)/BK28) -> -0.0026281224
... B36: 45340 | C36: 12.7 | G36: =C36+C36*D36+C36*E36-F36*E36 -> 12.7 | I36: =LN((G36+H36)/G35) -> 0.0079051795 | J36: 45340 | K36: 41 | O36: =K36+K36*L36+K36*M36-N36*M36 -> 41 | Q36: =LN((O36+P36)/O35) -> -0.019324273 | R36: 45340 | S36: 286.6 | W36: =S36+S36*T36+S36*U36-V36*U36 -> 286.6 | Y36: =LN((W36+X36)/W35) -> 0 | Z36: 45340 | AA36: 1001.3 | AE36: =AA36+AA36*AB36+AA36*AC36-AD36*AC36 -> 1001.3 | AG36: =LN((AE36+AF36)/AE35) -> 0.00089923571 | AH36: 45340 | AI36: 977.9 | AM36: =AI36+AI36*AJ36+AI36*AK36-AL36*AK36 -> 977.9 | AO36: =LN((AM36+AN36)/AM35) -> -0.0071326979 | AP36: 45340 | AQ36: 778 | AU36: =AQ36+AQ36*AR36+AQ36*AS36-AT36*AS36 -> 778 | AW36: =LN((AU36+AV36)/AU35) -> 0.0015436072 | AX36: 45340 | AY36: 38.1 | BC36: =AY36+AY36*AZ36+AY36*BA36-BB36*BA36 -> 38.1 | BE36: =LN((BC36+BD36)/BC35) -> 0.015873349 | BF36: 45340 | BG36: 150.5 | BK36: =BG36+BG36*BH36+BG36*BI36-BJ36*BI36 -> 150.5 | BM36: =LN((BK36+BL36)/BK35) -> 0.0019953449
B37: 45341 | C37: 13 | G37: =C37+C37*D37+C37*E37-F37*E37 -> 13 | I37: =LN((G37+H37)/G36) -> 0.023347364 | J37: 45341 | K37: 40.6 | O37: =K37+K37*L37+K37*M37-N37*M37 -> 40.6 | Q37: =LN((O37+P37)/O36) -> -0.0098040001 | R37: 45341 | S37: 286.6 | W37: =S37+S37*T37+S37*U37-V37*U37 -> 286.6 | Y37: =LN((W37+X37)/W36) -> 0 | Z37: 45341 | AA37: 1000 | AE37: =AA37+AA37*AB37+AA37*AC37-AD37*AC37 -> 1000 | AG37: =LN((AE37+AF37)/AE36) -> -0.0012991557 | AH37: 45341 | AI37: 977.1 | AM37: =AI37+AI37*AJ37+AI37*AK37-AL37*AK37 -> 977.1 | AO37: =LN((AM37+AN37)/AM36) -> -0.00081841437 | AP37: 45341 | AQ37: 760.9 | AU37: =AQ37+AQ37*AR37+AQ37*AS37-AT37*AS37 -> 760.9 | AW37: =LN((AU37+AV37)/AU36) -> -0.022224581 | AX37: 45341 | AY37: 38.1 | BC37: =AY37+AY37*AZ37+AY37*BA37-BB37*BA37 -> 38.1 | BD37: 1 | BE37: =LN((BC37+BD37)/BC36) -> 0.025908185 | BF37: 45341 | BG37: 150.2 | BK37: =BG37+BG37*BH37+BG37*BI37-BJ37*BI37 -> 150.2 | BM37: =LN((BK37+BL37)/BK36) -> -0.0019953449
B38: 45342 | C38: 13.1 | G38: =C38+C38*D38+C38*E38-F38*E38 -> 13.1 | I38: =LN((G38+H38)/G37) -> 0.0076628727 | J38: 45342 | K38: 40.6 | O38: =K38+K38*L38+K38*M38-N38*M38 -> 40.6 | Q38: =LN((O38+P38)/O37) -> 0 | R38: 45342 | S38: 286.6 | W38: =S38+S38*T38+S38*U38-V38*U38 -> 286.6 | Y38: =LN((W38+X38)/W37) -> 0 | Z38: 45342 | AA38: 988 | AE38: =AA38+AA38*AB38+AA38*AC38-AD38*AC38 -> 988 | AG38: =LN((AE38+AF38)/AE37) -> -0.012072581 | AH38: 45342 | AI38: 969.3 | AM38: =AI38+AI38*AJ38+AI38*AK38-AL38*AK38 -> 969.3 | AO38: =LN((AM38+AN38)/AM37) -> -0.0080148395 | AP38: 45342 | AQ38: 761.3 | AU38: =AQ38+AQ38*AR38+AQ38*AS38-AT38*AS38 -> 761.3 | AW38: =LN((AU38+AV38)/AU37) -> 0.00052555513 | AX38: 45342 | AY38: 37.3 | BC38: =AY38+AY38*AZ38+AY38*BA38-BB38*BA38 -> 37.3 | BE38: =LN((BC38+BD38)/BC37) -> -0.021220955 | BF38: 45342 | BG38: 150 | BK38: =BG38+BG38*BH38+BG38*BI38-BJ38*BI38 -> 150 | BM38: =LN((BK38+BL38)/BK37) -> -0.0013324452
B39: 45344 | C39: 13.1 | G39: =C39+C39*D39+C39*E39-F39*E39 -> 13.1 | I39: =LN((G39+H39)/G38) -> 0 | J39: 45344 | K39: 40.2 | O39: =K39+K39*L39+K39*M39-N39*M39 -> 40.2 | Q39: =LN((O39+P39)/O38) -> -0.009901071 | R39: 45344 | S39: 286.6 | W39: =S39+S39*T39+S39*U39-V39*U39 -> 286.6 | Y39: =LN((W39+X39)/W38) -> 0 | Z39: 45344 | AA39: 987.6 | AE39: =AA39+AA39*AB39+AA39*AC39-AD39*AC39 -> 987.6 | AG39: =LN((AE39+AF39)/AE38) -> -0.00040494028 | AH39: 45344 | AI39: 967.4 | AM39: =AI39+AI39*AJ39+AI39*AK39-AL39*AK39 -> 967.4 | AO39: =LN((AM39+AN39)/AM38) -> -0.0019621011 | AP39: 45344 | AQ39: 760.8 | AU39: =AQ39+AQ39*AR39+AQ39*AS39-AT39*AS39 -> 760.8 | AW39: =LN((AU39+AV39)/AU38) -> -0.00065698708 | AX39: 45344 | AY39: 37 | BC39: =AY39+AY39*AZ39+AY39*BA39-BB39*BA39 -> 37 | BE39: =LN((BC39+BD39)/BC38) -> -0.008075414 | BF39: 45344 | BG39: 149.6 | BK39: =BG39+BG39*BH39+BG39*BI39-BJ39*BI39 -> 149.6 | BM39: =LN((BK39+BL39)/BK38) -> -0.0026702286
B40: 45347 | C40: 13 | G40: =C40+C40*D40+C40*E40-F40*E40 -> 13 | I40: =LN((G40+H40)/G39) -> -0.0076628727 | J40: 45347 | K40: 40 | O40: =K40+K40*L40+K40*M40-N40*M40 -> 40 | Q40: =LN((O40+P40)/O39) -> -0.0049875415 | R40: 45347 | S40: 286.6 | W40: =S40+S40*T40+S40*U40-V40*U40 -> 286.6 | Y40: =LN((W40+X40)/W39) -> 0 | Z40: 45347 | AA40: 979.8 | AE40: =AA40+AA40*AB40+AA40*AC40-AD40*AC40 -> 979.8 | AG40: =LN((AE40+AF40)/AE39) -> -0.0079292883 | AH40: 45347 | AI40: 958.8 | AM40: =AI40+AI40*AJ40+AI40*AK40-AL40*AK40 -> 958.8 | AO40: =LN((AM40+AN40)/AM39) -> -0.0089295578 | AP40: 45347 | AQ40: 753 | AU40: =AQ40+AQ40*AR40+AQ40*AS40-AT40*AS40 -> 753 | AW40: =LN((AU40+AV40)/AU39) -> -0.010305283 | AX40: 45347 | AY40: 36.7 | BC40: =AY40+AY40*AZ40+AY40*BA40-BB40*BA40 -> 36.7 | BE40: =LN((BC40+BD40)/BC39) -> -0.0081411576 | BF40: 45347 | BG40: 149.6 | BK40: =BG40+BG40*BH40+BG40*BI40-BJ40*BI40 -> 149.6 | BM40: =LN((BK40+BL40)/BK39) -> 0
B41: 45349 | C41: 13 | G41: =C41+C41*D41+C41*E41-F41*E41 -> 13 | I41: =LN((G41+H41)/G40) -> 0 | J41: 45349 | K41: 40.1 | O41: =K41+K41*L41+K41*M41-N41*M41 -> 40.1 | Q41: =LN((O41+P41)/O40) -> 0.0024968802 | R41: 45349 | S41: 286.6 | W41: =S41+S41*T41+S41*U41-V41*U41 -> 286.6 | Y41: =LN((W41+X41)/W40) -> 0 | Z41: 45349 | AA41: 999.8 | AE41: =AA41+AA41*AB41+AA41*AC41-AD41*AC41 -> 999.8 | AG41: =LN((AE41+AF41)/AE40) -> 0.02020679 | AH41: 45349 | AI41: 945.6 | AM41: =AI41+AI41*AJ41+AI41*AK41-AL41*AK41 -> 945.6 | AO41: =LN((AM41+AN41)/AM40) -> -0.013862856 | AP41: 45349 | AQ41: 750.3 | AU41: =AQ41+AQ41*AR41+AQ41*AS41-AT41*AS41 -> 750.3 | AW41: =LN((AU41+AV41)/AU40) -> -0.0035921012 | AX41: 45349 | AY41: 36.6 | BC41: =AY41+AY41*AZ41+AY41*BA41-BB41*BA41 -> 36.6 | BE41: =LN((BC41+BD41)/BC40) -> -0.0027285147 | BF41: 45349 | BG41: 146.2 | BK41: =BG41+BG41*BH41+BG41*BI41-BJ41*BI41 -> 146.2 | BM41: =LN((BK41+BL41)/BK40) -> -0.022989518
B42: 45350 | C42: 13 | G42: =C42+C42*D42+C42*E42-F42*E42 -> 13 | I42: =LN((G42+H42)/G41) -> 0 | J42: 45350 | K42: 40 | O42: =K42+K42*L42+K42*M42-N42*M42 -> 40 | Q42: =LN((O42+P42)/O41) -> -0.0024968802 | R42: 45350 | S42: 286.6 | W42: =S42+S42*T42+S42*U42-V42*U42 -> 286.6 | Y42: =LN((W42+X42)/W41) -> 0 | Z42: 45350 | AA42: 994.3 | AE42: =AA42+AA42*AB42+AA42*AC42-AD42*AC42 -> 994.3 | AG42: =LN((AE42+AF42)/AE41) -> -0.005516287 | AH42: 45350 | AI42: 951.8 | AM42: =AI42+AI42*AJ42+AI42*AK42-AL42*AK42 -> 951.8 | AO42: =LN((AM42+AN42)/AM41) -> 0.006535282 | AP42: 45350 | AQ42: 748.2 | AU42: =AQ42+AQ42*AR42+AQ42*AS42-AT42*AS42 -> 748.2 | AW42: =LN((AU42+AV42)/AU41) -> -0.0028028046 | AX42: 45350 | AY42: 36.9 | BC42: =AY42+AY42*AZ42+AY42*BA42-BB42*BA42 -> 36.9 | BE42: =LN((BC42+BD42)/BC41) -> 0.0081633106 | BF42: 45350 | BG42: 145.8 | BK42: =BG42+BG42*BH42+BG42*BI42-BJ42*BI42 -> 145.8 | BM42: =LN((BK42+BL42)/BK41) -> -0.0027397277
B43: 45351 | C43: 13.1 | G43: =C43+C43*D43+C43*E43-F43*E43 -> 13.1 | I43: =LN((G43+H43)/G42) -> 0.0076628727 | J43: 45351 | K43: 39.8 | O43: =K43+K43*L43+K43*M43-N43*M43 -> 39.8 | Q43: =LN((O43+P43)/O42) -> -0.0050125418 | R43: 45351 | S43: 286.6 | W43: =S43+S43*T43+S43*U43-V43*U43 -> 286.6 | Y43: =LN((W43+X43)/W42) -> 0 | Z43: 45351 | AA43: 980.5 | AE43: =AA43+AA43*AB43+AA43*AC43-AD43*AC43 -> 980.5 | AG43: =LN((AE43+AF43)/AE42) -> -0.013976326 | AH43: 45351 | AI43: 943.6 | AM43: =AI43+AI43*AJ43+AI43*AK43-AL43*AK43 -> 943.6 | AO43: =LN((AM43+AN43)/AM42) -> -0.0086525812 | AP43: 45351 | AQ43: 745.5 | AU43: =AQ43+AQ43*AR43+AQ43*AS43-AT43*AS43 -> 745.5 | AW43: =LN((AU43+AV43)/AU42) -> -0.0036151877 | AX43: 45351 | AY43: 36.7 | BC43: =AY43+AY43*AZ43+AY43*BA43-BB43*BA43 -> 36.7 | BE43: =LN((BC43+BD43)/BC42) -> -0.005434796 | BF43: 45351 | BG43: 145.2 | BK43: =BG43+BG43*BH43+BG43*BI43-BJ43*BI43 -> 145.2 | BM43: =LN((BK43+BL43)/BK42) -> -0.0041237172
B44: 45354 | C44: 12.9 | G44: =C44+C44*D44+C44*E44-F44*E44 -> 12.9 | I44: =LN((G44+H44)/G43) -> -0.015384919 | J44: 45354 | K44: 39.4 | O44: =K44+K44*L44+K44*M44-N44*M44 -> 39.4 | Q44: =LN((O44+P44)/O43) -> -0.010101096 | R44: 45354 | S44: 261.6 | W44: =S44+S44*T44+S44*U44-V44*U44 -> 261.6 | X44: 12.5 | Y44: =LN((W44+X44)/W43) -> -0.044594512 | Z44: 45354 | AA44: 978.1 | AE44: =AA44+AA44*AB44+AA44*AC44-AD44*AC44 -> 978.1 | AG44: =LN((AE44+AF44)/AE43) -> -0.0024507313 | AH44: 45354 | AI44: 945.6 | AM44: =AI44+AI44*AJ44+AI44*AK44-AL44*AK44 -> 945.6 | AO44: =LN((AM44+AN44)/AM43) -> 0.0021172991 | AP44: 45354 | AQ44: 761.2 | AU44: =AQ44+AQ44*AR44+AQ44*AS44-AT44*AS44 -> 761.2 | AW44: =LN((AU44+AV44)/AU43) -> 0.020841001 | AX44: 45354 | AY44: 36.7 | BC44: =AY44+AY44*AZ44+AY44*BA44-BB44*BA44 -> 36.7 | BE44: =LN((BC44+BD44)/BC43) -> 0 | BF44: 45354 | BG44: 144.3 | BK44: =BG44+BG44*BH44+BG44*BI44-BJ44*BI44 -> 144.3 | BM44: =LN((BK44+BL44)/BK43) -> -0.0062176366
B45: 45355 | C45: 13 | G45: =C45+C45*D45+C45*E45-F45*E45 -> 13 | I45: =LN((G45+H45)/G44) -> 0.0077220461 | J45: 45355 | K45: 39 | O45: =K45+K45*L45+K45*M45-N45*M45 -> 39 | Q45: =LN((O45+P45)/O44) -> -0.01020417 | R45: 45355 | S45: 257.2 | W45: =S45+S45*T45+S45*U45-V45*U45 -> 257.2 | Y45: =LN((W45+X45)/W44) -> -0.016962627 | Z45: 45355 | AA45: 986.9 | AE45: =AA45+AA45*AB45+AA45*AC45-AD45*AC45 -> 986.9 | AG45: =LN((AE45+AF45)/AE44) -> 0.0089568029 | AH45: 45355 | AI45: 940.2 | AM45: =AI45+AI45*AJ45+AI45*AK45-AL45*AK45 -> 940.2 | AO45: =LN((AM45+AN45)/AM44) -> -0.0057270281 | AP45: 45355 | AQ45: 751.4 | AU45: =AQ45+AQ45*AR45+AQ45*AS45-AT45*AS45 -> 751.4 | AW45: =LN((AU45+AV45)/AU44) -> -0.012958002 | AX45: 45355 | AY45: 36 | BC45: =AY45+AY45*AZ45+AY45*BA45-BB45*BA45 -> 36 | BE45: =LN((BC45+BD45)/BC44) -> -0.019257817 | BF45: 45355 | BG45: 146.1 | BK45: =BG45+BG45*BH45+BG45*BI45-BJ45*BI45 -> 146.1 | BM45: =LN((BK45+BL45)/BK44) -> 0.012396853
B46: 45356 | C46: 12.7 | G46: =C46+C46*D46+C46*E46-F46*E46 -> 12.7 | I46: =LN((G46+H46)/G45) -> -0.023347364 | J46: 45356 | K46: 39 | O46: =K46+K46*L46+K46*M46-N46*M46 -> 39 | Q46: =LN((O46+P46)/O45) -> 0 | R46: 45356 | S46: 252.6 | W46: =S46+S46*T46+S46*U46-V46*U46 -> 252.6 | Y46: =LN((W46+X46)/W45) -> -0.018046782 | Z46: 45356 | AA46: 989.5 | AE46: =AA46+AA46*AB46+AA46*AC46-AD46*AC46 -> 989.5 | AG46: =LN((AE46+AF46)/AE45) -> 0.0026310479 | AH46: 45356 | AI46: 932.2 | AM46: =AI46+AI46*AJ46+AI46*AK46-AL46*AK46 -> 932.2 | AO46: =LN((AM46+AN46)/AM45) -> -0.0085452347 | AP46: 45356 | AQ46: 741.8 | AU46: =AQ46+AQ46*AR46+AQ46*AS46-AT46*AS46 -> 741.8 | AW46: =LN((AU46+AV46)/AU45) -> -0.012858468 | AX46: 45356 | AY46: 35.8 | BC46: =AY46+AY46*AZ46+AY46*BA46-BB46*BA46 -> 35.8 | BE46: =LN((BC46+BD46)/BC45) -> -0.005571045 | BF46: 45356 | BG46: 151.2 | BK46: =BG46+BG46*BH46+BG46*BI46-BJ46*BI46 -> 151.2 | BM46: =LN((BK46+BL46)/BK45) -> 0.034312145
B47: 45357 | C47: 12.9 | G47: =C47+C47*D47+C47*E47-F47*E47 -> 12.9 | I47: =LN((G47+H47)/G46) -> 0.015625318 | J47: 45357 | K47: 39.1 | O47: =K47+K47*L47+K47*M47-N47*M47 -> 39.1 | Q47: =LN((O47+P47)/O46) -> 0.0025608209 | R47: 45357 | S47: 256.7 | W47: =S47+S47*T47+S47*U47-V47*U47 -> 256.7 | Y47: =LN((W47+X47)/W46) -> 0.016100878 | Z47: 45357 | AA47: 983.1 | AE47: =AA47+AA47*AB47+AA47*AC47-AD47*AC47 -> 983.1 | AG47: =LN((AE47+AF47)/AE46) -> -0.0064889207 | AH47: 45357 | AI47: 933.6 | AM47: =AI47+AI47*AJ47+AI47*AK47-AL47*AK47 -> 933.6 | AO47: =LN((AM47+AN47)/AM46) -> 0.001500697 | AP47: 45357 | AQ47: 728.8 | AU47: =AQ47+AQ47*AR47+AQ47*AS47-AT47*AS47 -> 728.8 | AW47: =LN((AU47+AV47)/AU46) -> -0.017680319 | AX47: 45357 | AY47: 35.7 | BC47: =AY47+AY47*AZ47+AY47*BA47-BB47*BA47 -> 35.7 | BE47: =LN((BC47+BD47)/BC46) -> -0.0027972046 | BF47: 45357 | BG47: 149.9 | BK47: =BG47+BG47*BH47+BG47*BI47-BJ47*BI47 -> 149.9 | BM47: =LN((BK47+BL47)/BK46) -> -0.0086350586
B48: 45358 | C48: 12.7 | G48: =C48+C48*D48+C48*E48-F48*E48 -> 12.7 | I48: =LN((G48+H48)/G47) -> -0.015625318 | J48: 45358 | K48: 38.8 | O48: =K48+K48*L48+K48*M48-N48*M48 -> 38.8 | Q48: =LN((O48+P48)/O47) -> -0.0077022204 | R48: 45358 | S48: 253.5 | W48: =S48+S48*T48+S48*U48-V48*U48 -> 253.5 | Y48: =LN((W48+X48)/W47) -> -0.012544265 | Z48: 45358 | AA48: 984.7 | AE48: =AA48+AA48*AB48+AA48*AC48-AD48*AC48 -> 984.7 | AG48: =LN((AE48+AF48)/AE47) -> 0.0016261819 | AH48: 45358 | AI48: 923.5 | AM48: =AI48+AI48*AJ48+AI48*AK48-AL48*AK48 -> 923.5 | AO48: =LN((AM48+AN48)/AM47) -> -0.010877281 | AP48: 45358 | AQ48: 727.8 | AU48: =AQ48+AQ48*AR48+AQ48*AS48-AT48*AS48 -> 727.8 | AW48: =LN((AU48+AV48)/AU47) -> -0.0013730608 | AX48: 45358 | AY48: 35.3 | BC48: =AY48+AY48*AZ48+AY48*BA48-BB48*BA48 -> 35.3 | BE48: =LN((BC48+BD48)/BC47) -> -0.011267725 | BF48: 45358 | BG48: 150 | BK48: =BG48+BG48*BH48+BG48*BI48-BJ48*BI48 -> 150 | BM48: =LN((BK48+BL48)/BK47) -> 0.00066688899
B49: 45361 | C49: 12.6 | G49: =C49+C49*D49+C49*E49-F49*E49 -> 12.6 | I49: =LN((G49+H49)/G48) -> -0.0079051795 | J49: 45361 | K49: 38.7 | O49: =K49+K49*L49+K49*M49-N49*M49 -> 38.7 | Q49: =LN((O49+P49)/O48) -> -0.0025806466 | R49: 45361 | S49: 250.4 | W49: =S49+S49*T49+S49*U49-V49*U49 -> 250.4 | Y49: =LN((W49+X49)/W48) -> -0.012304184 | Z49: 45361 | AA49: 985 | AE49: =AA49+AA49*AB49+AA49*AC49-AD49*AC49 -> 985 | AG49: =LN((AE49+AF49)/AE48) -> 0.00030461492 | AH49: 45361 | AI49: 912.1 | AM49: =AI49+AI49*AJ49+AI49*AK49-AL49*AK49 -> 912.1 | AO49: =LN((AM49+AN49)/AM48) -> -0.012421166 | AP49: 45361 | AQ49: 723 | AU49: =AQ49+AQ49*AR49+AQ49*AS49-AT49*AS49 -> 723 | AW49: =LN((AU49+AV49)/AU48) -> -0.006617063 | AX49: 45361 | AY49: 35.1 | BC49: =AY49+AY49*AZ49+AY49*BA49-BB49*BA49 -> 35.1 | BE49: =LN((BC49+BD49)/BC48) -> -0.0056818335 | BF49: 45361 | BG49: 150.9 | BK49: =BG49+BG49*BH49+BG49*BI49-BJ49*BI49 -> 150.9 | BM49: =LN((BK49+BL49)/BK48) -> 0.0059820717
B50: 45362 | C50: 12.5 | G50: =C50+C50*D50+C50*E50-F50*E50 -> 12.5 | I50: =LN((G50+H50)/G49) -> -0.0079681696 | J50: 45362 | K50: 38.2 | O50: =K50+K50*L50+K50*M50-N50*M50 -> 38.2 | Q50: =LN((O50+P50)/O49) -> -0.013004084 | R50: 45362 | S50: 246.6 | W50: =S50+S50*T50+S50*U50-V50*U50 -> 246.6 | Y50: =LN((W50+X50)/W49) -> -0.015292048 | Z50: 45362 | AA50: 992.9 | AE50: =AA50+AA50*AB50+AA50*AC50-AD50*AC50 -> 992.9 | AG50: =LN((AE50+AF50)/AE49) -> 0.0079883129 | AH50: 45362 | AI50: 907.7 | AM50: =AI50+AI50*AJ50+AI50*AK50-AL50*AK50 -> 907.7 | AO50: =LN((AM50+AN50)/AM49) -> -0.0048357057 | AP50: 45362 | AQ50: 718.2 | AU50: =AQ50+AQ50*AR50+AQ50*AS50-AT50*AS50 -> 718.2 | AW50: =LN((AU50+AV50)/AU49) -> -0.0066611404 | AX50: 45362 | AY50: 35.2 | BC50: =AY50+AY50*AZ50+AY50*BA50-BB50*BA50 -> 35.2 | BE50: =LN((BC50+BD50)/BC49) -> 0.0028449521 | BF50: 45362 | BG50: 150 | BK50: =BG50+BG50*BH50+BG50*BI50-BJ50*BI50 -> 150 | BM50: =LN((BK50+BL50)/BK49) -> -0.0059820717
B51: 45363 | C51: 12.5 | G51: =C51+C51*D51+C51*E51-F51*E51 -> 12.5 | I51: =LN((G51+H51)/G50) -> 0 | J51: 45363 | K51: 38.2 | O51: =K51+K51*L51+K51*M51-N51*M51 -> 38.2 | Q51: =LN((O51+P51)/O50) -> 0 | R51: 45363 | S51: 244.9 | W51: =S51+S51*T51+S51*U51-V51*U51 -> 244.9 | Y51: =LN((W51+X51)/W50) -> -0.0069176268 | Z51: 45363 | AA51: 981.8 | AE51: =AA51+AA51*AB51+AA51*AC51-AD51*AC51 -> 981.8 | AG51: =LN((AE51+AF51)/AE50) -> -0.011242332 | AH51: 45363 | AI51: 896.5 | AM51: =AI51+AI51*AJ51+AI51*AK51-AL51*AK51 -> 896.5 | AO51: =LN((AM51+AN51)/AM50) -> -0.012415634 | AP51: 45363 | AQ51: 713.7 | AU51: =AQ51+AQ51*AR51+AQ51*AS51-AT51*AS51 -> 713.7 | AW51: =LN((AU51+AV51)/AU50) -> -0.0062853758 | AX51: 45363 | AY51: 34.6 | BC51: =AY51+AY51*AZ51+AY51*BA51-BB51*BA51 -> 34.6 | BE51: =LN((BC51+BD51)/BC50) -> -0.017192401 | BF51: 45363 | BG51: 150.2 | BK51: =BG51+BG51*BH51+BG51*BI51-BJ51*BI51 -> 150.2 | BM51: =LN((BK51+BL51)/BK50) -> 0.0013324452
B52: 45364 | C52: 12.5 | G52: =C52+C52*D52+C52*E52-F52*E52 -> 12.5 | I52: =LN((G52+H52)/G51) -> 0 | J52: 45364 | K52: 37.5 | O52: =K52+K52*L52+K52*M52-N52*M52 -> 37.5 | Q52: =LN((O52+P52)/O51) -> -0.018494583 | R52: 45364 | S52: 241.2 | W52: =S52+S52*T52+S52*U52-V52*U52 -> 241.2 | Y52: =LN((W52+X52)/W51) -> -0.015223499 | Z52: 45364 | AA52: 990 | AE52: =AA52+AA52*AB52+AA52*AC52-AD52*AC52 -> 990 | AG52: =LN((AE52+AF52)/AE51) -> 0.0083173215 | AH52: 45364 | AI52: 887.6 | AM52: =AI52+AI52*AJ52+AI52*AK52-AL52*AK52 -> 887.6 | AO52: =LN((AM52+AN52)/AM51) -> -0.009977102 | AP52: 45364 | AQ52: 718.4 | AU52: =AQ52+AQ52*AR52+AQ52*AS52-AT52*AS52 -> 718.4 | AW52: =LN((AU52+AV52)/AU51) -> 0.006563811 | AX52: 45364 | AY52: 34.2 | BC52: =AY52+AY52*AZ52+AY52*BA52-BB52*BA52 -> 34.2 | BE52: =LN((BC52+BD52)/BC51) -> -0.011628038 | BF52: 45364 | BG52: 149.6 | BK52: =BG52+BG52*BH52+BG52*BI52-BJ52*BI52 -> 149.6 | BM52: =LN((BK52+BL52)/BK51) -> -0.0040026738
B53: 45365 | C53: 12.5 | G53: =C53+C53*D53+C53*E53-F53*E53 -> 12.5 | I53: =LN((G53+H53)/G52) -> 0 | J53: 45365 | K53: 37.1 | O53: =K53+K53*L53+K53*M53-N53*M53 -> 37.1 | Q53: =LN((O53+P53)/O52) -> -0.010723963 | R53: 45365 | S53: 243.3 | W53: =S53+S53*T53+S53*U53-V53*U53 -> 243.3 | Y53: =LN((W53+X53)/W52) -> 0.0086687849 | Z53: 45365 | AA53: 989.2 | AE53: =AA53+AA53*AB53+AA53*AC53-AD53*AC53 -> 989.2 | AG53: =LN((AE53+AF53)/AE52) -> -0.00080840748 | AH53: 45365 | AI53: 877.2 | AM53: =AI53+AI53*AJ53+AI53*AK53-AL53*AK53 -> 877.2 | AO53: =LN((AM53+AN53)/AM52) -> -0.011786175 | AP53: 45365 | AQ53: 718.2 | AU53: =AQ53+AQ53*AR53+AQ53*AS53-AT53*AS53 -> 718.2 | AW53: =LN((AU53+AV53)/AU52) -> -0.0002784352 | AX53: 45365 | AY53: 34.1 | BC53: =AY53+AY53*AZ53+AY53*BA53-BB53*BA53 -> 34.1 | BE53: =LN((BC53+BD53)/BC52) -> -0.0029282598 | BF53: 45365 | BG53: 150.1 | BK53: =BG53+BG53*BH53+BG53*BI53-BJ53*BI53 -> 150.1 | BM53: =LN((BK53+BL53)/BK52) -> 0.0033366731
B54: 45369 | C54: 12.1 | G54: =C54+C54*D54+C54*E54-F54*E54 -> 12.1 | I54: =LN((G54+H54)/G53) -> -0.032523192 | J54: 45369 | K54: 36 | O54: =K54+K54*L54+K54*M54-N54*M54 -> 36 | Q54: =LN((O54+P54)/O53) -> -0.030098031 | R54: 45369 | S54: 243.5 | W54: =S54+S54*T54+S54*U54-V54*U54 -> 243.5 | Y54: =LN((W54+X54)/W53) -> 0.00082169273 | Z54: 45369 | AA54: 985 | AE54: =AA54+AA54*AB54+AA54*AC54-AD54*AC54 -> 985 | AG54: =LN((AE54+AF54)/AE53) -> -0.0042548945 | AH54: 45369 | AI54: 863.5 | AM54: =AI54+AI54*AJ54+AI54*AK54-AL54*AK54 -> 863.5 | AO54: =LN((AM54+AN54)/AM53) -> -0.015741119 | AP54: 45369 | AQ54: 709.7 | AU54: =AQ54+AQ54*AR54+AQ54*AS54-AT54*AS54 -> 709.7 | AW54: =LN((AU54+AV54)/AU53) -> -0.011905736 | AX54: 45369 | AY54: 33.3 | BC54: =AY54+AY54*AZ54+AY54*BA54-BB54*BA54 -> 33.3 | BE54: =LN((BC54+BD54)/BC53) -> -0.023739987 | BF54: 45369 | BG54: 148.5 | BK54: =BG54+BG54*BH54+BG54*BI54-BJ54*BI54 -> 148.5 | BM54: =LN((BK54+BL54)/BK53) -> -0.01071678
B55: 45370 | C55: 11.8 | G55: =C55+C55*D55+C55*E55-F55*E55 -> 11.8 | I55: =LN((G55+H55)/G54) -> -0.025105921 | J55: 45370 | K55: 34 | O55: =K55+K55*L55+K55*M55-N55*M55 -> 34 | Q55: =LN((O55+P55)/O54) -> -0.057158414 | R55: 45370 | S55: 242.5 | W55: =S55+S55*T55+S55*U55-V55*U55 -> 242.5 | Y55: =LN((W55+X55)/W54) -> -0.0041152321 | Z55: 45370 | AA55: 983 | AE55: =AA55+AA55*AB55+AA55*AC55-AD55*AC55 -> 983 | AG55: =LN((AE55+AF55)/AE54) -> -0.002032521 | AH55: 45370 | AI55: 851.2 | AM55: =AI55+AI55*AJ55+AI55*AK55-AL55*AK55 -> 851.2 | AO55: =LN((AM55+AN55)/AM54) -> -0.014346779 | AP55: 45370 | AQ55: 708.3 | AU55: =AQ55+AQ55*AR55+AQ55*AS55-AT55*AS55 -> 708.3 | AW55: =LN((AU55+AV55)/AU54) -> -0.0019746128 | AX55: 45370 | AY55: 32 | BC55: =AY55+AY55*AZ55+AY55*BA55-BB55*BA55 -> 32 | BE55: =LN((BC55+BD55)/BC54) -> -0.039821494 | BF55: 45370 | BG55: 147.8 | BK55: =BG55+BG55*BH55+BG55*BI55-BJ55*BI55 -> 147.8 | BM55: =LN((BK55+BL55)/BK54) -> -0.0047249497
B56: 45371 | C56: 12.1 | G56: =C56+C56*D56+C56*E56-F56*E56 -> 12.1 | I56: =LN((G56+H56)/G55) -> 0.025105921 | J56: 45371 | K56: 34.4 | O56: =K56+K56*L56+K56*M56-N56*M56 -> 34.4 | Q56: =LN((O56+P56)/O55) -> 0.01169604 | R56: 45371 | S56: 240.7 | W56: =S56+S56*T56+S56*U56-V56*U56 -> 240.7 | Y56: =LN((W56+X56)/W55) -> -0.0074503656 | Z56: 45371 | AA56: 985.1 | AE56: =AA56+AA56*AB56+AA56*AC56-AD56*AC56 -> 985.1 | AG56: =LN((AE56+AF56)/AE55) -> 0.0021340387 | AH56: 45371 | AI56: 840.8 | AM56: =AI56+AI56*AJ56+AI56*AK56-AL56*AK56 -> 840.8 | AO56: =LN((AM56+AN56)/AM55) -> -0.012293299 | AP56: 45371 | AQ56: 709.6 | AU56: =AQ56+AQ56*AR56+AQ56*AS56-AT56*AS56 -> 709.6 | AW56: =LN((AU56+AV56)/AU55) -> 0.0018336982 | AX56: 45371 | AY56: 33.4 | BC56: =AY56+AY56*AZ56+AY56*BA56-BB56*BA56 -> 33.4 | BE56: =LN((BC56+BD56)/BC55) -> 0.042819997 | BF56: 45371 | BG56: 147.9 | BK56: =BG56+BG56*BH56+BG56*BI56-BJ56*BI56 -> 147.9 | BM56: =LN((BK56+BL56)/BK55) -> 0.0006763612
... B62: 45382 | C62: 12 | G62: =C62+C62*D62+C62*E62-F62*E62 -> 12 | I62: =LN((G62+H62)/G61) -> 0.0083682497 | J62: 45382 | K62: 36.6 | O62: =K62+K62*L62+K62*M62-N62*M62 -> 36.6 | Q62: =LN((O62+P62)/O61) -> 0.016529302 | R62: 45382 | S62: 237.8 | W62: =S62+S62*T62+S62*U62-V62*U62 -> 237.8 | Y62: =LN((W62+X62)/W61) -> 0.0084459962 | Z62: 45382 | AA62: 988.6 | AE62: =AA62+AA62*AB62+AA62*AC62-AD62*AC62 -> 988.6 | AG62: =LN((AE62+AF62)/AE61) -> 0.0080231985 | AH62: 45382 | AI62: 776 | AM62: =AI62+AI62*AJ62+AI62*AK62-AL62*AK62 -> 776 | AO62: =LN((AM62+AN62)/AM61) -> 0.011926509 | AP62: 45382 | AQ62: 650 | AU62: =AQ62+AQ62*AR62+AQ62*AS62-AT62*AS62 -> 650 | AW62: =LN((AU62+AV62)/AU61) -> -0.0088835015 | AX62: 45382 | AY62: 32.6 | BC62: =AY62+AY62*AZ62+AY62*BA62-BB62*BA62 -> 32.6 | BE62: =LN((BC62+BD62)/BC61) -> 0.024845999 | BF62: 45382 | BG62: 152.1 | BK62: =BG62+BG62*BH62+BG62*BI62-BJ62*BI62 -> 152.1 | BM62: =LN((BK62+BL62)/BK61) -> 0.016573134
A63: 2024 Q2 | B63: 45383 | C63: 11.7 | G63: =C63+C63*D63+C63*E63-F63*E63 -> 11.7 | I63: =LN((G63+H63)/G62) -> -0.025317808 | J63: 45383 | K63: 36.7 | O63: =K63+K63*L63+K63*M63-N63*M63 -> 36.7 | Q63: =LN((O63+P63)/O62) -> 0.0027285147 | R63: 45383 | S63: 236.9 | W63: =S63+S63*T63+S63*U63-V63*U63 -> 236.9 | Y63: =LN((W63+X63)/W62) -> -0.0037918731 | Z63: 45383 | AA63: 993.2 | AE63: =AA63+AA63*AB63+AA63*AC63-AD63*AC63 -> 993.2 | AG63: =LN((AE63+AF63)/AE62) -> 0.0046422528 | AH63: 45383 | AI63: 748.7 | AM63: =AI63+AI63*AJ63+AI63*AK63-AL63*AK63 -> 748.7 | AO63: =LN((AM63+AN63)/AM62) -> -0.035814151 | AP63: 45383 | AQ63: 649.8 | AU63: =AQ63+AQ63*AR63+AQ63*AS63-AT63*AS63 -> 649.8 | AW63: =LN((AU63+AV63)/AU62) -> -0.00030773965 | AX63: 45383 | AY63: 32.4 | BC63: =AY63+AY63*AZ63+AY63*BA63-BB63*BA63 -> 32.4 | BE63: =LN((BC63+BD63)/BC62) -> -0.0061538656 | BF63: 45383 | BG63: 152.9 | BK63: =BG63+BG63*BH63+BG63*BI63-BJ63*BI63 -> 152.9 | BM63: =LN((BK63+BL63)/BK62) -> 0.0052459137
B64: 45384 | C64: 11.6 | G64: =C64+C64*D64+C64*E64-F64*E64 -> 11.6 | I64: =LN((G64+H64)/G63) -> -0.0085837437 | J64: 45384 | K64: 36.7 | O64: =K64+K64*L64+K64*M64-N64*M64 -> 36.7 | Q64: =LN((O64+P64)/O63) -> 0 | R64: 45384 | S64: 237.7 | W64: =S64+S64*T64+S64*U64-V64*U64 -> 237.7 | Y64: =LN((W64+X64)/W63) -> 0.0033712632 | Z64: 45384 | AA64: 995.7 | AE64: =AA64+AA64*AB64+AA64*AC64-AD64*AC64 -> 995.7 | AG64: =LN((AE64+AF64)/AE63) -> 0.0025139538 | AH64: 45384 | AI64: 764.3 | AM64: =AI64+AI64*AJ64+AI64*AK64-AL64*AK64 -> 764.3 | AO64: =LN((AM64+AN64)/AM63) -> 0.020622013 | AP64: 45384 | AQ64: 672.1 | AU64: =AQ64+AQ64*AR64+AQ64*AS64-AT64*AS64 -> 672.1 | AW64: =LN((AU64+AV64)/AU63) -> 0.033742516 | AX64: 45384 | AY64: 32.1 | BC64: =AY64+AY64*AZ64+AY64*BA64-BB64*BA64 -> 32.1 | BE64: =LN((BC64+BD64)/BC63) -> -0.0093023927 | BF64: 45384 | BG64: 153.5 | BK64: =BG64+BG64*BH64+BG64*BI64-BJ64*BI64 -> 153.5 | BM64: =LN((BK64+BL64)/BK63) -> 0.0039164541
B65: 45385 | C65: 11.7 | G65: =C65+C65*D65+C65*E65-F65*E65 -> 11.7 | I65: =LN((G65+H65)/G64) -> 0.0085837437 | J65: 45385 | K65: 37.3 | O65: =K65+K65*L65+K65*M65-N65*M65 -> 37.3 | Q65: =LN((O65+P65)/O64) -> 0.016216572 | R65: 45385 | S65: 239.6 | W65: =S65+S65*T65+S65*U65-V65*U65 -> 239.6 | Y65: =LN((W65+X65)/W64) -> 0.0079614919 | Z65: 45385 | AA65: 1001.7 | AE65: =AA65+AA65*AB65+AA65*AC65-AD65*AC65 -> 1001.7 | AG65: =LN((AE65+AF65)/AE64) -> 0.0060078282 | AH65: 45385 | AI65: 766.4 | AM65: =AI65+AI65*AJ65+AI65*AK65-AL65*AK65 -> 766.4 | AO65: =LN((AM65+AN65)/AM64) -> 0.0027438444 | AP65: 45385 | AQ65: 680.1 | AU65: =AQ65+AQ65*AR65+AQ65*AS65-AT65*AS65 -> 680.1 | AW65: =LN((AU65+AV65)/AU64) -> 0.011832707 | AX65: 45385 | AY65: 32.6 | BC65: =AY65+AY65*AZ65+AY65*BA65-BB65*BA65 -> 32.6 | BE65: =LN((BC65+BD65)/BC64) -> 0.015456258 | BF65: 45385 | BG65: 154.4 | BK65: =BG65+BG65*BH65+BG65*BI65-BJ65*BI65 -> 154.4 | BM65: =LN((BK65+BL65)/BK64) -> 0.0058460706
B66: 45386 | C66: 11.5 | G66: =C66+C66*D66+C66*E66-F66*E66 -> 11.5 | I66: =LN((G66+H66)/G65) -> -0.017241806 | J66: 45386 | K66: 37.3 | O66: =K66+K66*L66+K66*M66-N66*M66 -> 37.3 | Q66: =LN((O66+P66)/O65) -> 0 | R66: 45386 | S66: 240.2 | W66: =S66+S66*T66+S66*U66-V66*U66 -> 240.2 | Y66: =LN((W66+X66)/W65) -> 0.0025010434 | Z66: 45386 | AA66: 990 | AE66: =AA66+AA66*AB66+AA66*AC66-AD66*AC66 -> 990 | AG66: =LN((AE66+AF66)/AE65) -> -0.011748892 | AH66: 45386 | AI66: 769 | AM66: =AI66+AI66*AJ66+AI66*AK66-AL66*AK66 -> 769 | AO66: =LN((AM66+AN66)/AM65) -> 0.0033867428 | AP66: 45386 | AQ66: 674.5 | AU66: =AQ66+AQ66*AR66+AQ66*AS66-AT66*AS66 -> 674.5 | AW66: =LN((AU66+AV66)/AU65) -> -0.0082681705 | AX66: 45386 | AY66: 32.8 | BC66: =AY66+AY66*AZ66+AY66*BA66-BB66*BA66 -> 32.8 | BE66: =LN((BC66+BD66)/BC65) -> 0.006116227 | BF66: 45386 | BG66: 154.3 | BK66: =BG66+BG66*BH66+BG66*BI66-BJ66*BI66 -> 154.3 | BM66: =LN((BK66+BL66)/BK65) -> -0.00064787822
B67: 45390 | C67: 11.6 | G67: =C67+C67*D67+C67*E67-F67*E67 -> 11.6 | I67: =LN((G67+H67)/G66) -> 0.0086580627 | J67: 45390 | K67: 36 | O67: =K67+K67*L67+K67*M67-N67*M67 -> 36 | P67: 1.5 | Q67: =LN((O67+P67)/O66) -> 0.0053476063 | R67: 45390 | S67: 240.2 | W67: =S67+S67*T67+S67*U67-V67*U67 -> 240.2 | Y67: =LN((W67+X67)/W66) -> 0 | Z67: 45390 | AA67: 997.8 | AE67: =AA67+AA67*AB67+AA67*AC67-AD67*AC67 -> 997.8 | AG67: =LN((AE67+AF67)/AE66) -> 0.0078479123 | AH67: 45390 | AI67: 779.8 | AM67: =AI67+AI67*AJ67+AI67*AK67-AL67*AK67 -> 779.8 | AO67: =LN((AM67+AN67)/AM66) -> 0.013946507 | AP67: 45390 | AQ67: 679.9 | AU67: =AQ67+AQ67*AR67+AQ67*AS67-AT67*AS67 -> 679.9 | AW67: =LN((AU67+AV67)/AU66) -> 0.0079740529 | AX67: 45390 | AY67: 33.3 | BC67: =AY67+AY67*AZ67+AY67*BA67-BB67*BA67 -> 33.3 | BE67: =LN((BC67+BD67)/BC66) -> 0.015128882 | BF67: 45390 | BG67: 155.1 | BK67: =BG67+BG67*BH67+BG67*BI67-BJ67*BI67 -> 155.1 | BM67: =LN((BK67+BL67)/BK66) -> 0.0051713108
B68: 45391 | C68: 11.4 | G68: =C68+C68*D68+C68*E68-F68*E68 -> 11.4 | I68: =LN((G68+H68)/G67) -> -0.017391743 | J68: 45391 | K68: 36.3 | O68: =K68+K68*L68+K68*M68-N68*M68 -> 36.3 | Q68: =LN((O68+P68)/O67) -> 0.0082988028 | R68: 45391 | S68: 240 | W68: =S68+S68*T68+S68*U68-V68*U68 -> 240 | Y68: =LN((W68+X68)/W67) -> -0.0008329863 | Z68: 45391 | AA68: 994.8 | AE68: =AA68+AA68*AB68+AA68*AC68-AD68*AC68 -> 994.8 | AG68: =LN((AE68+AF68)/AE67) -> -0.0030111435 | AH68: 45391 | AI68: 806.9 | AM68: =AI68+AI68*AJ68+AI68*AK68-AL68*AK68 -> 806.9 | AO68: =LN((AM68+AN68)/AM67) -> 0.034162268 | AP68: 45391 | AQ68: 673.9 | AU68: =AQ68+AQ68*AR68+AQ68*AS68-AT68*AS68 -> 673.9 | AW68: =LN((AU68+AV68)/AU67) -> -0.0088639966 | AX68: 45391 | AY68: 33.8 | BC68: =AY68+AY68*AZ68+AY68*BA68-BB68*BA68 -> 33.8 | BE68: =LN((BC68+BD68)/BC67) -> 0.014903406 | BF68: 45391 | BG68: 153 | BK68: =BG68+BG68*BH68+BG68*BI68-BJ68*BI68 -> 153 | BM68: =LN((BK68+BL68)/BK67) -> -0.013632149
B69: 45397 | C69: 11.4 | G69: =C69+C69*D69+C69*E69-F69*E69 -> 11.4 | I69: =LN((G69+H69)/G68) -> 0 | J69: 45397 | K69: 35.4 | O69: =K69+K69*L69+K69*M69-N69*M69 -> 35.4 | Q69: =LN((O69+P69)/O68) -> -0.025105921 | R69: 45397 | S69: 238.9 | W69: =S69+S69*T69+S69*U69-V69*U69 -> 238.9 | Y69: =LN((W69+X69)/W68) -> -0.004593869 | Z69: 45397 | AA69: 989.2 | AE69: =AA69+AA69*AB69+AA69*AC69-AD69*AC69 -> 989.2 | AG69: =LN((AE69+AF69)/AE68) -> -0.0056451763 | AH69: 45397 | AI69: 807.2 | AM69: =AI69+AI69*AJ69+AI69*AK69-AL69*AK69 -> 807.2 | AO69: =LN((AM69+AN69)/AM68) -> 0.00037172418 | AP69: 45397 | AQ69: 661.2 | AU69: =AQ69+AQ69*AR69+AQ69*AS69-AT69*AS69 -> 661.2 | AW69: =LN((AU69+AV69)/AU68) -> -0.019025366 | AX69: 45397 | AY69: 32.5 | BC69: =AY69+AY69*AZ69+AY69*BA69-BB69*BA69 -> 32.5 | BE69: =LN((BC69+BD69)/BC68) -> -0.039220713 | BF69: 45397 | BG69: 150 | BK69: =BG69+BG69*BH69+BG69*BI69-BJ69*BI69 -> 150 | BM69: =LN((BK69+BL69)/BK68) -> -0.019802627
B70: 45398 | C70: 11.5 | G70: =C70+C70*D70+C70*E70-F70*E70 -> 11.5 | I70: =LN((G70+H70)/G69) -> 0.00873368 | J70: 45398 | K70: 35.3 | O70: =K70+K70*L70+K70*M70-N70*M70 -> 35.3 | Q70: =LN((O70+P70)/O69) -> -0.0028288562 | R70: 45398 | S70: 236.1 | W70: =S70+S70*T70+S70*U70-V70*U70 -> 236.1 | Y70: =LN((W70+X70)/W69) -> -0.01178961 | Z70: 45398 | AA70: 980.3 | AE70: =AA70+AA70*AB70+AA70*AC70-AD70*AC70 -> 980.3 | AG70: =LN((AE70+AF70)/AE69) -> -0.0090378884 | AH70: 45398 | AI70: 807.8 | AM70: =AI70+AI70*AJ70+AI70*AK70-AL70*AK70 -> 807.8 | AO70: =LN((AM70+AN70)/AM69) -> 0.00074303409 | AP70: 45398 | AQ70: 660 | AU70: =AQ70+AQ70*AR70+AQ70*AS70-AT70*AS70 -> 660 | AW70: =LN((AU70+AV70)/AU69) -> -0.0018165309 | AX70: 45398 | AY70: 32.3 | BC70: =AY70+AY70*AZ70+AY70*BA70-BB70*BA70 -> 32.3 | BE70: =LN((BC70+BD70)/BC69) -> -0.0061728591 | BF70: 45398 | BG70: 151.8 | BK70: =BG70+BG70*BH70+BG70*BI70-BJ70*BI70 -> 151.8 | BM70: =LN((BK70+BL70)/BK69) -> 0.011928571
B71: 45399 | C71: 11.5 | G71: =C71+C71*D71+C71*E71-F71*E71 -> 11.5 | I71: =LN((G71+H71)/G70) -> 0 | J71: 45399 | K71: 35.1 | O71: =K71+K71*L71+K71*M71-N71*M71 -> 35.1 | Q71: =LN((O71+P71)/O70) -> -0.0056818335 | R71: 45399 | S71: 236.9 | W71: =S71+S71*T71+S71*U71-V71*U71 -> 236.9 | Y71: =LN((W71+X71)/W70) -> 0.0033826671 | Z71: 45399 | AA71: 982 | AE71: =AA71+AA71*AB71+AA71*AC71-AD71*AC71 -> 982 | AG71: =LN((AE71+AF71)/AE70) -> 0.0017326611 | AH71: 45399 | AI71: 812.9 | AM71: =AI71+AI71*AJ71+AI71*AK71-AL71*AK71 -> 812.9 | AO71: =LN((AM71+AN71)/AM70) -> 0.0062935976 | AP71: 45399 | AQ71: 651.5 | AU71: =AQ71+AQ71*AR71+AQ71*AS71-AT71*AS71 -> 651.5 | AW71: =LN((AU71+AV71)/AU70) -> -0.012962438 | AX71: 45399 | AY71: 31.9 | BC71: =AY71+AY71*AZ71+AY71*BA71-BB71*BA71 -> 31.9 | BE71: =LN((BC71+BD71)/BC70) -> -0.01246122 | BF71: 45399 | BG71: 153.1 | BK71: =BG71+BG71*BH71+BG71*BI71-BJ71*BI71 -> 153.1 | BM71: =LN((BK71+BL71)/BK70) -> 0.0085274377
B72: 45400 | C72: 11.4 | G72: =C72+C72*D72+C72*E72-F72*E72 -> 11.4 | I72: =LN((G72+H72)/G71) -> -0.00873368 | J72: 45400 | K72: 33.2 | O72: =K72+K72*L72+K72*M72-N72*M72 -> 33.2 | Q72: =LN((O72+P72)/O71) -> -0.055651255 | R72: 45400 | S72: 234.7 | W72: =S72+S72*T72+S72*U72-V72*U72 -> 234.7 | Y72: =LN((W72+X72)/W71) -> -0.0093300083 | Z72: 45400 | AA72: 965.3 | AE72: =AA72+AA72*AB72+AA72*AC72-AD72*AC72 -> 965.3 | AG72: =LN((AE72+AF72)/AE71) -> -0.017152374 | AH72: 45400 | AI72: 800.4 | AM72: =AI72+AI72*AJ72+AI72*AK72-AL72*AK72 -> 800.4 | AO72: =LN((AM72+AN72)/AM71) -> -0.015496498 | AP72: 45400 | AQ72: 646.3 | AU72: =AQ72+AQ72*AR72+AQ72*AS72-AT72*AS72 -> 646.3 | AW72: =LN((AU72+AV72)/AU71) -> -0.0080136043 | AX72: 45400 | AY72: 31.4 | BC72: =AY72+AY72*AZ72+AY72*BA72-BB72*BA72 -> 31.4 | BE72: =LN((BC72+BD72)/BC71) -> -0.015798117 | BF72: 45400 | BG72: 148.6 | BK72: =BG72+BG72*BH72+BG72*BI72-BJ72*BI72 -> 148.6 | BM72: =LN((BK72+BL72)/BK71) -> -0.02983317
B73: 45403 | C73: 11 | G73: =C73+C73*D73+C73*E73-F73*E73 -> 11 | I73: =LN((G73+H73)/G72) -> -0.035718083 | J73: 45403 | K73: 32.4 | O73: =K73+K73*L73+K73*M73-N73*M73 -> 32.4 | Q73: =LN((O73+P73)/O72) -> -0.024391453 | R73: 45403 | S73: 234.2 | W73: =S73+S73*T73+S73*U73-V73*U73 -> 234.2 | Y73: =LN((W73+X73)/W72) -> -0.0021326517 | Z73: 45403 | AA73: 970 | AE73: =AA73+AA73*AB73+AA73*AC73-AD73*AC73 -> 970 | AG73: =LN((AE73+AF73)/AE72) -> 0.0048571376 | AH73: 45403 | AI73: 782.4 | AM73: =AI73+AI73*AJ73+AI73*AK73-AL73*AK73 -> 782.4 | AO73: =LN((AM73+AN73)/AM72) -> -0.022745484 | AP73: 45403 | AQ73: 631.9 | AU73: =AQ73+AQ73*AR73+AQ73*AS73-AT73*AS73 -> 631.9 | AW73: =LN((AU73+AV73)/AU72) -> -0.022532638 | AX73: 45403 | AY73: 31.3 | BC73: =AY73+AY73*AZ73+AY73*BA73-BB73*BA73 -> 31.3 | BE73: =LN((BC73+BD73)/BC72) -> -0.0031897954 | BF73: 45403 | BG73: 148.8 | BK73: =BG73+BG73*BH73+BG73*BI73-BJ73*BI73 -> 148.8 | BM73: =LN((BK73+BL73)/BK72) -> 0.0013449901
B74: 45404 | C74: 11.1 | G74: =C74+C74*D74+C74*E74-F74*E74 -> 11.1 | I74: =LN((G74+H74)/G73) -> 0.0090498355 | J74: 45404 | K74: 32.9 | O74: =K74+K74*L74+K74*M74-N74*M74 -> 32.9 | Q74: =LN((O74+P74)/O73) -> 0.015314235 | R74: 45404 | S74: 233.1 | W74: =S74+S74*T74+S74*U74-V74*U74 -> 233.1 | Y74: =LN((W74+X74)/W73) -> -0.0047079051 | Z74: 45404 | AA74: 970 | AE74: =AA74+AA74*AB74+AA74*AC74-AD74*AC74 -> 970 | AG74: =LN((AE74+AF74)/AE73) -> 0 | AH74: 45404 | AI74: 783.1 | AM74: =AI74+AI74*AJ74+AI74*AK74-AL74*AK74 -> 783.1 | AO74: =LN((AM74+AN74)/AM73) -> 0.00089428304 | AP74: 45404 | AQ74: 645.6 | AU74: =AQ74+AQ74*AR74+AQ74*AS74-AT74*AS74 -> 645.6 | AW74: =LN((AU74+AV74)/AU73) -> 0.021448963 | AX74: 45404 | AY74: 31.3 | BC74: =AY74+AY74*AZ74+AY74*BA74-BB74*BA74 -> 31.3 | BE74: =LN((BC74+BD74)/BC73) -> 0 | BF74: 45404 | BG74: 148 | BK74: =BG74+BG74*BH74+BG74*BI74-BJ74*BI74 -> 148 | BM74: =LN((BK74+BL74)/BK73) -> -0.0053908486
B75: 45405 | C75: 10.8 | G75: =C75+C75*D75+C75*E75-F75*E75 -> 10.8 | I75: =LN((G75+H75)/G74) -> -0.027398974 | J75: 45405 | K75: 32.6 | O75: =K75+K75*L75+K75*M75-N75*M75 -> 32.6 | Q75: =LN((O75+P75)/O74) -> -0.0091603694 | R75: 45405 | S75: 232.6 | W75: =S75+S75*T75+S75*U75-V75*U75 -> 232.6 | Y75: =LN((W75+X75)/W74) -> -0.002147306 | Z75: 45405 | AA75: 955.5 | AE75: =AA75+AA75*AB75+AA75*AC75-AD75*AC75 -> 955.5 | AG75: =LN((AE75+AF75)/AE74) -> -0.015061308 | AH75: 45405 | AI75: 786.9 | AM75: =AI75+AI75*AJ75+AI75*AK75-AL75*AK75 -> 786.9 | AO75: =LN((AM75+AN75)/AM74) -> 0.0048407738 | AP75: 45405 | AQ75: 651 | AU75: =AQ75+AQ75*AR75+AQ75*AS75-AT75*AS75 -> 651 | AW75: =LN((AU75+AV75)/AU74) -> 0.0083295253 | AX75: 45405 | AY75: 30.1 | BC75: =AY75+AY75*AZ75+AY75*BA75-BB75*BA75 -> 30.1 | BE75: =LN((BC75+BD75)/BC74) -> -0.039092926 | BF75: 45405 | BG75: 147.5 | BK75: =BG75+BG75*BH75+BG75*BI75-BJ75*BI75 -> 147.5 | BM75: =LN((BK75+BL75)/BK74) -> -0.003384098
B76: 45406 | C76: 10.8 | G76: =C76+C76*D76+C76*E76-F76*E76 -> 10.8 | I76: =LN((G76+H76)/G75) -> 0 | J76: 45406 | K76: 31.9 | O76: =K76+K76*L76+K76*M76-N76*M76 -> 31.9 | Q76: =LN((O76+P76)/O75) -> -0.021706279 | R76: 45406 | S76: 232.5 | W76: =S76+S76*T76+S76*U76-V76*U76 -> 232.5 | Y76: =LN((W76+X76)/W75) -> -0.00043001506 | Z76: 45406 | AA76: 977.9 | AE76: =AA76+AA76*AB76+AA76*AC76-AD76*AC76 -> 977.9 | AG76: =LN((AE76+AF76)/AE75) -> 0.023172652 | AH76: 45406 | AI76: 783.4 | AM76: =AI76+AI76*AJ76+AI76*AK76-AL76*AK76 -> 783.4 | AO76: =LN((AM76+AN76)/AM75) -> -0.0044577543 | AP76: 45406 | AQ76: 642 | AU76: =AQ76+AQ76*AR76+AQ76*AS76-AT76*AS76 -> 642 | AW76: =LN((AU76+AV76)/AU75) -> -0.013921339 | AX76: 45406 | AY76: 29.7 | BC76: =AY76+AY76*AZ76+AY76*BA76-BB76*BA76 -> 29.7 | BE76: =LN((BC76+BD76)/BC75) -> -0.013378126 | BF76: 45406 | BG76: 146.8 | BK76: =BG76+BG76*BH76+BG76*BI76-BJ76*BI76 -> 146.8 | BM76: =LN((BK76+BL76)/BK75) -> -0.0047570596
B77: 45407 | C77: 10.7 | G77: =C77+C77*D77+C77*E77-F77*E77 -> 10.7 | I77: =LN((G77+H77)/G76) -> -0.0093023927 | J77: 45407 | K77: 31.2 | O77: =K77+K77*L77+K77*M77-N77*M77 -> 31.2 | Q77: =LN((O77+P77)/O76) -> -0.022187915 | R77: 45407 | S77: 235 | W77: =S77+S77*T77+S77*U77-V77*U77 -> 235 | Y77: =LN((W77+X77)/W76) -> 0.010695289 | Z77: 45407 | AA77: 941 | AE77: =AA77+AA77*AB77+AA77*AC77-AD77*AC77 -> 941 | AG77: =LN((AE77+AF77)/AE76) -> -0.038464276 | AH77: 45407 | AI77: 759.9 | AM77: =AI77+AI77*AJ77+AI77*AK77-AL77*AK77 -> 759.9 | AO77: =LN((AM77+AN77)/AM76) -> -0.030456576 | AP77: 45407 | AQ77: 627.7 | AU77: =AQ77+AQ77*AR77+AQ77*AS77-AT77*AS77 -> 627.7 | AW77: =LN((AU77+AV77)/AU76) -> -0.022525958 | AX77: 45407 | AY77: 29.3 | BC77: =AY77+AY77*AZ77+AY77*BA77-BB77*BA77 -> 29.3 | BE77: =LN((BC77+BD77)/BC76) -> -0.01355953 | BF77: 45407 | BG77: 143.4 | BK77: =BG77+BG77*BH77+BG77*BI77-BJ77*BI77 -> 143.4 | BM77: =LN((BK77+BL77)/BK76) -> -0.023433188
B78: 45410 | C78: 10.7 | G78: =C78+C78*D78+C78*E78-F78*E78 -> 10.7 | I78: =LN((G78+H78)/G77) -> 0 | J78: 45410 | K78: 32.4 | O78: =K78+K78*L78+K78*M78-N78*M78 -> 32.4 | Q78: =LN((O78+P78)/O77) -> 0.037740328 | R78: 45410 | S78: 240.5 | W78: =S78+S78*T78+S78*U78-V78*U78 -> 240.5 | Y78: =LN((W78+X78)/W77) -> 0.023134575 | Z78: 45410 | AA78: 979.2 | AE78: =AA78+AA78*AB78+AA78*AC78-AD78*AC78 -> 979.2 | AG78: =LN((AE78+AF78)/AE77) -> 0.039792772 | AH78: 45410 | AI78: 771.7 | AM78: =AI78+AI78*AJ78+AI78*AK78-AL78*AK78 -> 771.7 | AO78: =LN((AM78+AN78)/AM77) -> 0.015409028 | AP78: 45410 | AQ78: 634 | AU78: =AQ78+AQ78*AR78+AQ78*AS78-AT78*AS78 -> 634 | AW78: =LN((AU78+AV78)/AU77) -> 0.0099866091 | AX78: 45410 | AY78: 29.8 | BC78: =AY78+AY78*AZ78+AY78*BA78-BB78*BA78 -> 29.8 | BE78: =LN((BC78+BD78)/BC77) -> 0.016920877 | BF78: 45410 | BG78: 143.9 | BK78: =BG78+BG78*BH78+BG78*BI78-BJ78*BI78 -> 143.9 | BM78: =LN((BK78+BL78)/BK77) -> 0.0034806857
B79: 45411 | C79: 10.8 | G79: =C79+C79*D79+C79*E79-F79*E79 -> 10.8 | I79: =LN((G79+H79)/G78) -> 0.0093023927 | J79: 45411 | K79: 32.7 | O79: =K79+K79*L79+K79*M79-N79*M79 -> 32.7 | Q79: =LN((O79+P79)/O78) -> 0.0092166551 | R79: 45411 | S79: 236.5 | W79: =S79+S79*T79+S79*U79-V79*U79 -> 236.5 | Y79: =LN((W79+X79)/W78) -> -0.016771882 | Z79: 45411 | AA79: 975.8 | AE79: =AA79+AA79*AB79+AA79*AC79-AD79*AC79 -> 975.8 | AG79: =LN((AE79+AF79)/AE78) -> -0.0034782644 | AH79: 45411 | AI79: 767.2 | AM79: =AI79+AI79*AJ79+AI79*AK79-AL79*AK79 -> 767.2 | AO79: =LN((AM79+AN79)/AM78) -> -0.0058483499 | AP79: 45411 | AQ79: 623.7 | AU79: =AQ79+AQ79*AR79+AQ79*AS79-AT79*AS79 -> 623.7 | AW79: =LN((AU79+AV79)/AU78) -> -0.016379471 | AX79: 45411 | AY79: 29 | BC79: =AY79+AY79*AZ79+AY79*BA79-BB79*BA79 -> 29 | BE79: =LN((BC79+BD79)/BC78) -> -0.027212564 | BF79: 45411 | BG79: 142.7 | BK79: =BG79+BG79*BH79+BG79*BI79-BJ79*BI79 -> 142.7 | BM79: =LN((BK79+BL79)/BK78) -> -0.0083740894
... B91: 45428 | C91: 10.5 | G91: =C91+C91*D91+C91*E91-F91*E91 -> 10.5 | I91: =LN((G91+H91)/G90) -> 0 | J91: 45428 | K91: 32.1 | O91: =K91+K91*L91+K91*M91-N91*M91 -> 32.1 | Q91: =LN((O91+P91)/O90) -> -0.0062112001 | R91: 45428 | S91: 232.3 | W91: =S91+S91*T91+S91*U91-V91*U91 -> 232.3 | Y91: =LN((W91+X91)/W90) -> -0.0055806112 | Z91: 45428 | AA91: 954.9 | AE91: =AA91+AA91*AB91+AA91*AC91-AD91*AC91 -> 954.9 | AG91: =LN((AE91+AF91)/AE90) -> 0 | AH91: 45428 | AI91: 699.5 | AM91: =AI91+AI91*AJ91+AI91*AK91-AL91*AK91 -> 699.5 | AO91: =LN((AM91+AN91)/AM90) -> -0.01377178 | AP91: 45428 | AQ91: 580.1 | AU91: =AQ91+AQ91*AR91+AQ91*AS91-AT91*AS91 -> 580.1 | AW91: =LN((AU91+AV91)/AU90) -> -0.00068929867 | AX91: 45428 | AY91: 27.8 | BC91: =AY91+AY91*AZ91+AY91*BA91-BB91*BA91 -> 27.8 | BE91: =LN((BC91+BD91)/BC90) -> 0 | BF91: 45428 | BG91: 131.4 | BK91: =BG91+BG91*BH91+BG91*BI91-BJ91*BI91 -> 131.4 | BM91: =LN((BK91+BL91)/BK90) -> -0.0098448353
B92: 45431 | C92: 10.5 | G92: =C92+C92*D92+C92*E92-F92*E92 -> 10.5 | I92: =LN((G92+H92)/G91) -> 0 | J92: 45431 | K92: 31.2 | O92: =K92+K92*L92+K92*M92-N92*M92 -> 31.2 | Q92: =LN((O92+P92)/O91) -> -0.028437935 | R92: 45431 | S92: 225.8 | W92: =S92+S92*T92+S92*U92-V92*U92 -> 225.8 | Y92: =LN((W92+X92)/W91) -> -0.028379988 | Z92: 45431 | AA92: 945.9 | AE92: =AA92+AA92*AB92+AA92*AC92-AD92*AC92 -> 945.9 | AF92: 10.5 | AG92: =LN((AE92+AF92)/AE91) -> 0.0015696126 | AH92: 45431 | AI92: 680.5 | AM92: =AI92+AI92*AJ92+AI92*AK92-AL92*AK92 -> 680.5 | AO92: =LN((AM92+AN92)/AM91) -> -0.027537972 | AP92: 45431 | AQ92: 562.7 | AU92: =AQ92+AQ92*AR92+AQ92*AS92-AT92*AS92 -> 562.7 | AW92: =LN((AU92+AV92)/AU91) -> -0.030453876 | AX92: 45431 | AY92: 27 | BC92: =AY92+AY92*AZ92+AY92*BA92-BB92*BA92 -> 27 | BE92: =LN((BC92+BD92)/BC91) -> -0.029199155 | BF92: 45431 | BG92: 130.9 | BK92: =BG92+BG92*BH92+BG92*BI92-BJ92*BI92 -> 130.9 | BM92: =LN((BK92+BL92)/BK91) -> -0.0038124331
B93: 45432 | C93: 10.2 | G93: =C93+C93*D93+C93*E93-F93*E93 -> 10.2 | I93: =LN((G93+H93)/G92) -> -0.028987537 | J93: 45432 | K93: 31 | O93: =K93+K93*L93+K93*M93-N93*M93 -> 31 | Q93: =LN((O93+P93)/O92) -> -0.0064308903 | R93: 45432 | S93: 224.4 | W93: =S93+S93*T93+S93*U93-V93*U93 -> 224.4 | Y93: =LN((W93+X93)/W92) -> -0.0062194781 | Z93: 45432 | AA93: 933 | AE93: =AA93+AA93*AB93+AA93*AC93-AD93*AC93 -> 933 | AG93: =LN((AE93+AF93)/AE92) -> -0.013731654 | AH93: 45432 | AI93: 677 | AM93: =AI93+AI93*AJ93+AI93*AK93-AL93*AK93 -> 677 | AO93: =LN((AM93+AN93)/AM92) -> -0.0051565492 | AP93: 45432 | AQ93: 547.1 | AU93: =AQ93+AQ93*AR93+AQ93*AS93-AT93*AS93 -> 547.1 | AW93: =LN((AU93+AV93)/AU92) -> -0.028115025 | AX93: 45432 | AY93: 26.4 | BC93: =AY93+AY93*AZ93+AY93*BA93-BB93*BA93 -> 26.4 | BE93: =LN((BC93+BD93)/BC92) -> -0.022472856 | BF93: 45432 | BG93: 128.5 | BK93: =BG93+BG93*BH93+BG93*BI93-BJ93*BI93 -> 128.5 | BM93: =LN((BK93+BL93)/BK92) -> -0.018504769
B94: 45433 | C94: 10.2 | G94: =C94+C94*D94+C94*E94-F94*E94 -> 10.2 | I94: =LN((G94+H94)/G93) -> 0 | J94: 45433 | K94: 31.2 | O94: =K94+K94*L94+K94*M94-N94*M94 -> 31.2 | Q94: =LN((O94+P94)/O93) -> 0.0064308903 | R94: 45433 | S94: 225.3 | W94: =S94+S94*T94+S94*U94-V94*U94 -> 225.3 | Y94: =LN((W94+X94)/W93) -> 0.0040026738 | Z94: 45433 | AA94: 949 | AE94: =AA94+AA94*AB94+AA94*AC94-AD94*AC94 -> 949 | AG94: =LN((AE94+AF94)/AE93) -> 0.017003598 | AH94: 45433 | AI94: 670.4 | AM94: =AI94+AI94*AJ94+AI94*AK94-AL94*AK94 -> 670.4 | AO94: =LN((AM94+AN94)/AM93) -> -0.0097967237 | AP94: 45433 | AQ94: 545.7 | AU94: =AQ94+AQ94*AR94+AQ94*AS94-AT94*AS94 -> 545.7 | AW94: =LN((AU94+AV94)/AU93) -> -0.0025622269 | AX94: 45433 | AY94: 26.4 | BC94: =AY94+AY94*AZ94+AY94*BA94-BB94*BA94 -> 26.4 | BE94: =LN((BC94+BD94)/BC93) -> 0 | BF94: 45433 | BG94: 127.3 | BK94: =BG94+BG94*BH94+BG94*BI94-BJ94*BI94 -> 127.3 | BM94: =LN((BK94+BL94)/BK93) -> -0.0093823988
B95: 45435 | C95: 10.2 | G95: =C95+C95*D95+C95*E95-F95*E95 -> 10.2 | I95: =LN((G95+H95)/G94) -> 0 | J95: 45435 | K95: 30.3 | O95: =K95+K95*L95+K95*M95-N95*M95 -> 30.3 | Q95: =LN((O95+P95)/O94) -> -0.029270382 | R95: 45435 | S95: 224.9 | W95: =S95+S95*T95+S95*U95-V95*U95 -> 224.9 | Y95: =LN((W95+X95)/W94) -> -0.0017769885 | Z95: 45435 | AA95: 940.6 | AE95: =AA95+AA95*AB95+AA95*AC95-AD95*AC95 -> 940.6 | AG95: =LN((AE95+AF95)/AE94) -> -0.0088908291 | AH95: 45435 | AI95: 650.7 | AM95: =AI95+AI95*AJ95+AI95*AK95-AL95*AK95 -> 650.7 | AO95: =LN((AM95+AN95)/AM94) -> -0.029825843 | AP95: 45435 | AQ95: 537.4 | AU95: =AQ95+AQ95*AR95+AQ95*AS95-AT95*AS95 -> 537.4 | AW95: =LN((AU95+AV95)/AU94) -> -0.015326678 | AX95: 45435 | AY95: 25.8 | BC95: =AY95+AY95*AZ95+AY95*BA95-BB95*BA95 -> 25.8 | BE95: =LN((BC95+BD95)/BC94) -> -0.022989518 | BF95: 45435 | BG95: 129.3 | BK95: =BG95+BG95*BH95+BG95*BI95-BJ95*BI95 -> 129.3 | BM95: =LN((BK95+BL95)/BK94) -> 0.01558878
B96: 45438 | C96: 9.9 | D96: 0.05 | G96: =C96+C96*D96+C96*E96-F96*E96 -> 10.395 | H96: 0.5 | I96: =LN((G96+H96)/G95) -> 0.065916248 | J96: 45438 | K96: 29.9 | O96: =K96+K96*L96+K96*M96-N96*M96 -> 29.9 | Q96: =LN((O96+P96)/O95) -> -0.013289232 | R96: 45438 | S96: 226 | W96: =S96+S96*T96+S96*U96-V96*U96 -> 226 | Y96: =LN((W96+X96)/W95) -> 0.0048791403 | Z96: 45438 | AA96: 938.1 | AE96: =AA96+AA96*AB96+AA96*AC96-AD96*AC96 -> 938.1 | AG96: =LN((AE96+AF96)/AE95) -> -0.0026614164 | AH96: 45438 | AI96: 631.5 | AM96: =AI96+AI96*AJ96+AI96*AK96-AL96*AK96 -> 631.5 | AO96: =LN((AM96+AN96)/AM95) -> -0.029950765 | AP96: 45438 | AQ96: 522.4 | AU96: =AQ96+AQ96*AR96+AQ96*AS96-AT96*AS96 -> 522.4 | AW96: =LN((AU96+AV96)/AU95) -> -0.028309118 | AX96: 45438 | AY96: 25.4 | BC96: =AY96+AY96*AZ96+AY96*BA96-BB96*BA96 -> 25.4 | BE96: =LN((BC96+BD96)/BC95) -> -0.015625318 | BF96: 45438 | BG96: 129.5 | BK96: =BG96+BG96*BH96+BG96*BI96-BJ96*BI96 -> 129.5 | BM96: =LN((BK96+BL96)/BK95) -> 0.0015455954
B97: 45439 | C97: 9.7 | G97: =C97+C97*D97+C97*E97-F97*E97 -> 9.7 | I97: =LN((G97+H97)/G96) -> -0.069199036 | J97: 45439 | K97: 31 | O97: =K97+K97*L97+K97*M97-N97*M97 -> 31 | Q97: =LN((O97+P97)/O96) -> 0.036128724 | R97: 45439 | S97: 229.3 | W97: =S97+S97*T97+S97*U97-V97*U97 -> 229.3 | Y97: =LN((W97+X97)/W96) -> 0.014496191 | Z97: 45439 | AA97: 963.7 | AE97: =AA97+AA97*AB97+AA97*AC97-AD97*AC97 -> 963.7 | AG97: =LN((AE97+AF97)/AE96) -> 0.02692349 | AH97: 45439 | AI97: 634.9 | AM97: =AI97+AI97*AJ97+AI97*AK97-AL97*AK97 -> 634.9 | AO97: =LN((AM97+AN97)/AM96) -> 0.0053695644 | AP97: 45439 | AQ97: 521.4 | AU97: =AQ97+AQ97*AR97+AQ97*AS97-AT97*AS97 -> 521.4 | AW97: =LN((AU97+AV97)/AU96) -> -0.0019160765 | AX97: 45439 | AY97: 26.1 | BC97: =AY97+AY97*AZ97+AY97*BA97-BB97*BA97 -> 26.1 | BE97: =LN((BC97+BD97)/BC96) -> 0.02718614 | BF97: 45439 | BG97: 129.6 | BK97: =BG97+BG97*BH97+BG97*BI97-BJ97*BI97 -> 129.6 | BM97: =LN((BK97+BL97)/BK96) -> 0.00077190278
B98: 45440 | C98: 9.5 | G98: =C98+C98*D98+C98*E98-F98*E98 -> 9.5 | I98: =LN((G98+H98)/G97) -> -0.020834087 | J98: 45440 | K98: 30.2 | O98: =K98+K98*L98+K98*M98-N98*M98 -> 30.2 | Q98: =LN((O98+P98)/O97) -> -0.02614528 | R98: 45440 | S98: 225.5 | W98: =S98+S98*T98+S98*U98-V98*U98 -> 225.5 | Y98: =LN((W98+X98)/W97) -> -0.016711031 | Z98: 45440 | AA98: 954.1 | AE98: =AA98+AA98*AB98+AA98*AC98-AD98*AC98 -> 954.1 | AG98: =LN((AE98+AF98)/AE97) -> -0.010011555 | AH98: 45440 | AI98: 636.5 | AM98: =AI98+AI98*AJ98+AI98*AK98-AL98*AK98 -> 636.5 | AO98: =LN((AM98+AN98)/AM97) -> 0.0025169118 | AP98: 45440 | AQ98: 526.4 | AU98: =AQ98+AQ98*AR98+AQ98*AS98-AT98*AS98 -> 526.4 | AW98: =LN((AU98+AV98)/AU97) -> 0.0095438785 | AX98: 45440 | AY98: 26.2 | BC98: =AY98+AY98*AZ98+AY98*BA98-BB98*BA98 -> 26.2 | BE98: =LN((BC98+BD98)/BC97) -> 0.0038240964 | BF98: 45440 | BG98: 132 | BK98: =BG98+BG98*BH98+BG98*BI98-BJ98*BI98 -> 132 | BM98: =LN((BK98+BL98)/BK97) -> 0.018349139
B99: 45441 | C99: 9.5 | G99: =C99+C99*D99+C99*E99-F99*E99 -> 9.5 | I99: =LN((G99+H99)/G98) -> 0 | J99: 45441 | K99: 29.5 | O99: =K99+K99*L99+K99*M99-N99*M99 -> 29.5 | Q99: =LN((O99+P99)/O98) -> -0.023451661 | R99: 45441 | S99: 227.7 | W99: =S99+S99*T99+S99*U99-V99*U99 -> 227.7 | Y99: =LN((W99+X99)/W98) -> 0.0097088141 | Z99: 45441 | AA99: 968.9 | AE99: =AA99+AA99*AB99+AA99*AC99-AD99*AC99 -> 968.9 | AG99: =LN((AE99+AF99)/AE98) -> 0.01539292 | AH99: 45441 | AI99: 635.6 | AM99: =AI99+AI99*AJ99+AI99*AK99-AL99*AK99 -> 635.6 | AO99: =LN((AM99+AN99)/AM98) -> -0.0014149833 | AP99: 45441 | AQ99: 512.4 | AU99: =AQ99+AQ99*AR99+AQ99*AS99-AT99*AS99 -> 512.4 | AW99: =LN((AU99+AV99)/AU98) -> -0.02695581 | AX99: 45441 | AY99: 25.5 | BC99: =AY99+AY99*AZ99+AY99*BA99-BB99*BA99 -> 25.5 | BE99: =LN((BC99+BD99)/BC98) -> -0.027080959 | BF99: 45441 | BG99: 129.3 | BK99: =BG99+BG99*BH99+BG99*BI99-BJ99*BI99 -> 129.3 | BM99: =LN((BK99+BL99)/BK98) -> -0.020666637
B100: 45442 | C100: 9.4 | G100: =C100+C100*D100+C100*E100-F100*E100 -> 9.4 | I100: =LN((G100+H100)/G99) -> -0.010582109 | J100: 45442 | K100: 30.6 | O100: =K100+K100*L100+K100*M100-N100*M100 -> 30.6 | Q100: =LN((O100+P100)/O99) -> 0.036609746 | R100: 45442 | S100: 223.5 | W100: =S100+S100*T100+S100*U100-V100*U100 -> 223.5 | Y100: =LN((W100+X100)/W99) -> -0.018617559 | Z100: 45442 | AA100: 939.9 | AE100: =AA100+AA100*AB100+AA100*AC100-AD100*AC100 -> 939.9 | AG100: =LN((AE100+AF100)/AE99) -> -0.030387921 | AH100: 45442 | AI100: 634.2 | AM100: =AI100+AI100*AJ100+AI100*AK100-AL100*AK100 -> 634.2 | AO100: =LN((AM100+AN100)/AM99) -> -0.0022050726 | AP100: 45442 | AQ100: 514.3 | AU100: =AQ100+AQ100*AR100+AQ100*AS100-AT100*AS100 -> 514.3 | AW100: =LN((AU100+AV100)/AU99) -> 0.0037011828 | AX100: 45442 | AY100: 25.9 | BC100: =AY100+AY100*AZ100+AY100*BA100-BB100*BA100 -> 25.9 | BE100: =LN((BC100+BD100)/BC99) -> 0.015564517 | BF100: 45442 | BG100: 131.8 | BK100: =BG100+BG100*BH100+BG100*BI100-BJ100*BI100 -> 131.8 | BM100: =LN((BK100+BL100)/BK99) -> 0.019150336
B101: 45445 | C101: 9.5 | G101: =C101+C101*D101+C101*E101-F101*E101 -> 9.5 | I101: =LN((G101+H101)/G100) -> 0.010582109 | J101: 45445 | K101: 29.7 | O101: =K101+K101*L101+K101*M101-N101*M101 -> 29.7 | Q101: =LN((O101+P101)/O100) -> -0.029852963 | R101: 45445 | S101: 225.4 | W101: =S101+S101*T101+S101*U101-V101*U101 -> 225.4 | Y101: =LN((W101+X101)/W100) -> 0.0084651876 | Z101: 45445 | AA101: 951.7 | AE101: =AA101+AA101*AB101+AA101*AC101-AD101*AC101 -> 951.7 | AG101: =LN((AE101+AF101)/AE100) -> 0.012476372 | AH101: 45445 | AI101: 638.5 | AM101: =AI101+AI101*AJ101+AI101*AK101-AL101*AK101 -> 638.5 | AO101: =LN((AM101+AN101)/AM100) -> 0.0067573134 | AP101: 45445 | AQ101: 511.1 | AU101: =AQ101+AQ101*AR101+AQ101*AS101-AT101*AS101 -> 511.1 | AW101: =LN((AU101+AV101)/AU100) -> -0.006241487 | AX101: 45445 | AY101: 25.6 | BC101: =AY101+AY101*AZ101+AY101*BA101-BB101*BA101 -> 25.6 | BE101: =LN((BC101+BD101)/BC100) -> -0.011650617 | BF101: 45445 | BG101: 131.8 | BK101: =BG101+BG101*BH101+BG101*BI101-BJ101*BI101 -> 131.8 | BM101: =LN((BK101+BL101)/BK100) -> 0
B102: 45446 | C102: 9.5 | G102: =C102+C102*D102+C102*E102-F102*E102 -> 9.5 | I102: =LN((G102+H102)/G101) -> 0 | J102: 45446 | K102: 29.6 | O102: =K102+K102*L102+K102*M102-N102*M102 -> 29.6 | Q102: =LN((O102+P102)/O101) -> -0.0033726845 | R102: 45446 | S102: 225.7 | W102: =S102+S102*T102+S102*U102-V102*U102 -> 225.7 | Y102: =LN((W102+X102)/W101) -> 0.0013300822 | Z102: 45446 | AA102: 926.6 | AE102: =AA102+AA102*AB102+AA102*AC102-AD102*AC102 -> 926.6 | AG102: =LN((AE102+AF102)/AE101) -> -0.026727886 | AH102: 45446 | AI102: 639.8 | AM102: =AI102+AI102*AJ102+AI102*AK102-AL102*AK102 -> 639.8 | AO102: =LN((AM102+AN102)/AM101) -> 0.002033952 | AP102: 45446 | AQ102: 500.2 | AU102: =AQ102+AQ102*AR102+AQ102*AS102-AT102*AS102 -> 500.2 | AW102: =LN((AU102+AV102)/AU101) -> -0.021557247 | AX102: 45446 | AY102: 26 | BC102: =AY102+AY102*AZ102+AY102*BA102-BB102*BA102 -> 26 | BE102: =LN((BC102+BD102)/BC101) -> 0.015504187 | BF102: 45446 | BG102: 132.1 | BK102: =BG102+BG102*BH102+BG102*BI102-BJ102*BI102 -> 132.1 | BM102: =LN((BK102+BL102)/BK101) -> 0.0022735895
B103: 45447 | C103: 9 | G103: =C103+C103*D103+C103*E103-F103*E103 -> 9 | I103: =LN((G103+H103)/G102) -> -0.054067221 | J103: 45447 | K103: 29.9 | O103: =K103+K103*L103+K103*M103-N103*M103 -> 29.9 | Q103: =LN((O103+P103)/O102) -> 0.010084119 | R103: 45447 | S103: 227.5 | W103: =S103+S103*T103+S103*U103-V103*U103 -> 227.5 | Y103: =LN((W103+X103)/W102) -> 0.0079435546 | Z103: 45447 | AA103: 931.9 | AE103: =AA103+AA103*AB103+AA103*AC103-AD103*AC103 -> 931.9 | AG103: =LN((AE103+AF103)/AE102) -> 0.0057035398 | AH103: 45447 | AI103: 643.8 | AM103: =AI103+AI103*AJ103+AI103*AK103-AL103*AK103 -> 643.8 | AO103: =LN((AM103+AN103)/AM102) -> 0.0062324913 | AP103: 45447 | AQ103: 499.1 | AU103: =AQ103+AQ103*AR103+AQ103*AS103-AT103*AS103 -> 499.1 | AW103: =LN((AU103+AV103)/AU102) -> -0.002201542 | AX103: 45447 | AY103: 26.5 | BC103: =AY103+AY103*AZ103+AY103*BA103-BB103*BA103 -> 26.5 | BE103: =LN((BC103+BD103)/BC102) -> 0.019048195 | BF103: 45447 | BG103: 132 | BK103: =BG103+BG103*BH103+BG103*BI103-BJ103*BI103 -> 132 | BM103: =LN((BK103+BL103)/BK102) -> -0.00075728894
B104: 45448 | C104: 9 | G104: =C104+C104*D104+C104*E104-F104*E104 -> 9 | I104: =LN((G104+H104)/G103) -> 0 | J104: 45448 | K104: 29.4 | O104: =K104+K104*L104+K104*M104-N104*M104 -> 29.4 | Q104: =LN((O104+P104)/O103) -> -0.016863806 | R104: 45448 | S104: 226.2 | W104: =S104+S104*T104+S104*U104-V104*U104 -> 226.2 | Y104: =LN((W104+X104)/W103) -> -0.0057306747 | Z104: 45448 | AA104: 936.4 | AE104: =AA104+AA104*AB104+AA104*AC104-AD104*AC104 -> 936.4 | AG104: =LN((AE104+AF104)/AE103) -> 0.0048172228 | AH104: 45448 | AI104: 639.8 | AM104: =AI104+AI104*AJ104+AI104*AK104-AL104*AK104 -> 639.8 | AO104: =LN((AM104+AN104)/AM103) -> -0.0062324913 | AP104: 45448 | AQ104: 490.4 | AU104: =AQ104+AQ104*AR104+AQ104*AS104-AT104*AS104 -> 490.4 | AW104: =LN((AU104+AV104)/AU103) -> -0.017585092 | AX104: 45448 | AY104: 25.8 | BC104: =AY104+AY104*AZ104+AY104*BA104-BB104*BA104 -> 25.8 | BE104: =LN((BC104+BD104)/BC103) -> -0.026770241 | BF104: 45448 | BG104: 129.3 | BK104: =BG104+BG104*BH104+BG104*BI104-BJ104*BI104 -> 129.3 | BM104: =LN((BK104+BL104)/BK103) -> -0.020666637
B105: 45449 | C105: 8.9 | G105: =C105+C105*D105+C105*E105-F105*E105 -> 8.9 | I105: =LN((G105+H105)/G104) -> -0.011173301 | J105: 45449 | K105: 29.4 | O105: =K105+K105*L105+K105*M105-N105*M105 -> 29.4 | Q105: =LN((O105+P105)/O104) -> 0 | R105: 45449 | S105: 227.6 | W105: =S105+S105*T105+S105*U105-V105*U105 -> 227.6 | Y105: =LN((W105+X105)/W104) -> 0.0061701386 | Z105: 45449 | AA105: 926.5 | AE105: =AA105+AA105*AB105+AA105*AC105-AD105*AC105 -> 926.5 | AG105: =LN((AE105+AF105)/AE104) -> -0.01062869 | AH105: 45449 | AI105: 635 | AM105: =AI105+AI105*AJ105+AI105*AK105-AL105*AK105 -> 635 | AO105: =LN((AM105+AN105)/AM104) -> -0.0075306286 | AP105: 45449 | AQ105: 478.1 | AU105: =AQ105+AQ105*AR105+AQ105*AS105-AT105*AS105 -> 478.1 | AW105: =LN((AU105+AV105)/AU104) -> -0.025401469 | AX105: 45449 | AY105: 25.8 | BC105: =AY105+AY105*AZ105+AY105*BA105-BB105*BA105 -> 25.8 | BE105: =LN((BC105+BD105)/BC104) -> 0 | BF105: 45449 | BG105: 127.1 | BK105: =BG105+BG105*BH105+BG105*BI105-BJ105*BI105 -> 127.1 | BM105: =LN((BK105+BL105)/BK104) -> -0.017161108
B106: 45452 | C106: 8.7 | G106: =C106+C106*D106+C106*E106-F106*E106 -> 8.7 | I106: =LN((G106+H106)/G105) -> -0.022728251 | J106: 45452 | K106: 29.1 | O106: =K106+K106*L106+K106*M106-N106*M106 -> 29.1 | Q106: =LN((O106+P106)/O105) -> -0.0102565 | R106: 45452 | S106: 229.1 | W106: =S106+S106*T106+S106*U106-V106*U106 -> 229.1 | Y106: =LN((W106+X106)/W105) -> 0.0065688872 | Z106: 45452 | AA106: 931.4 | AE106: =AA106+AA106*AB106+AA106*AC106-AD106*AC106 -> 931.4 | AG106: =LN((AE106+AF106)/AE105) -> 0.0052747848 | AH106: 45452 | AI106: 629.8 | AM106: =AI106+AI106*AJ106+AI106*AK106-AL106*AK106 -> 629.8 | AO106: =LN((AM106+AN106)/AM105) -> -0.0082226902 | AP106: 45452 | AQ106: 465.3 | AU106: =AQ106+AQ106*AR106+AQ106*AS106-AT106*AS106 -> 465.3 | AW106: =LN((AU106+AV106)/AU105) -> -0.027137557 | AX106: 45452 | AY106: 25.2 | BC106: =AY106+AY106*AZ106+AY106*BA106-BB106*BA106 -> 25.2 | BE106: =LN((BC106+BD106)/BC105) -> -0.023530497 | BF106: 45452 | BG106: 123.4 | BK106: =BG106+BG106*BH106+BG106*BI106-BJ106*BI106 -> 123.4 | BM106: =LN((BK106+BL106)/BK105) -> -0.029543067
B107: 45453 | C107: 8.7 | G107: =C107+C107*D107+C107*E107-F107*E107 -> 8.7 | I107: =LN((G107+H107)/G106) -> 0 | J107: 45453 | K107: 28.5 | O107: =K107+K107*L107+K107*M107-N107*M107 -> 28.5 | Q107: =LN((O107+P107)/O106) -> -0.020834087 | R107: 45453 | S107: 225.4 | W107: =S107+S107*T107+S107*U107-V107*U107 -> 225.4 | Y107: =LN((W107+X107)/W106) -> -0.016281988 | Z107: 45453 | AA107: 910.2 | AE107: =AA107+AA107*AB107+AA107*AC107-AD107*AC107 -> 910.2 | AG107: =LN((AE107+AF107)/AE106) -> -0.023024475 | AH107: 45453 | AI107: 613.8 | AM107: =AI107+AI107*AJ107+AI107*AK107-AL107*AK107 -> 613.8 | AO107: =LN((AM107+AN107)/AM106) -> -0.025733166 | AP107: 45453 | AQ107: 451.9 | AU107: =AQ107+AQ107*AR107+AQ107*AS107-AT107*AS107 -> 451.9 | AW107: =LN((AU107+AV107)/AU106) -> -0.029221442 | AX107: 45453 | AY107: 24.6 | BC107: =AY107+AY107*AZ107+AY107*BA107-BB107*BA107 -> 24.6 | BE107: =LN((BC107+BD107)/BC106) -> -0.024097552 | BF107: 45453 | BG107: 120 | BK107: =BG107+BG107*BH107+BG107*BI107-BJ107*BI107 -> 120 | BM107: =LN((BK107+BL107)/BK106) -> -0.027939369
B108: 45454 | C108: 8.8 | G108: =C108+C108*D108+C108*E108-F108*E108 -> 8.8 | I108: =LN((G108+H108)/G107) -> 0.011428696 | J108: 45454 | K108: 27.9 | O108: =K108+K108*L108+K108*M108-N108*M108 -> 27.9 | Q108: =LN((O108+P108)/O107) -> -0.021277398 | R108: 45454 | S108: 223.5 | W108: =S108+S108*T108+S108*U108-V108*U108 -> 223.5 | Y108: =LN((W108+X108)/W107) -> -0.0084651876 | Z108: 45454 | AA108: 901.7 | AE108: =AA108+AA108*AB108+AA108*AC108-AD108*AC108 -> 901.7 | AG108: =LN((AE108+AF108)/AE107) -> -0.0093824851 | AH108: 45454 | AI108: 610.5 | AM108: =AI108+AI108*AJ108+AI108*AK108-AL108*AK108 -> 610.5 | AO108: =LN((AM108+AN108)/AM107) -> -0.0053908486 | AP108: 45454 | AQ108: 439.9 | AU108: =AQ108+AQ108*AR108+AQ108*AS108-AT108*AS108 -> 439.9 | AW108: =LN((AU108+AV108)/AU107) -> -0.026913488 | AX108: 45454 | AY108: 24.1 | BC108: =AY108+AY108*AZ108+AY108*BA108-BB108*BA108 -> 24.1 | BE108: =LN((BC108+BD108)/BC107) -> -0.020534602 | BF108: 45454 | BG108: 118.2 | BK108: =BG108+BG108*BH108+BG108*BI108-BJ108*BI108 -> 118.2 | BM108: =LN((BK108+BL108)/BK107) -> -0.015113638
... B118: 45473 | C118: 8.3 | G118: =C118+C118*D118+C118*E118-F118*E118 -> 8.3 | I118: =LN((G118+H118)/G117) -> -0.023810649 | J118: 45473 | K118: 29.5 | O118: =K118+K118*L118+K118*M118-N118*M118 -> 29.5 | Q118: =LN((O118+P118)/O117) -> -0.020134908 | R118: 45473 | S118: 247.7 | W118: =S118+S118*T118+S118*U118-V118*U118 -> 247.7 | Y118: =LN((W118+X118)/W117) -> 0.025763028 | Z118: 45473 | AA118: 977.2 | AE118: =AA118+AA118*AB118+AA118*AC118-AD118*AC118 -> 977.2 | AG118: =LN((AE118+AF118)/AE117) -> 0.019321777 | AH118: 45473 | AI118: 770.1 | AM118: =AI118+AI118*AJ118+AI118*AK118-AL118*AK118 -> 770.1 | AO118: =LN((AM118+AN118)/AM117) -> 0.0054687636 | AP118: 45473 | AQ118: 649.4 | AU118: =AQ118+AQ118*AR118+AQ118*AS118-AT118*AS118 -> 649.4 | AW118: =LN((AU118+AV118)/AU117) -> -0.0047622795 | AX118: 45473 | AY118: 26.2 | BC118: =AY118+AY118*AZ118+AY118*BA118-BB118*BA118 -> 26.2 | BE118: =LN((BC118+BD118)/BC117) -> -0.015151805 | BF118: 45473 | BG118: 132.4 | BK118: =BG118+BG118*BH118+BG118*BI118-BJ118*BI118 -> 132.4 | BM118: =LN((BK118+BL118)/BK117) -> -0.0060241146
A119: 2024 Q3 | B119: 45475 | C119: 8.3 | G119: =C119+C119*D119+C119*E119-F119*E119 -> 8.3 | I119: =LN((G119+H119)/G118) -> 0 | J119: 45475 | K119: 29.4 | O119: =K119+K119*L119+K119*M119-N119*M119 -> 29.4 | Q119: =LN((O119+P119)/O118) -> -0.003395589 | R119: 45475 | S119: 244 | W119: =S119+S119*T119+S119*U119-V119*U119 -> 244 | Y119: =LN((W119+X119)/W118) -> -0.015050111 | Z119: 45475 | AA119: 955.2 | AE119: =AA119+AA119*AB119+AA119*AC119-AD119*AC119 -> 955.2 | AG119: =LN((AE119+AF119)/AE118) -> -0.022770597 | AH119: 45475 | AI119: 756.6 | AM119: =AI119+AI119*AJ119+AI119*AK119-AL119*AK119 -> 756.6 | AO119: =LN((AM119+AN119)/AM118) -> -0.017685664 | AP119: 45475 | AQ119: 648.4 | AU119: =AQ119+AQ119*AR119+AQ119*AS119-AT119*AS119 -> 648.4 | AW119: =LN((AU119+AV119)/AU118) -> -0.0015410698 | AX119: 45475 | AY119: 25.9 | BC119: =AY119+AY119*AZ119+AY119*BA119-BB119*BA119 -> 25.9 | BE119: =LN((BC119+BD119)/BC118) -> -0.011516442 | BF119: 45475 | BG119: 129.8 | BK119: =BG119+BG119*BH119+BG119*BI119-BJ119*BI119 -> 129.8 | BM119: =LN((BK119+BL119)/BK118) -> -0.019832839
B120: 45476 | C120: 8.5 | G120: =C120+C120*D120+C120*E120-F120*E120 -> 8.5 | I120: =LN((G120+H120)/G119) -> 0.023810649 | J120: 45476 | K120: 30.4 | O120: =K120+K120*L120+K120*M120-N120*M120 -> 30.4 | Q120: =LN((O120+P120)/O119) -> 0.033447934 | R120: 45476 | S120: 240.2 | W120: =S120+S120*T120+S120*U120-V120*U120 -> 240.2 | Y120: =LN((W120+X120)/W119) -> -0.015696316 | Z120: 45476 | AA120: 955.6 | AE120: =AA120+AA120*AB120+AA120*AC120-AD120*AC120 -> 955.6 | AG120: =LN((AE120+AF120)/AE119) -> 0.00041867281 | AH120: 45476 | AI120: 743.5 | AM120: =AI120+AI120*AJ120+AI120*AK120-AL120*AK120 -> 743.5 | AO120: =LN((AM120+AN120)/AM119) -> -0.017465946 | AP120: 45476 | AQ120: 655.5 | AU120: =AQ120+AQ120*AR120+AQ120*AS120-AT120*AS120 -> 655.5 | AW120: =LN((AU120+AV120)/AU119) -> 0.010890513 | AX120: 45476 | AY120: 26.5 | BC120: =AY120+AY120*AZ120+AY120*BA120-BB120*BA120 -> 26.5 | BE120: =LN((BC120+BD120)/BC119) -> 0.022901764 | BF120: 45476 | BG120: 129.1 | BK120: =BG120+BG120*BH120+BG120*BI120-BJ120*BI120 -> 129.1 | BM120: =LN((BK120+BL120)/BK119) -> -0.0054075064
B121: 45477 | C121: 8.8 | G121: =C121+C121*D121+C121*E121-F121*E121 -> 8.8 | I121: =LN((G121+H121)/G120) -> 0.034685558 | J121: 45477 | K121: 32.5 | O121: =K121+K121*L121+K121*M121-N121*M121 -> 32.5 | Q121: =LN((O121+P121)/O120) -> 0.066797481 | R121: 45477 | S121: 245.6 | W121: =S121+S121*T121+S121*U121-V121*U121 -> 245.6 | Y121: =LN((W121+X121)/W120) -> 0.022232287 | Z121: 45477 | AA121: 971.3 | AE121: =AA121+AA121*AB121+AA121*AC121-AD121*AC121 -> 971.3 | AG121: =LN((AE121+AF121)/AE120) -> 0.016295965 | AH121: 45477 | AI121: 759.6 | AM121: =AI121+AI121*AJ121+AI121*AK121-AL121*AK121 -> 759.6 | AO121: =LN((AM121+AN121)/AM120) -> 0.021423213 | AP121: 45477 | AQ121: 658.1 | AU121: =AQ121+AQ121*AR121+AQ121*AS121-AT121*AS121 -> 658.1 | AW121: =LN((AU121+AV121)/AU120) -> 0.0039585923 | AX121: 45477 | AY121: 27.5 | BC121: =AY121+AY121*AZ121+AY121*BA121-BB121*BA121 -> 27.5 | BE121: =LN((BC121+BD121)/BC120) -> 0.037041272 | BF121: 45477 | BG121: 132.9 | BK121: =BG121+BG121*BH121+BG121*BI121-BJ121*BI121 -> 132.9 | BM121: =LN((BK121+BL121)/BK120) -> 0.029009668
B122: 45480 | C122: 9.2 | G122: =C122+C122*D122+C122*E122-F122*E122 -> 9.2 | I122: =LN((G122+H122)/G121) -> 0.044451763 | J122: 45480 | K122: 33.8 | O122: =K122+K122*L122+K122*M122-N122*M122 -> 33.8 | Q122: =LN((O122+P122)/O121) -> 0.039220713 | R122: 45480 | S122: 251.2 | W122: =S122+S122*T122+S122*U122-V122*U122 -> 251.2 | Y122: =LN((W122+X122)/W121) -> 0.022545238 | Z122: 45480 | AA122: 977.7 | AE122: =AA122+AA122*AB122+AA122*AC122-AD122*AC122 -> 977.7 | AG122: =LN((AE122+AF122)/AE121) -> 0.0065674941 | AH122: 45480 | AI122: 754.3 | AM122: =AI122+AI122*AJ122+AI122*AK122-AL122*AK122 -> 754.3 | AO122: =LN((AM122+AN122)/AM121) -> -0.0070018121 | AP122: 45480 | AQ122: 638.5 | AU122: =AQ122+AQ122*AR122+AQ122*AS122-AT122*AS122 -> 638.5 | AW122: =LN((AU122+AV122)/AU121) -> -0.03023522 | AX122: 45480 | AY122: 28.1 | BC122: =AY122+AY122*AZ122+AY122*BA122-BB122*BA122 -> 28.1 | BE122: =LN((BC122+BD122)/BC121) -> 0.021583572 | BF122: 45480 | BG122: 134.1 | BK122: =BG122+BG122*BH122+BG122*BI122-BJ122*BI122 -> 134.1 | BM122: =LN((BK122+BL122)/BK121) -> 0.0089888246
B123: 45481 | C123: 9.2 | G123: =C123+C123*D123+C123*E123-F123*E123 -> 9.2 | I123: =LN((G123+H123)/G122) -> 0 | J123: 45481 | K123: 33.2 | O123: =K123+K123*L123+K123*M123-N123*M123 -> 33.2 | Q123: =LN((O123+P123)/O122) -> -0.017910927 | R123: 45481 | S123: 248.8 | W123: =S123+S123*T123+S123*U123-V123*U123 -> 248.8 | Y123: =LN((W123+X123)/W122) -> -0.0096000737 | Z123: 45481 | AA123: 960.1 | AE123: =AA123+AA123*AB123+AA123*AC123-AD123*AC123 -> 960.1 | AG123: =LN((AE123+AF123)/AE122) -> -0.018165429 | AH123: 45481 | AI123: 751.7 | AM123: =AI123+AI123*AJ123+AI123*AK123-AL123*AK123 -> 751.7 | AO123: =LN((AM123+AN123)/AM122) -> -0.0034528587 | AP123: 45481 | AQ123: 621.6 | AU123: =AQ123+AQ123*AR123+AQ123*AS123-AT123*AS123 -> 621.6 | AW123: =LN((AU123+AV123)/AU122) -> -0.026824876 | AX123: 45481 | AY123: 27.7 | BC123: =AY123+AY123*AZ123+AY123*BA123-BB123*BA123 -> 27.7 | BE123: =LN((BC123+BD123)/BC122) -> -0.014337163 | BF123: 45481 | BG123: 133.7 | BK123: =BG123+BG123*BH123+BG123*BI123-BJ123*BI123 -> 133.7 | BM123: =LN((BK123+BL123)/BK122) -> -0.0029873062
B124: 45482 | C124: 9.1 | G124: =C124+C124*D124+C124*E124-F124*E124 -> 9.1 | I124: =LN((G124+H124)/G123) -> -0.010929071 | J124: 45482 | K124: 32.4 | O124: =K124+K124*L124+K124*M124-N124*M124 -> 32.4 | Q124: =LN((O124+P124)/O123) -> -0.024391453 | R124: 45482 | S124: 245.1 | W124: =S124+S124*T124+S124*U124-V124*U124 -> 245.1 | Y124: =LN((W124+X124)/W123) -> -0.01498307 | Z124: 45482 | AA124: 947.4 | AE124: =AA124+AA124*AB124+AA124*AC124-AD124*AC124 -> 947.4 | AG124: =LN((AE124+AF124)/AE123) -> -0.013316055 | AH124: 45482 | AI124: 749.7 | AM124: =AI124+AI124*AJ124+AI124*AK124-AL124*AK124 -> 749.7 | AO124: =LN((AM124+AN124)/AM123) -> -0.0026641817 | AP124: 45482 | AQ124: 620.3 | AU124: =AQ124+AQ124*AR124+AQ124*AS124-AT124*AS124 -> 620.3 | AW124: =LN((AU124+AV124)/AU123) -> -0.0020935671 | AX124: 45482 | AY124: 28.6 | BC124: =AY124+AY124*AZ124+AY124*BA124-BB124*BA124 -> 28.6 | BE124: =LN((BC124+BD124)/BC123) -> 0.031974305 | BF124: 45482 | BG124: 133.3 | BK124: =BG124+BG124*BH124+BG124*BI124-BJ124*BI124 -> 133.3 | BM124: =LN((BK124+BL124)/BK123) -> -0.0029962569
B125: 45483 | C125: 9.3 | G125: =C125+C125*D125+C125*E125-F125*E125 -> 9.3 | I125: =LN((G125+H125)/G124) -> 0.021739987 | J125: 45483 | K125: 33.2 | O125: =K125+K125*L125+K125*M125-N125*M125 -> 33.2 | Q125: =LN((O125+P125)/O124) -> 0.024391453 | R125: 45483 | S125: 244.7 | W125: =S125+S125*T125+S125*U125-V125*U125 -> 244.7 | Y125: =LN((W125+X125)/W124) -> -0.0016333201 | Z125: 45483 | AA125: 952.3 | AE125: =AA125+AA125*AB125+AA125*AC125-AD125*AC125 -> 952.3 | AG125: =LN((AE125+AF125)/AE124) -> 0.0051587207 | AH125: 45483 | AI125: 742.8 | AM125: =AI125+AI125*AJ125+AI125*AK125-AL125*AK125 -> 742.8 | AO125: =LN((AM125+AN125)/AM124) -> -0.009246297 | AP125: 45483 | AQ125: 611.3 | AU125: =AQ125+AQ125*AR125+AQ125*AS125-AT125*AS125 -> 611.3 | AW125: =LN((AU125+AV125)/AU124) -> -0.014615395 | AX125: 45483 | AY125: 28.5 | BC125: =AY125+AY125*AZ125+AY125*BA125-BB125*BA125 -> 28.5 | BE125: =LN((BC125+BD125)/BC124) -> -0.0035026306 | BF125: 45483 | BG125: 136.4 | BK125: =BG125+BG125*BH125+BG125*BI125-BJ125*BI125 -> 136.4 | BM125: =LN((BK125+BL125)/BK124) -> 0.022989518
B126: 45484 | C126: 9.1 | G126: =C126+C126*D126+C126*E126-F126*E126 -> 9.1 | I126: =LN((G126+H126)/G125) -> -0.021739987 | J126: 45484 | K126: 32.5 | O126: =K126+K126*L126+K126*M126-N126*M126 -> 32.5 | Q126: =LN((O126+P126)/O125) -> -0.021309787 | R126: 45484 | S126: 243.5 | W126: =S126+S126*T126+S126*U126-V126*U126 -> 243.5 | Y126: =LN((W126+X126)/W125) -> -0.0049160279 | Z126: 45484 | AA126: 942.9 | AE126: =AA126+AA126*AB126+AA126*AC126-AD126*AC126 -> 942.9 | AG126: =LN((AE126+AF126)/AE125) -> -0.0099198787 | AH126: 45484 | AI126: 738.2 | AM126: =AI126+AI126*AJ126+AI126*AK126-AL126*AK126 -> 738.2 | AO126: =LN((AM126+AN126)/AM125) -> -0.0062120389 | AP126: 45484 | AQ126: 597.4 | AU126: =AQ126+AQ126*AR126+AQ126*AS126-AT126*AS126 -> 597.4 | AW126: =LN((AU126+AV126)/AU125) -> -0.023000931 | AX126: 45484 | AY126: 27.7 | BC126: =AY126+AY126*AZ126+AY126*BA126-BB126*BA126 -> 27.7 | BE126: =LN((BC126+BD126)/BC125) -> -0.028471674 | BF126: 45484 | BG126: 132.6 | BK126: =BG126+BG126*BH126+BG126*BI126-BJ126*BI126 -> 132.6 | BM126: =LN((BK126+BL126)/BK125) -> -0.028254668
B127: 45487 | C127: 9 | G127: =C127+C127*D127+C127*E127-F127*E127 -> 9 | I127: =LN((G127+H127)/G126) -> -0.011049836 | J127: 45487 | K127: 32.2 | O127: =K127+K127*L127+K127*M127-N127*M127 -> 32.2 | Q127: =LN((O127+P127)/O126) -> -0.0092736368 | R127: 45487 | S127: 244.5 | W127: =S127+S127*T127+S127*U127-V127*U127 -> 244.5 | Y127: =LN((W127+X127)/W126) -> 0.0040983664 | Z127: 45487 | AA127: 960.6 | AE127: =AA127+AA127*AB127+AA127*AC127-AD127*AC127 -> 960.6 | AG127: =LN((AE127+AF127)/AE126) -> 0.018597857 | AH127: 45487 | AI127: 734.5 | AM127: =AI127+AI127*AJ127+AI127*AK127-AL127*AK127 -> 734.5 | AO127: =LN((AM127+AN127)/AM126) -> -0.005024795 | AP127: 45487 | AQ127: 589.8 | AU127: =AQ127+AQ127*AR127+AQ127*AS127-AT127*AS127 -> 589.8 | AW127: =LN((AU127+AV127)/AU126) -> -0.012803409 | AX127: 45487 | AY127: 27.1 | BC127: =AY127+AY127*AZ127+AY127*BA127-BB127*BA127 -> 27.1 | BE127: =LN((BC127+BD127)/BC126) -> -0.021898685 | BF127: 45487 | BG127: 130.2 | BK127: =BG127+BG127*BH127+BG127*BI127-BJ127*BI127 -> 130.2 | BM127: =LN((BK127+BL127)/BK126) -> -0.018265348
B128: 45488 | C128: 9 | G128: =C128+C128*D128+C128*E128-F128*E128 -> 9 | I128: =LN((G128+H128)/G127) -> 0 | J128: 45488 | K128: 32.3 | O128: =K128+K128*L128+K128*M128-N128*M128 -> 32.3 | Q128: =LN((O128+P128)/O127) -> 0.0031007777 | R128: 45488 | S128: 244.6 | W128: =S128+S128*T128+S128*U128-V128*U128 -> 244.6 | Y128: =LN((W128+X128)/W127) -> 0.00040891434 | Z128: 45488 | AA128: 945.2 | AE128: =AA128+AA128*AB128+AA128*AC128-AD128*AC128 -> 945.2 | AG128: =LN((AE128+AF128)/AE127) -> -0.016161544 | AH128: 45488 | AI128: 735.8 | AM128: =AI128+AI128*AJ128+AI128*AK128-AL128*AK128 -> 735.8 | AO128: =LN((AM128+AN128)/AM127) -> 0.0017683471 | AP128: 45488 | AQ128: 634 | AU128: =AQ128+AQ128*AR128+AQ128*AS128-AT128*AS128 -> 634 | AW128: =LN((AU128+AV128)/AU127) -> 0.072265458 | AX128: 45488 | AY128: 26.9 | BC128: =AY128+AY128*AZ128+AY128*BA128-BB128*BA128 -> 26.9 | BE128: =LN((BC128+BD128)/BC127) -> -0.0074074413 | BF128: 45488 | BG128: 129.6 | BK128: =BG128+BG128*BH128+BG128*BI128-BJ128*BI128 -> 129.6 | BM128: =LN((BK128+BL128)/BK127) -> -0.0046189459
B129: 45489 | C129: 9.1 | G129: =C129+C129*D129+C129*E129-F129*E129 -> 9.1 | I129: =LN((G129+H129)/G128) -> 0.011049836 | J129: 45489 | K129: 33.2 | O129: =K129+K129*L129+K129*M129-N129*M129 -> 33.2 | Q129: =LN((O129+P129)/O128) -> 0.027482646 | R129: 45489 | S129: 249.3 | W129: =S129+S129*T129+S129*U129-V129*U129 -> 249.3 | Y129: =LN((W129+X129)/W128) -> 0.019032767 | Z129: 45489 | AA129: 958.9 | AE129: =AA129+AA129*AB129+AA129*AC129-AD129*AC129 -> 958.9 | AG129: =LN((AE129+AF129)/AE128) -> 0.014390249 | AH129: 45489 | AI129: 742.6 | AM129: =AI129+AI129*AJ129+AI129*AK129-AL129*AK129 -> 742.6 | AO129: =LN((AM129+AN129)/AM128) -> 0.0091991991 | AP129: 45489 | AQ129: 660.5 | AU129: =AQ129+AQ129*AR129+AQ129*AS129-AT129*AS129 -> 660.5 | AW129: =LN((AU129+AV129)/AU128) -> 0.04094817 | AX129: 45489 | AY129: 26.5 | BC129: =AY129+AY129*AZ129+AY129*BA129-BB129*BA129 -> 26.5 | BE129: =LN((BC129+BD129)/BC128) -> -0.014981554 | BF129: 45489 | BG129: 128.9 | BK129: =BG129+BG129*BH129+BG129*BI129-BJ129*BI129 -> 128.9 | BM129: =LN((BK129+BL129)/BK128) -> -0.005415874
B130: 45491 | C130: 9.1 | G130: =C130+C130*D130+C130*E130-F130*E130 -> 9.1 | I130: =LN((G130+H130)/G129) -> 0 | J130: 45491 | K130: 33 | O130: =K130+K130*L130+K130*M130-N130*M130 -> 33 | Q130: =LN((O130+P130)/O129) -> -0.0060423145 | R130: 45491 | S130: 251.6 | W130: =S130+S130*T130+S130*U130-V130*U130 -> 251.6 | Y130: =LN((W130+X130)/W129) -> 0.0091835343 | Z130: 45491 | AA130: 933.9 | AE130: =AA130+AA130*AB130+AA130*AC130-AD130*AC130 -> 933.9 | AG130: =LN((AE130+AF130)/AE129) -> -0.026417428 | AH130: 45491 | AI130: 740 | AM130: =AI130+AI130*AJ130+AI130*AK130-AL130*AK130 -> 740 | AO130: =LN((AM130+AN130)/AM129) -> -0.0035073555 | AP130: 45491 | AQ130: 640.7 | AU130: =AQ130+AQ130*AR130+AQ130*AS130-AT130*AS130 -> 640.7 | AW130: =LN((AU130+AV130)/AU129) -> -0.030435795 | AX130: 45491 | AY130: 26.1 | BC130: =AY130+AY130*AZ130+AY130*BA130-BB130*BA130 -> 26.1 | BE130: =LN((BC130+BD130)/BC129) -> -0.015209419 | BF130: 45491 | BG130: 127 | BK130: =BG130+BG130*BH130+BG130*BI130-BJ130*BI130 -> 127 | BM130: =LN((BK130+BL130)/BK129) -> -0.014849823
B131: 45497 | C131: 8.9 | G131: =C131+C131*D131+C131*E131-F131*E131 -> 8.9 | I131: =LN((G131+H131)/G130) -> -0.022223137 | J131: 45497 | K131: 32.1 | O131: =K131+K131*L131+K131*M131-N131*M131 -> 32.1 | Q131: =LN((O131+P131)/O130) -> -0.027651531 | R131: 45497 | S131: 249.1 | W131: =S131+S131*T131+S131*U131-V131*U131 -> 249.1 | Y131: =LN((W131+X131)/W130) -> -0.0099861026 | Z131: 45497 | AA131: 921.9 | AE131: =AA131+AA131*AB131+AA131*AC131-AD131*AC131 -> 921.9 | AG131: =LN((AE131+AF131)/AE130) -> -0.012932608 | AH131: 45497 | AI131: 720.8 | AM131: =AI131+AI131*AJ131+AI131*AK131-AL131*AK131 -> 720.8 | AO131: =LN((AM131+AN131)/AM130) -> -0.02628848 | AP131: 45497 | AQ131: 621.5 | AU131: =AQ131+AQ131*AR131+AQ131*AS131-AT131*AS131 -> 621.5 | AW131: =LN((AU131+AV131)/AU130) -> -0.030425418 | AX131: 45497 | AY131: 25.5 | BC131: =AY131+AY131*AZ131+AY131*BA131-BB131*BA131 -> 25.5 | BE131: =LN((BC131+BD131)/BC130) -> -0.023256862 | BF131: 45497 | BG131: 125.1 | BK131: =BG131+BG131*BH131+BG131*BI131-BJ131*BI131 -> 125.1 | BM131: =LN((BK131+BL131)/BK130) -> -0.015073669
...

Sheet DSEX Data
B2: Date | C2: DSEX Value | D2: Average DSEX Value | E2: Change in DSEX Value | G2: Quarter | H2: Average DSEX Value | I2: Change in DSEX Value
B3: 45292 | C3: 6242.87 | G3: Q4 2024 | H3: =D193 -> 5243.632
B4: 45293 | C4: 6233.42 | G4: Q1 2025 | H4: =D250 -> 5190.0984 | I4: =H4-H3 -> -53.53362
B5: 45294 | C5: 6236.07 | G5: Q2 2025 | H5: =D304 -> 4878.9333 | I5: =H5-H4 -> -311.16509
B6: 45295 | C6: 6244.17 | G6: Q3 2025 | H6: =D366 -> 5357.3376 | I6: =H6-H5 -> 478.40425
B7: 45299 | C7: 6269.51
B8: 45300 | C8: 6267.82
B9: 45301 | C9: 6285.25
B10: 45302 | C10: 6301.7
B11: 45306 | C11: 6318.08
B12: 45307 | C12: 6331.61
B13: 45308 | C13: 6346.21
B14: 45309 | C14: 6336.76
B15: 45313 | C15: 6254.31
B16: 45314 | C16: 6276.26
B17: 45315 | C17: 6226.65
B18: 45316 | C18: 6156.41
... B191: 45650 | C191: 5169.32
B192: 45652 | C192: 5184.45 | D192: Q4 2024
B193: 45656 | C193: 5216.44 | D193: =AVERAGE(C145:C193) -> 5243.632
B194: 45658 | C194: 5218.16
B195: 45659 | C195: 5199.62
B196: 45663 | C196: 5198.84
B197: 45664 | C197: 5190.78
B198: 45665 | C198: 5185
B199: 45666 | C199: 5194.43
B200: 45670 | C200: 5151.88
B201: 45671 | C201: 5150.87
B202: 45672 | C202: 5142.52
B203: 45673 | C203: 5133.92
B204: 45677 | C204: 5195.83
B205: 45678 | C205: 5202.62
... B248: 45740 | C248: 5196.89
B249: 45741 | C249: 5214.21 | D249: Q1 2025
B250: 45743 | C250: 5219.16 | D250: =AVERAGE(C194:C250) -> 5190.0984 | E250: =D250-D193 -> -53.53362
B251: 45753 | C251: 5205.19
B252: 45754 | C252: 5196.7
B253: 45755 | C253: 5185.83
B254: 45756 | C254: 5196.05
B255: 45757 | C255: 5205.23
B256: 45760 | C256: 5169.68
B257: 45762 | C257: 5132.02
B258: 45763 | C258: 5105.69
B259: 45764 | C259: 5097.33
B260: 45767 | C260: 5074.38
B261: 45768 | C261: 5044.85
B262: 45769 | C262: 5026.57
... B302: 45834 | C302: 4832.83
B303: 45837 | C303: 4839.78 | D303: Q2 2025
B304: 45838 | C304: 4838.39 | D304: =AVERAGE(C251:C304) -> 4878.9333 | E304: =D304-D366 -> -478.40425
B305: 45840 | C305: 4865.33
B306: 45841 | C306: 4894.07
B307: 45845 | C307: 4976.16
B308: 45846 | C308: 4981.64
B309: 45847 | C309: 5035.47
B310: 45848 | C310: 5068.04
B311: 45851 | C311: 5066.44
B312: 45852 | C312: 5061.83
B313: 45853 | C313: 5062.2
B314: 45854 | C314: 5116.9
B315: 45855 | C315: 5132.48
B316: 45858 | C316: 5194.03
... B364: 45928 | C364: 5380.08
B365: 45929 | C365: 5389.78 | D365: Q3 2025
B366: 45930 | C366: 5415.79 | D366: =AVERAGE(C305:C366) -> 5357.3376 | E366: =D366-D250 -> 167.23916

Sheet Returns
B2: Stock Returns
B4: Quarter | C4: Date | D4: UCB | E4: IDLC | F4: GP | G4: BATASHOE | H4: RENATA | I4: WALTONHIL | J4: RAKC | K4: OLYMPIC | L4: No. of Trading Days
B5: 2024 Q1 | C5: 45292 | L5: 60
C6: 45293 | D6: =Data!I4 -> 0 | E6: =Data!Q4 -> 0 | F6: =Data!Y4 -> 0 | G6: =Data!AG4 -> -0.0054982243 | H6: =Data!AO4 -> 0 | I6: =Data!AW4 -> 0 | J6: =Data!BE4 -> 0 | K6: =Data!BM4 -> 0.0052770571
C7: 45294 | D7: =Data!I5 -> 0 | E7: =Data!Q5 -> 0 | F7: =Data!Y5 -> 0 | G7: =Data!AG5 -> -0.00010403121 | H7: =Data!AO5 -> 0 | I7: =Data!AW5 -> 0 | J7: =Data!BE5 -> 0 | K7: =Data!BM5 -> 0.015018239
C8: 45295 | D8: =Data!I6 -> 0 | E8: =Data!Q6 -> 0 | F8: =Data!Y6 -> 0 | G8: =Data!AG6 -> 0.0076692261 | H8: =Data!AO6 -> 0 | I8: =Data!AW6 -> 0 | J8: =Data!BE6 -> 0 | K8: =Data!BM6 -> 0.012878478
C9: 45299 | D9: =Data!I7 -> 0 | E9: =Data!Q7 -> 0 | F9: =Data!Y7 -> 0 | G9: =Data!AG7 -> 0.00082559344 | H9: =Data!AO7 -> 0 | I9: =Data!AW7 -> 0 | J9: =Data!BE7 -> 0 | K9: =Data!BM7 -> -0.0051315058
C10: 45300 | D10: =Data!I8 -> 0 | E10: =Data!Q8 -> 0 | F10: =Data!Y8 -> 0 | G10: =Data!AG8 -> -0.0066239116 | H10: =Data!AO8 -> 0 | I10: =Data!AW8 -> 0 | J10: =Data!BE8 -> 0 | K10: =Data!BM8 -> -0.0019311239
C11: 45301 | D11: =Data!I9 -> 0 | E11: =Data!Q9 -> 0 | F11: =Data!Y9 -> 0 | G11: =Data!AG9 -> 0.012384059 | H11: =Data!AO9 -> 0 | I11: =Data!AW9 -> 0 | J11: =Data!BE9 -> 0 | K11: =Data!BM9 -> 0.0012878302
C12: 45302 | D12: =Data!I10 -> 0 | E12: =Data!Q10 -> 0 | F12: =Data!Y10 -> 0 | G12: =Data!AG10 -> -0.0060696653 | H12: =Data!AO10 -> 0 | I12: =Data!AW10 -> 0 | J12: =Data!BE10 -> 0 | K12: =Data!BM10 -> -0.0038684768
C13: 45305 | D13: =Data!I11 -> 0 | E13: =Data!Q11 -> 0 | F13: =Data!Y11 -> 0 | G13: =Data!AG11 -> 0.0099595258 | H13: =Data!AO11 -> 0 | I13: =Data!AW11 -> 0 | J13: =Data!BE11 -> 0 | K13: =Data!BM11 -> 0.0025806466
C14: 45306 | D14: =Data!I12 -> 0 | E14: =Data!Q12 -> 0 | F14: =Data!Y12 -> 0 | G14: =Data!AG12 -> 0.0047903063 | H14: =Data!AO12 -> 0 | I14: =Data!AW12 -> 0 | J14: =Data!BE12 -> 0 | K14: =Data!BM12 -> 0.0102565
C15: 45307 | D15: =Data!I13 -> 0 | E15: =Data!Q13 -> 0 | F15: =Data!Y13 -> 0 | G15: =Data!AG13 -> -0.00050851768 | H15: =Data!AO13 -> 0 | I15: =Data!AW13 -> 0 | J15: =Data!BE13 -> 0 | K15: =Data!BM13 -> -0.0031938705
C16: 45308 | D16: =Data!I14 -> 0 | E16: =Data!Q14 -> 0 | F16: =Data!Y14 -> 0 | G16: =Data!AG14 -> 0.011932592 | H16: =Data!AO14 -> 0 | I16: =Data!AW14 -> 0 | J16: =Data!BE14 -> 0 | K16: =Data!BM14 -> -0.0070626297
C17: 45309 | D17: =Data!I15 -> 0 | E17: =Data!Q15 -> 0 | F17: =Data!Y15 -> 0 | G17: =Data!AG15 -> -0.0072639545 | H17: =Data!AO15 -> 0 | I17: =Data!AW15 -> 0 | J17: =Data!BE15 -> 0 | K17: =Data!BM15 -> -0.0064641466
... C64: 45382 | D64: =Data!I62 -> 0.0083682497 | E64: =Data!Q62 -> 0.016529302 | F64: =Data!Y62 -> 0.0084459962 | G64: =Data!AG62 -> 0.0080231985 | H64: =Data!AO62 -> 0.011926509 | I64: =Data!AW62 -> -0.0088835015 | J64: =Data!BE62 -> 0.024845999 | K64: =Data!BM62 -> 0.016573134
B65: 2024 Q2 | C65: 45383 | D65: =Data!I63 -> -0.025317808 | E65: =Data!Q63 -> 0.0027285147 | F65: =Data!Y63 -> -0.0037918731 | G65: =Data!AG63 -> 0.0046422528 | H65: =Data!AO63 -> -0.035814151 | I65: =Data!AW63 -> -0.00030773965 | J65: =Data!BE63 -> -0.0061538656 | K65: =Data!BM63 -> 0.0052459137 | L65: 56
C66: 45384 | D66: =Data!I64 -> -0.0085837437 | E66: =Data!Q64 -> 0 | F66: =Data!Y64 -> 0.0033712632 | G66: =Data!AG64 -> 0.0025139538 | H66: =Data!AO64 -> 0.020622013 | I66: =Data!AW64 -> 0.033742516 | J66: =Data!BE64 -> -0.0093023927 | K66: =Data!BM64 -> 0.0039164541
C67: 45385 | D67: =Data!I65 -> 0.0085837437 | E67: =Data!Q65 -> 0.016216572 | F67: =Data!Y65 -> 0.0079614919 | G67: =Data!AG65 -> 0.0060078282 | H67: =Data!AO65 -> 0.0027438444 | I67: =Data!AW65 -> 0.011832707 | J67: =Data!BE65 -> 0.015456258 | K67: =Data!BM65 -> 0.0058460706
C68: 45386 | D68: =Data!I66 -> -0.017241806 | E68: =Data!Q66 -> 0 | F68: =Data!Y66 -> 0.0025010434 | G68: =Data!AG66 -> -0.011748892 | H68: =Data!AO66 -> 0.0033867428 | I68: =Data!AW66 -> -0.0082681705 | J68: =Data!BE66 -> 0.006116227 | K68: =Data!BM66 -> -0.00064787822
C69: 45390 | D69: =Data!I67 -> 0.0086580627 | E69: =Data!Q67 -> 0.0053476063 | F69: =Data!Y67 -> 0 | G69: =Data!AG67 -> 0.0078479123 | H69: =Data!AO67 -> 0.013946507 | I69: =Data!AW67 -> 0.0079740529 | J69: =Data!BE67 -> 0.015128882 | K69: =Data!BM67 -> 0.0051713108
C70: 45391 | D70: =Data!I68 -> -0.017391743 | E70: =Data!Q68 -> 0.0082988028 | F70: =Data!Y68 -> -0.0008329863 | G70: =Data!AG68 -> -0.0030111435 | H70: =Data!AO68 -> 0.034162268 | I70: =Data!AW68 -> -0.0088639966 | J70: =Data!BE68 -> 0.014903406 | K70: =Data!BM68 -> -0.013632149
C71: 45397 | D71: =Data!I69 -> 0 | E71: =Data!Q69 -> -0.025105921 | F71: =Data!Y69 -> -0.004593869 | G71: =Data!AG69 -> -0.0056451763 | H71: =Data!AO69 -> 0.00037172418 | I71: =Data!AW69 -> -0.019025366 | J71: =Data!BE69 -> -0.039220713 | K71: =Data!BM69 -> -0.019802627
C72: 45398 | D72: =Data!I70 -> 0.00873368 | E72: =Data!Q70 -> -0.0028288562 | F72: =Data!Y70 -> -0.01178961 | G72: =Data!AG70 -> -0.0090378884 | H72: =Data!AO70 -> 0.00074303409 | I72: =Data!AW70 -> -0.0018165309 | J72: =Data!BE70 -> -0.0061728591 | K72: =Data!BM70 -> 0.011928571
C73: 45399 | D73: =Data!I71 -> 0 | E73: =Data!Q71 -> -0.0056818335 | F73: =Data!Y71 -> 0.0033826671 | G73: =Data!AG71 -> 0.0017326611 | H73: =Data!AO71 -> 0.0062935976 | I73: =Data!AW71 -> -0.012962438 | J73: =Data!BE71 -> -0.01246122 | K73: =Data!BM71 -> 0.0085274377
C74: 45400 | D74: =Data!I72 -> -0.00873368 | E74: =Data!Q72 -> -0.055651255 | F74: =Data!Y72 -> -0.0093300083 | G74: =Data!AG72 -> -0.017152374 | H74: =Data!AO72 -> -0.015496498 | I74: =Data!AW72 -> -0.0080136043 | J74: =Data!BE72 -> -0.015798117 | K74: =Data!BM72 -> -0.02983317
C75: 45403 | D75: =Data!I73 -> -0.035718083 | E75: =Data!Q73 -> -0.024391453 | F75: =Data!Y73 -> -0.0021326517 | G75: =Data!AG73 -> 0.0048571376 | H75: =Data!AO73 -> -0.022745484 | I75: =Data!AW73 -> -0.022532638 | J75: =Data!BE73 -> -0.0031897954 | K75: =Data!BM73 -> 0.0013449901
C76: 45404 | D76: =Data!I74 -> 0.0090498355 | E76: =Data!Q74 -> 0.015314235 | F76: =Data!Y74 -> -0.0047079051 | G76: =Data!AG74 -> 0 | H76: =Data!AO74 -> 0.00089428304 | I76: =Data!AW74 -> 0.021448963 | J76: =Data!BE74 -> 0 | K76: =Data!BM74 -> -0.0053908486
C77: 45405 | D77: =Data!I75 -> -0.027398974 | E77: =Data!Q75 -> -0.0091603694 | F77: =Data!Y75 -> -0.002147306 | G77: =Data!AG75 -> -0.015061308 | H77: =Data!AO75 -> 0.0048407738 | I77: =Data!AW75 -> 0.0083295253 | J77: =Data!BE75 -> -0.039092926 | K77: =Data!BM75 -> -0.003384098
... C120: 45473 | D120: =Data!I118 -> -0.023810649 | E120: =Data!Q118 -> -0.020134908 | F120: =Data!Y118 -> 0.025763028 | G120: =Data!AG118 -> 0.019321777 | H120: =Data!AO118 -> 0.0054687636 | I120: =Data!AW118 -> -0.0047622795 | J120: =Data!BE118 -> -0.015151805 | K120: =Data!BM118 -> -0.0060241146
B121: 2024 Q3 | C121: 45475 | D121: =Data!I119 -> 0 | E121: =Data!Q119 -> -0.003395589 | F121: =Data!Y119 -> -0.015050111 | G121: =Data!AG119 -> -0.022770597 | H121: =Data!AO119 -> -0.017685664 | I121: =Data!AW119 -> -0.0015410698 | J121: =Data!BE119 -> -0.011516442 | K121: =Data!BM119 -> -0.019832839 | L121: 58
C122: 45476 | D122: =Data!I120 -> 0.023810649 | E122: =Data!Q120 -> 0.033447934 | F122: =Data!Y120 -> -0.015696316 | G122: =Data!AG120 -> 0.00041867281 | H122: =Data!AO120 -> -0.017465946 | I122: =Data!AW120 -> 0.010890513 | J122: =Data!BE120 -> 0.022901764 | K122: =Data!BM120 -> -0.0054075064
C123: 45477 | D123: =Data!I121 -> 0.034685558 | E123: =Data!Q121 -> 0.066797481 | F123: =Data!Y121 -> 0.022232287 | G123: =Data!AG121 -> 0.016295965 | H123: =Data!AO121 -> 0.021423213 | I123: =Data!AW121 -> 0.0039585923 | J123: =Data!BE121 -> 0.037041272 | K123: =Data!BM121 -> 0.029009668
C124: 45480 | D124: =Data!I122 -> 0.044451763 | E124: =Data!Q122 -> 0.039220713 | F124: =Data!Y122 -> 0.022545238 | G124: =Data!AG122 -> 0.0065674941 | H124: =Data!AO122 -> -0.0070018121 | I124: =Data!AW122 -> -0.03023522 | J124: =Data!BE122 -> 0.021583572 | K124: =Data!BM122 -> 0.0089888246
C125: 45481 | D125: =Data!I123 -> 0 | E125: =Data!Q123 -> -0.017910927 | F125: =Data!Y123 -> -0.0096000737 | G125: =Data!AG123 -> -0.018165429 | H125: =Data!AO123 -> -0.0034528587 | I125: =Data!AW123 -> -0.026824876 | J125: =Data!BE123 -> -0.014337163 | K125: =Data!BM123 -> -0.0029873062
C126: 45482 | D126: =Data!I124 -> -0.010929071 | E126: =Data!Q124 -> -0.024391453 | F126: =Data!Y124 -> -0.01498307 | G126: =Data!AG124 -> -0.013316055 | H126: =Data!AO124 -> -0.0026641817 | I126: =Data!AW124 -> -0.0020935671 | J126: =Data!BE124 -> 0.031974305 | K126: =Data!BM124 -> -0.0029962569
C127: 45483 | D127: =Data!I125 -> 0.021739987 | E127: =Data!Q125 -> 0.024391453 | F127: =Data!Y125 -> -0.0016333201 | G127: =Data!AG125 -> 0.0051587207 | H127: =Data!AO125 -> -0.009246297 | I127: =Data!AW125 -> -0.014615395 | J127: =Data!BE125 -> -0.0035026306 | K127: =Data!BM125 -> 0.022989518
C128: 45484 | D128: =Data!I126 -> -0.021739987 | E128: =Data!Q126 -> -0.021309787 | F128: =Data!Y126 -> -0.0049160279 | G128: =Data!AG126 -> -0.0099198787 | H128: =Data!AO126 -> -0.0062120389 | I128: =Data!AW126 -> -0.023000931 | J128: =Data!BE126 -> -0.028471674 | K128: =Data!BM126 -> -0.028254668
C129: 45487 | D129: =Data!I127 -> -0.011049836 | E129: =Data!Q127 -> -0.0092736368 | F129: =Data!Y127 -> 0.0040983664 | G129: =Data!AG127 -> 0.018597857 | H129: =Data!AO127 -> -0.005024795 | I129: =Data!AW127 -> -0.012803409 | J129: =Data!BE127 -> -0.021898685 | K129: =Data!BM127 -> -0.018265348
C130: 45488 | D130: =Data!I128 -> 0 | E130: =Data!Q128 -> 0.0031007777 | F130: =Data!Y128 -> 0.00040891434 | G130: =Data!AG128 -> -0.016161544 | H130: =Data!AO128 -> 0.0017683471 | I130: =Data!AW128 -> 0.072265458 | J130: =Data!BE128 -> -0.0074074413 | K130: =Data!BM128 -> -0.0046189459
C131: 45489 | D131: =Data!I129 -> 0.011049836 | E131: =Data!Q129 -> 0.027482646 | F131: =Data!Y129 -> 0.019032767 | G131: =Data!AG129 -> 0.014390249 | H131: =Data!AO129 -> 0.0091991991 | I131: =Data!AW129 -> 0.04094817 | J131: =Data!BE129 -> -0.014981554 | K131: =Data!BM129 -> -0.005415874
C132: 45491 | D132: =Data!I130 -> 0 | E132: =Data!Q130 -> -0.0060423145 | F132: =Data!Y130 -> 0.0091835343 | G132: =Data!AG130 -> -0.026417428 | H132: =Data!AO130 -> -0.0035073555 | I132: =Data!AW130 -> -0.030435795 | J132: =Data!BE130 -> -0.015209419 | K132: =Data!BM130 -> -0.014849823
C133: 45497 | D133: =Data!I131 -> -0.022223137 | E133: =Data!Q131 -> -0.027651531 | F133: =Data!Y131 -> -0.0099861026 | G133: =Data!AG131 -> -0.012932608 | H133: =Data!AO131 -> -0.02628848 | I133: =Data!AW131 -> -0.030425418 | J133: =Data!BE131 -> -0.023256862 | K133: =Data!BM131 -> -0.015073669
... C178: 45565 | D178: =Data!I176 -> -0.025975486 | E178: =Data!Q176 -> 0.011173301 | F178: =Data!Y176 -> 0.002573268 | G178: =Data!AG176 -> 0.0059035217 | H178: =Data!AO176 -> -0.031748698 | I178: =Data!AW176 -> 0 | J178: =Data!BE176 -> -0.020284671 | K178: =Data!BM176 -> 0.0059799037
B179: 2024 Q4 | C179: 45566 | D179: =Data!I177 -> -0.035718083 | E179: =Data!Q177 -> -0.013986242 | F179: =Data!Y177 -> -0.0048661897 | G179: =Data!AG177 -> 0.0017108644 | H179: =Data!AO177 -> 0.0032775234 | I179: =Data!AW177 -> 0.011686277 | J179: =Data!BE177 -> -0.03333642 | K179: =Data!BM177 -> -0.038115633 | L179: 61
C180: 45567 | D180: =Data!I178 -> -0.018349139 | E180: =Data!Q178 -> -0.02279301 | F180: =Data!Y178 -> -0.021462541 | G180: =Data!AG178 -> -0.0071838619 | H180: =Data!AO178 -> -0.009146841 | I180: =Data!AW178 -> -0.02552115 | J180: =Data!BE178 -> -0.0042462909 | K180: =Data!BM178 -> -0.057953643
C181: 45568 | D181: =Data!I179 -> -0.0093023927 | E181: =Data!Q179 -> -0.03221362 | F181: =Data!Y179 -> -0.0094256957 | G181: =Data!AG179 -> 0.00032277153 | H181: =Data!AO179 -> 0.012555451 | I181: =Data!AW179 -> 0.0072046421 | J181: =Data!BE179 -> -0.0042643988 | K181: =Data!BM179 -> 0.014806311
C182: 45571 | D182: =Data!I180 -> -0.018868484 | E182: =Data!Q180 -> 0 | F182: =Data!Y180 -> -0.017615025 | G182: =Data!AG180 -> -0.0012917117 | H182: =Data!AO180 -> -0.0045474002 | I182: =Data!AW180 -> -0.015736962 | J182: =Data!BE180 -> 0 | K182: =Data!BM180 -> -0.052500744
C183: 45572 | D183: =Data!I181 -> 0.009478744 | E183: =Data!Q181 -> -0.00896867 | F183: =Data!Y181 -> -0.018851273 | G183: =Data!AG181 -> 0.0011841328 | H183: =Data!AO181 -> -0.0091573111 | I183: =Data!AW181 -> -0.049136623 | J183: =Data!BE181 -> -0.017241806 | K183: =Data!BM181 -> -0.01435282
C184: 45573 | D184: =Data!I182 -> -0.009478744 | E184: =Data!Q182 -> -0.021245109 | F184: =Data!Y182 -> 0.010989122 | G184: =Data!AG182 -> -0.0028011223 | H184: =Data!AO182 -> -0.0050436017 | I184: =Data!AW182 -> -0.0094276793 | J184: =Data!BE182 -> 0.0086580627 | K184: =Data!BM182 -> 0.054431044
C185: 45574 | D185: =Data!I183 -> 0.009478744 | E185: =Data!Q183 -> 0.071035773 | F185: =Data!Y183 -> 0.026068892 | G185: =Data!AG183 -> 0.0074165977 | H185: =Data!AO183 -> 0.0083441716 | I185: =Data!AW183 -> 0.012105057 | J185: =Data!BE183 -> 0.02972618 | K185: =Data!BM183 -> 0.009478744
C186: 45579 | D186: =Data!I184 -> 0 | E186: =Data!Q184 -> 0 | F186: =Data!Y184 -> -0.0077197533 | G186: =Data!AG184 -> -0.0016076312 | H186: =Data!AO184 -> -0.0022948949 | I186: =Data!AW184 -> -0.070617567 | J186: =Data!BE184 -> -0.034045841 | K186: =Data!BM184 -> 0.02388695
C187: 45580 | D187: =Data!I185 -> 0.0093897403 | E187: =Data!Q185 -> -0.0086083745 | F187: =Data!Y185 -> -0.00029810702 | G187: =Data!AG185 -> -0.0053775135 | H187: =Data!AO185 -> -0.00071823604 | I187: =Data!AW185 -> -0.0076124223 | J187: =Data!BE185 -> 0.021414095 | K187: =Data!BM185 -> 0.0011507481
C188: 45581 | D188: =Data!I186 -> -0.0093897403 | E188: =Data!Q186 -> -0.017442303 | F188: =Data!Y186 -> 0.0065379133 | G188: =Data!AG186 -> -0.0062743607 | H188: =Data!AO186 -> -0.039870443 | I188: =Data!AW186 -> 0.020239881 | J188: =Data!BE186 -> -0.030109801 | K188: =Data!BM186 -> -0.013314234
C189: 45582 | D189: =Data!I187 -> -0.009478744 | E189: =Data!Q187 -> -0.0088365818 | F189: =Data!Y187 -> -0.0077312309 | G189: =Data!AG187 -> 0 | H189: =Data!AO187 -> -0.0093149712 | I189: =Data!AW187 -> -0.020446429 | J189: =Data!BE187 -> 0.013015368 | K189: =Data!BM187 -> 0.0081254074
C190: 45585 | D190: =Data!I188 -> -0.028987537 | E190: =Data!Q188 -> 0.034887259 | F190: =Data!Y188 -> -0.0065888229 | G190: =Data!AG188 -> -0.0067508967 | H190: =Data!AO188 -> -0.011232662 | I190: =Data!AW188 -> -0.032968865 | J190: =Data!BE188 -> -0.021787354 | K190: =Data!BM188 -> -0.034699159
C191: 45586 | D191: =Data!I189 -> 0.0097561749 | E191: =Data!Q189 -> 0.033711057 | F191: =Data!Y189 -> -0.01057252 | G191: =Data!AG189 -> -0.0030637949 | H191: =Data!AO189 -> 0 | I191: =Data!AW189 -> 0.0085034526 | J191: =Data!BE189 -> 0.0043956115 | K191: =Data!BM189 -> 0.0053715438
... C239: 45656 | D239: =Data!I237 -> 0.021978907 | E239: =Data!Q237 -> 0.015408625 | F239: =Data!Y237 -> 0.0018587366 | G239: =Data!AG237 -> -0.0016553555 | H239: =Data!AO237 -> 0.0094922402 | I239: =Data!AW237 -> -0.0024585138 | J239: =Data!BE237 -> 0 | K239: =Data!BM237 -> 0.012739026
B240: 2025 Q1 | C240: 45658 | D240: =Data!I238 -> 0.010810916 | E240: =Data!Q238 -> 0 | F240: =Data!Y238 -> 0.0061709545 | G240: =Data!AG238 -> 0.0020963212 | H240: =Data!AO238 -> 0.0017305125 | I240: =Data!AW238 -> 0.0038898606 | J240: =Data!BE238 -> -0.0088889474 | K240: =Data!BM238 -> -0.011457796 | L240: 61
C241: 45659 | D241: =Data!I239 -> 0.031748698 | E241: =Data!Q239 -> -0.0030627895 | F241: =Data!Y239 -> -0.002772218 | G241: =Data!AG239 -> -0.008967677 | H241: =Data!AO239 -> -0.0042529796 | I241: =Data!AW239 -> -0.0010221814 | J241: =Data!BE239 -> 0.0044543503 | K241: =Data!BM239 -> -0.0077121205
C242: 45662 | D242: =Data!I240 -> -0.0104713 | E242: =Data!Q240 -> -0.003072199 | F242: =Data!Y240 -> 0.0015410698 | G242: =Data!AG240 -> -0.0016695424 | H242: =Data!AO240 -> -0.0037956712 | I242: =Data!AW240 -> -0.0036885288 | J242: =Data!BE240 -> -0.017937701 | K242: =Data!BM240 -> 0.0045059619
C243: 45663 | D243: =Data!I241 -> 0 | E243: =Data!Q241 -> 0 | F243: =Data!Y241 -> 0.0015386986 | G243: =Data!AG241 -> 0.0062187874 | H243: =Data!AO241 -> 0.0033219994 | I243: =Data!AW241 -> 0.0032793635 | J243: =Data!BE241 -> 0.017937701 | K243: =Data!BM241 -> -0.0038610087
C244: 45664 | D244: =Data!I242 -> 0.0104713 | E244: =Data!Q242 -> -0.0092736368 | F244: =Data!Y242 -> 0.0027637051 | G244: =Data!AG242 -> -0.0022165586 | H244: =Data!AO242 -> -0.0052252514 | I244: =Data!AW242 -> -0.00081883321 | J244: =Data!BE242 -> -0.01342302 | K244: =Data!BM242 -> -0.0097182495
C245: 45665 | D245: =Data!I243 -> -0.0104713 | E245: =Data!Q243 -> -0.0062305498 | F245: =Data!Y243 -> 0.0018382358 | G245: =Data!AG243 -> -0.0089156949 | H245: =Data!AO243 -> 0.00015874276 | I245: =Data!AW243 -> -0.0022552547 | J245: =Data!BE243 -> 0.00896867 | K245: =Data!BM243 -> 0.0019512201
C246: 45666 | D246: =Data!I244 -> 0 | E246: =Data!Q244 -> -0.0094192219 | F246: =Data!Y244 -> 0.017296744 | G246: =Data!AG244 -> 0.0071389037 | H246: =Data!AO244 -> -0.0019065783 | I246: =Data!AW244 -> -0.0020546545 | J246: =Data!BE244 -> -0.018018506 | K246: =Data!BM244 -> 0.0051847167
C247: 45669 | D247: =Data!I245 -> 0 | E247: =Data!Q245 -> -0.0063291351 | F247: =Data!Y245 -> 0.0077914688 | G247: =Data!AG245 -> -0.0076987828 | H247: =Data!AO245 -> -0.013771234 | I247: =Data!AW245 -> 0.0020546545 | J247: =Data!BE245 -> -0.0091324836 | K247: =Data!BM245 -> -0.0032372964
C248: 45670 | D248: =Data!I246 -> -0.010582109 | E248: =Data!Q246 -> -0.028987537 | F248: =Data!Y246 -> 0.012164517 | G248: =Data!AG246 -> -0.00011201344 | H248: =Data!AO246 -> -0.013309724 | I248: =Data!AW246 -> 0.0081766604 | J248: =Data!BE246 -> -0.0045977092 | K248: =Data!BM246 -> 0.0071545021
C249: 45671 | D249: =Data!I247 -> -0.021506205 | E249: =Data!Q247 -> 0 | F249: =Data!Y247 -> -0.018452905 | G249: =Data!AG247 -> 0.00078383073 | H249: =Data!AO247 -> -0.005571045 | I249: =Data!AW247 -> 0.046344178 | J249: =Data!BE247 -> 0.0045977092 | K249: =Data!BM247 -> 0.0045263576
C250: 45672 | D250: =Data!I248 -> -0.021978907 | E250: =Data!Q248 -> -0.0032733253 | F250: =Data!Y248 -> -0.010569327 | G250: =Data!AG248 -> 0.00078321682 | H250: =Data!AO248 -> -0.015899639 | I250: =Data!AW248 -> -0.020024226 | J250: =Data!BE248 -> -0.0045977092 | K250: =Data!BM248 -> 0.0038634948
C251: 45673 | D251: =Data!I249 -> -0.011173301 | E251: =Data!Q249 -> -0.0032840752 | F251: =Data!Y249 -> 0.0051476268 | G251: =Data!AG249 -> -0.004034523 | H251: =Data!AO249 -> -0.014969584 | I251: =Data!AW249 -> -0.010164512 | J251: =Data!BE249 -> 0.0045977092 | K251: =Data!BM249 -> -0.026043139
C252: 45676 | D252: =Data!I250 -> -0.011299555 | E252: =Data!Q250 -> 0.0065574005 | F252: =Data!Y250 -> 0.0042194155 | G252: =Data!AG250 -> -0.0034872638 | H252: =Data!AO250 -> -0.00050851768 | I252: =Data!AW250 -> 0.0012012013 | J252: =Data!BE250 -> -0.0092166551 | K252: =Data!BM250 -> 0.011803416
... C300: 45743 | D300: =Data!I298 -> -0.018018506 | E300: =Data!Q298 -> -0.009508788 | F300: =Data!Y298 -> 0.0074836645 | G300: =Data!AG298 -> -0.0028711588 | H300: =Data!AO298 -> -0.0027932979 | I300: =Data!AW298 -> -0.00086411757 | J300: =Data!BE298 -> 0 | K300: =Data!BM298 -> -0.0047441634
B301: 2025 Q2 | C301: 45753 | D301: =Data!I299 -> 0.018018506 | E301: =Data!Q299 -> -0.0096000737 | F301: =Data!Y299 -> -0.0034230623 | G301: =Data!AG299 -> -0.0086632716 | H301: =Data!AO299 -> 0.0023947327 | I301: =Data!AW299 -> -0.0054177183 | J301: =Data!BE299 -> -0.0044345971 | K301: =Data!BM299 -> -0.01920498 | L301: 55
C302: 45754 | D302: =Data!I300 -> -0.018018506 | E302: =Data!Q300 -> 0.0064102784 | F302: =Data!Y300 -> 0.0052852602 | G302: =Data!AG300 -> -0.014362467 | H302: =Data!AO300 -> -0.0070007287 | I302: =Data!AW300 -> -0.00021732044 | J302: =Data!BE300 -> 0.0044345971 | K302: =Data!BM300 -> 0.0082759093
C303: 45755 | D303: =Data!I301 -> -0.018349139 | E303: =Data!Q301 -> -0.0096308931 | F303: =Data!Y301 -> -0.0062208599 | G303: =Data!AG301 -> -0.0027007136 | H303: =Data!AO301 -> -0.0034181193 | I303: =Data!AW301 -> -0.00043478262 | J303: =Data!BE301 -> 0.026202372 | K303: =Data!BM301 -> 0.02710193
C304: 45756 | D304: =Data!I302 -> 0 | E304: =Data!Q302 -> -0.0097245499 | F304: =Data!Y302 -> 0.00093559963 | G304: =Data!AG302 -> 0.010029438 | H304: =Data!AO302 -> 0.0016099822 | I304: =Data!AW302 -> 0.018100042 | J304: =Data!BE302 -> 0.02972618 | K304: =Data!BM302 -> 0.044451763
C305: 45757 | D305: =Data!I303 -> -0.018692133 | E305: =Data!Q303 -> 0 | F305: =Data!Y303 -> -0.00062363582 | G305: =Data!AG303 -> -0.0032912811 | H305: =Data!AO303 -> 0.0042139121 | I305: =Data!AW303 -> -0.0096556914 | J305: =Data!BE303 -> -0.0084034108 | K305: =Data!BM303 -> -0.011575692
C306: 45760 | D306: =Data!I304 -> -0.028710106 | E306: =Data!Q304 -> -0.006535971 | F306: =Data!Y304 -> -0.0015607932 | G306: =Data!AG304 -> 0.00073233251 | H306: =Data!AO304 -> -0.00020026034 | I306: =Data!AW304 -> 0.0049467786 | J306: =Data!BE304 -> -0.025642431 | K306: =Data!BM304 -> 0.043664007
C307: 45762 | D307: =Data!I305 -> -0.019608471 | E307: =Data!Q305 -> 0 | F307: =Data!Y305 -> 0.002184429 | G307: =Data!AG305 -> 0.0012193636 | H307: =Data!AO305 -> 0.0026002615 | I307: =Data!AW305 -> 0.014483746 | J307: =Data!BE305 -> -0.013072082 | K307: =Data!BM305 -> -0.011208087
C308: 45763 | D308: =Data!I306 -> -0.020000667 | E308: =Data!Q306 -> -0.0065789711 | F308: =Data!Y306 -> 0.00031167212 | G308: =Data!AG306 -> 0.00060912471 | H308: =Data!AO306 -> -0.0019996007 | I308: =Data!AW306 -> -0.013625929 | J308: =Data!BE306 -> -0.013245227 | K308: =Data!BM306 -> -0.024723922
C309: 45764 | D309: =Data!I307 -> 0.077708984 | E309: =Data!Q307 -> 0.0065789711 | F309: =Data!Y307 -> -0.0031211012 | G309: =Data!AG307 -> -0.0028050509 | H309: =Data!AO307 -> 0.00060030017 | I309: =Data!AW307 -> -0.015554429 | J309: =Data!BE307 -> 0 | K309: =Data!BM307 -> -0.0019274018
C310: 45767 | D310: =Data!I308 -> 0.018519048 | E310: =Data!Q308 -> 0.019481136 | F310: =Data!Y308 -> 0.0037441541 | G310: =Data!AG308 -> -0.011176045 | H310: =Data!AO308 -> -0.0050135471 | I310: =Data!AW308 -> -0.0050202004 | J310: =Data!BE308 -> -0.036203049 | K310: =Data!BM308 -> -0.022765211
C311: 45768 | D311: =Data!I309 -> -0.018519048 | E311: =Data!Q309 -> -0.0064516353 | F311: =Data!Y309 -> -0.0049953273 | G311: =Data!AG309 -> -0.017692961 | H311: =Data!AO309 -> -0.00080450527 | I311: =Data!AW309 -> -0.0041662159 | J311: =Data!BE309 -> -0.02803922 | K311: =Data!BM309 -> -0.0026350476
C312: 45769 | D312: =Data!I310 -> -0.028437935 | E312: =Data!Q310 -> -0.0064935293 | F312: =Data!Y310 -> 0.00062578225 | G312: =Data!AG310 -> 0.0056408799 | H312: =Data!AO310 -> -0.00020122749 | I312: =Data!AW310 -> -0.0013192614 | J312: =Data!BE310 -> 0.0047281412 | K312: =Data!BM310 -> 0.0085386397
C313: 45770 | D313: =Data!I311 -> -0.029270382 | E313: =Data!Q311 -> -0.0032626456 | F313: =Data!Y311 -> 0.0049922101 | G313: =Data!AG311 -> -0.0015011261 | H313: =Data!AO311 -> -0.0014097274 | I313: =Data!AW311 -> -0.0055157338 | J313: =Data!BE311 -> 0 | K313: =Data!BM311 -> 0.014930495
... C355: 45838 | D355: =Data!I353 -> -0.010050336 | E355: =Data!Q353 -> 0.013889112 | F355: =Data!Y353 -> -0.0013188264 | G355: =Data!AG353 -> -0.0012450201 | H355: =Data!AO353 -> -0.0040866424 | I355: =Data!AW353 -> -0.012960201 | J355: =Data!BE353 -> -0.020619287 | K355: =Data!BM353 -> 0.0085051216
B356: 2025 Q3 | C356: 45840 | D356: =Data!I354 -> 0.020000667 | E356: =Data!Q354 -> -0.0069204428 | F356: =Data!Y354 -> -0.010613698 | G356: =Data!AG354 -> 0.0033580033 | H356: =Data!AO354 -> -0.0024600258 | I356: =Data!AW354 -> 0.0095530426 | J356: =Data!BE354 -> 0.0051948169 | K356: =Data!BM354 -> 0.0013020835 | L356: 63
C357: 45841 | D357: =Data!I355 -> 0 | E357: =Data!Q355 -> 0.040821995 | F357: =Data!Y355 -> -0.0030055124 | G357: =Data!AG355 -> 0.00099280227 | H357: =Data!AO355 -> -0.0014378148 | I357: =Data!AW355 -> 0.0029211316 | J357: =Data!BE355 -> -0.010416761 | K357: =Data!BM355 -> -0.016399187
C358: 45845 | D358: =Data!I356 -> 0.019608471 | E358: =Data!Q356 -> 0.029558802 | F358: =Data!Y356 -> 0.0023384009 | G358: =Data!AG356 -> 0.00062000126 | H358: =Data!AO356 -> 0.0020533888 | I358: =Data!AW356 -> 0.010638398 | J358: =Data!BE356 -> 0.020726131 | K358: =Data!BM356 -> 0.011834458
C359: 45846 | D359: =Data!I357 -> 0.028710106 | E359: =Data!Q357 -> 0.012861914 | F359: =Data!Y357 -> -0.0033422491 | G359: =Data!AG357 -> 0.0025998158 | H359: =Data!AO357 -> 0.0040941715 | I359: =Data!AW357 -> -0.0016849204 | J359: =Data!BE357 -> 0.0051151007 | K359: =Data!BM357 -> -0.0045856615
C360: 45847 | D360: =Data!I358 -> 0.0093897403 | E360: =Data!Q358 -> -0.0096308931 | F360: =Data!Y358 -> 0.0030085264 | G360: =Data!AG358 -> 0.010209819 | H360: =Data!AO358 -> 0.0028559791 | I360: =Data!AW358 -> 0.026623869 | J360: =Data!BE358 -> 0.030153038 | K360: =Data!BM358 -> 0.0084995608
C361: 45848 | D361: =Data!I359 -> 0.0093023927 | E361: =Data!Q359 -> 0 | F361: =Data!Y359 -> -0.0010018368 | G361: =Data!AG359 -> 0.016146026 | H361: =Data!AO359 -> -0.0044916368 | I361: =Data!AW359 -> 0.00023454908 | J361: =Data!BE359 -> -0.0099503309 | K361: =Data!BM359 -> 0.027610101
C362: 45851 | D362: =Data!I360 -> -0.037740328 | E362: =Data!Q360 -> 0 | F362: =Data!Y360 -> 0.0013355595 | G362: =Data!AG360 -> 0.01482217 | H362: =Data!AO360 -> 0 | I362: =Data!AW360 -> -0.012745039 | J362: =Data!BE360 -> 0.024692613 | K362: =Data!BM360 -> 0.0075710141
C363: 45852 | D363: =Data!I361 -> 0.019048195 | E363: =Data!Q361 -> 0.0064308903 | F363: =Data!Y361 -> -0.0056884878 | G363: =Data!AG361 -> 0.0067404027 | H363: =Data!AO361 -> 0.0024524844 | I363: =Data!AW361 -> 0.0045029108 | J363: =Data!BE361 -> 0.033576296 | K363: =Data!BM361 -> -0.012014055
C364: 45853 | D364: =Data!I362 -> 0 | E364: =Data!Q362 -> 0.059115188 | F364: =Data!Y362 -> -0.0013431835 | G364: =Data!AG362 -> -0.016996903 | H364: =Data!AO362 -> -0.0032713176 | I364: =Data!AW362 -> -0.00094629768 | J364: =Data!BE362 -> -0.033576296 | K364: =Data!BM362 -> -0.0057416426
C365: 45854 | D365: =Data!I363 -> 0 | E365: =Data!Q363 -> 0.0615128 | F365: =Data!Y363 -> -0.0026917917 | G365: =Data!AG363 -> -0.019610845 | H365: =Data!AO363 -> 0.0038835 | I365: =Data!AW363 -> 0.0051935905 | J365: =Data!BE363 -> 0.014528101 | K365: =Data!BM363 -> 0.0025559119
C366: 45855 | D366: =Data!I364 -> -0.028710106 | E366: =Data!Q364 -> -0.017192401 | F366: =Data!Y364 -> 0.011390408 | G366: =Data!AG364 -> 0.025109962 | H366: =Data!AO364 -> 0.0077220461 | I366: =Data!AW364 -> 0.0070389779 | J366: =Data!BE364 -> 0.0047961723 | K366: =Data!BM364 -> -0.0044771421
C367: 45858 | D367: =Data!I365 -> 0.0096619109 | E367: =Data!Q365 -> 0.088455421 | F367: =Data!Y365 -> 0.0092838863 | G367: =Data!AG365 -> 0.0057061496 | H367: =Data!AO365 -> 0.045313915 | I367: =Data!AW365 -> 0.028352712 | J367: =Data!BE365 -> 0.0047732788 | K367: =Data!BM365 -> 0.019048195
C368: 45859 | D368: =Data!I366 -> 0.009569451 | E368: =Data!Q366 -> 0.0052770571 | F368: =Data!Y366 -> 0.023162021 | G368: =Data!AG366 -> 0.021924789 | H368: =Data!AO366 -> -0.00096777323 | I368: =Data!AW366 -> 0.034840505 | J368: =Data!BE366 -> -0.0047732788 | K368: =Data!BM366 -> -0.0037807228
... C418: 45930 | D418: =Data!I416 -> 0 | E418: =Data!Q416 -> 0.0073081933 | F418: =Data!Y416 -> 0.0033500869 | G418: =Data!AG416 -> -0.0027306878 | H418: =Data!AO416 -> 0.0010413413 | I418: =Data!AW416 -> -0.073643468 | J418: =Data!BE416 -> -0.0039761484 | K418: =Data!BM416 -> -0.0064433213
...

Sheet Forcast 2025Q1
B2: Forecast Q1 2025
C4: UCB | D4: IDLC | E4: GP | F4: BATASHOE | G4: RENATA | H4: WALTONHIL | I4: RAKC | J4: OLYMPIC | K4: Weights
B5: Weights | C5: 0.125 | D5: 0.125 | E5: 0.125 | F5: 0.125 | G5: 0.125 | H5: 0.125 | I5: 0.125 | J5: 0.125 | M5: Q1 2025
B6: ='Stock Selection'!C5 -> UCB | C6: =VARP(Returns!$D$6:$D$239) -> 0.00064885675 | D6: 0.00022769737 | E6: 0.00019397746 | F6: 5.7159373e-05 | G6: 0.0001103972 | H6: 9.938745e-05 | I6: 0.0002247945 | J6: 0.00014347402 | K6: 0.125 | M6: Portfolio Variance | P6: =MMULT(MMULT(C5:J5,C6:J13),K6:K13) -> 0.00020994703
B7: ='Stock Selection'!C6 -> IDLC | C7: 0.00022769737 | D7: =VARP(Returns!$E$6:$E$239) -> 0.00061207392 | E7: 0.00024598434 | F7: 0.00010330646 | G7: 0.00017700343 | H7: 0.00027099648 | I7: 0.00033436751 | J7: 0.00028662625 | K7: 0.125 | M7: Portfolio Standard Deviation | P7: =SQRT(P6) -> 0.014489549
B8: ='Stock Selection'!C7 -> GP | C8: 0.00019397746 | D8: 0.00024598434 | E8: =VARP(Returns!$F$6:$F$239) -> 0.00032926845 | F8: 6.3159963e-05 | G8: 0.0001811601 | H8: 0.000147565 | I8: 0.00015861336 | J8: 0.0001917167 | K8: 0.125 | M8: Quarterly Portfolio SD | P8: =P7*P9^0.5 -> 0.113167
B9: ='Stock Selection'!C8 -> BATASHOE | C9: 5.7159373e-05 | D9: 0.00010330646 | E9: 6.3159963e-05 | F9: =VARP(Returns!$G$6:$G$239) -> 0.00014397657 | G9: 6.9401378e-05 | H9: 8.3384363e-05 | I9: 0.00010129654 | J9: 7.9539258e-05 | K9: 0.125 | M9: Trading Days | P9: =Returns!L240 -> 61
B10: ='Stock Selection'!C9 -> RENATA | C10: 0.0001103972 | D10: 0.00017700343 | E10: 0.0001811601 | F10: 6.9401378e-05 | G10: =VARP(Returns!$H$6:$H$239) -> 0.00042423911 | H10: 0.00019402032 | I10: 0.00016509768 | J10: 0.00012489838 | K10: 0.125
B11: ='Stock Selection'!C10 -> WALTONHIL | C11: 9.938745e-05 | D11: 0.00027099648 | E11: 0.000147565 | F11: 8.3384363e-05 | G11: 0.00019402032 | H11: =VARP(Returns!$I$6:$I$239) -> 0.00065914533 | I11: 0.00027741736 | J11: 0.00015477947 | K11: 0.125
B12: ='Stock Selection'!C11 -> RAKC | C12: 0.0002247945 | D12: 0.00033436751 | E12: 0.00015861336 | F12: 0.00010129654 | G12: 0.00016509768 | H12: 0.00027741736 | I12: =VARP(Returns!$J$6:$J$239) -> 0.00065062327 | J12: 0.00021941036 | K12: 0.125
B13: ='Stock Selection'!C12 -> OLYMPIC | C13: 0.00014347402 | D13: 0.00028662625 | E13: 0.0001917167 | F13: 7.9539258e-05 | G13: 0.00012489838 | H13: 0.00015477947 | I13: 0.00021941036 | J13: =VARP(Returns!$K$6:$K$239) -> 0.0005951623 | K13: 0.125

Sheet Forcast 2025Q2
B2: Forecast Q2 2025
C4: UCB | D4: IDLC | E4: GP | F4: BATASHOE | G4: RENATA | H4: WALTONHIL | I4: RAKC | J4: OLYMPIC | K4: Weights
B5: Weights | C5: 0.125 | D5: 0.125 | E5: 0.125 | F5: 0.125 | G5: 0.125 | H5: 0.125 | I5: 0.125 | J5: 0.125 | M5: Q2 2025
B6: ='Stock Selection'!C5 -> UCB | C6: =VARP(Returns!$D$65:$D$300) -> 0.00068289667 | D6: 0.00022148298 | E6: 0.00018780466 | F6: 4.6455851e-05 | G6: 0.00013057235 | H6: 0.00010509688 | I6: 0.00018703653 | J6: 0.00014082131 | K6: 0.125 | M6: Portfolio Variance | P6: =MMULT(MMULT(C5:J5,C6:J13),K6:K13) -> 0.00019557536
B7: ='Stock Selection'!C6 -> IDLC | C7: 0.00022148298 | D7: =VARP(Returns!$E$65:$E$300) -> 0.00051645367 | E7: 0.00023610813 | F7: 0.0001109935 | G7: 0.00017618451 | H7: 0.00020112237 | I7: 0.00027977845 | J7: 0.00027495276 | K7: 0.125 | M7: Portfolio Standard Deviation | P7: =SQRT(P6) -> 0.013984826
B8: ='Stock Selection'!C7 -> GP | C8: 0.00018780466 | D8: 0.00023610813 | E8: =VARP(Returns!$F$65:$F$300) -> 0.00031619601 | F8: 6.5073022e-05 | G8: 0.00017370801 | H8: 0.0001432714 | I8: 0.00015318299 | J8: 0.00018890659 | K8: 0.125 | M8: Quarterly Portfolio SD | P8: =P7*P9^0.5 -> 0.10371425
B9: ='Stock Selection'!C8 -> BATASHOE | C9: 4.6455851e-05 | D9: 0.0001109935 | E9: 6.5073022e-05 | F9: =VARP(Returns!$G$65:$G$300) -> 0.00017802672 | G9: 7.4627615e-05 | H9: 9.4693178e-05 | I9: 8.4122357e-05 | J9: 8.1908455e-05 | K9: 0.125 | M9: Trading Days | P9: =Returns!L301 -> 55
B10: ='Stock Selection'!C9 -> RENATA | C10: 0.00013057235 | D10: 0.00017618451 | E10: 0.00017370801 | F10: 7.4627615e-05 | G10: =VARP(Returns!$H$65:$H$300) -> 0.00038278308 | H10: 0.0001771044 | I10: 0.00017260885 | J10: 0.00011894446 | K10: 0.125
B11: ='Stock Selection'!C10 -> WALTONHIL | C11: 0.00010509688 | D11: 0.00020112237 | E11: 0.0001432714 | F11: 9.4693178e-05 | G11: 0.0001771044 | H11: =VARP(Returns!$I$65:$I$300) -> 0.00049172163 | I11: 0.00019035703 | J11: 0.00016974052 | K11: 0.125
B12: ='Stock Selection'!C11 -> RAKC | C12: 0.00018703653 | D12: 0.00027977845 | E12: 0.00015318299 | F12: 8.4122357e-05 | G12: 0.00017260885 | H12: 0.00019035703 | I12: =VARP(Returns!$J$65:$J$300) -> 0.00055020141 | J12: 0.00022080993 | K12: 0.125
B13: ='Stock Selection'!C12 -> OLYMPIC | C13: 0.00014082131 | D13: 0.00027495276 | E13: 0.00018890659 | F13: 8.1908455e-05 | G13: 0.00011894446 | H13: 0.00016974052 | I13: 0.00022080993 | J13: =VARP(Returns!$K$65:$K$300) -> 0.00058360583 | K13: 0.125

Sheet Forcast 2025Q3
B2: Forecast Q3 2025
C4: UCB | D4: IDLC | E4: GP | F4: BATASHOE | G4: RENATA | H4: WALTONHIL | I4: RAKC | J4: OLYMPIC | K4: Weights
B5: Weights | C5: 0.125 | D5: 0.125 | E5: 0.125 | F5: 0.125 | G5: 0.125 | H5: 0.125 | I5: 0.125 | J5: 0.125 | M5: Q3 2025
B6: ='Stock Selection'!C5 -> UCB | C6: =VARP(Returns!$D$121:$D$355) -> 0.00078245028 | D6: 0.00026981402 | E6: 0.00019322445 | F6: 5.560698e-05 | G6: 0.00016310997 | H6: 0.00011227986 | I6: 0.00024002794 | J6: 0.00013437567 | K6: 0.125 | M6: Portfolio Variance | P6: =MMULT(MMULT(C5:J5,C6:J13),K6:K13) -> 0.00018452565
B7: ='Stock Selection'!C6 -> IDLC | C7: 0.00026981402 | D7: =VARP(Returns!$E$121:$E$355) -> 0.00049585688 | E7: 0.00023611878 | F7: 9.3939882e-05 | G7: 0.0001448042 | H7: 0.00016541448 | I7: 0.00025530735 | J7: 0.00025180181 | K7: 0.125 | M7: Portfolio Standard Deviation | P7: =SQRT(P6) -> 0.013584022
B8: ='Stock Selection'!C7 -> GP | C8: 0.00019322445 | D8: 0.00023611878 | E8: =VARP(Returns!$F$121:$F$355) -> 0.00032459544 | F8: 5.0807783e-05 | G8: 0.00016042601 | H8: 0.00013134271 | I8: 0.00014113956 | J8: 0.00018895355 | K8: 0.125 | M8: Quarterly Portfolio SD | P8: =P7*P9^0.5 -> 0.10781983
B9: ='Stock Selection'!C8 -> BATASHOE | C9: 5.560698e-05 | D9: 9.3939882e-05 | E9: 5.0807783e-05 | F9: =VARP(Returns!$G$121:$G$355) -> 0.00022543235 | G9: 4.3312823e-05 | H9: 7.4597745e-05 | I9: 7.7085519e-05 | J9: 7.324857e-05 | K9: 0.125 | M9: Trading Days | P9: =Returns!L356 -> 63
B10: ='Stock Selection'!C9 -> RENATA | C10: 0.00016310997 | D10: 0.0001448042 | E10: 0.00016042601 | F10: 4.3312823e-05 | G10: =VARP(Returns!$H$121:$H$355) -> 0.00029151489 | H10: 9.6365628e-05 | I10: 0.00013500997 | J10: 9.3941835e-05 | K10: 0.125
B11: ='Stock Selection'!C10 -> WALTONHIL | C11: 0.00011227986 | D11: 0.00016541448 | E11: 0.00013134271 | F11: 7.4597745e-05 | G11: 9.6365628e-05 | H11: =VARP(Returns!$I$121:$I$355) -> 0.00034839047 | I11: 0.00015826149 | J11: 0.000145558 | K11: 0.125
B12: ='Stock Selection'!C11 -> RAKC | C12: 0.00024002794 | D12: 0.00025530735 | E12: 0.00014113956 | F12: 7.7085519e-05 | G12: 0.00013500997 | H12: 0.00015826149 | I12: =VARP(Returns!$J$121:$J$355) -> 0.00055161501 | J12: 0.00021673748 | K12: 0.125
B13: ='Stock Selection'!C12 -> OLYMPIC | C13: 0.00013437567 | D13: 0.00025180181 | E13: 0.00018895355 | F13: 7.324857e-05 | G13: 9.3941835e-05 | H13: 0.000145558 | I13: 0.00021673748 | J13: =VARP(Returns!$K$121:$K$355) -> 0.00058455807 | K13: 0.125

Sheet 91Day T-Bill
C2: 91 Day Treasury Bill Rate
C4: Quarter 4 2024 | E4: Quarter 1 2025 | G4: Quarter 2 2025
C5: Issue Date | D5: Annual Rate | E5: Issue Date | F5: Annual Rate | G5: Issue Date | H5: Annual Rate
C6: 45572 | D6: 0.114499 | E6: 45663 | F6: 0.114299 | G6: 45754 | H6: 0.112391
C7: 45579 | D7: 0.114499 | E7: 45670 | F7: 0.113387 | G7: 45762 | H7: 0.114495
C8: 45587 | D8: 0.117501 | E8: 45677 | F8: 0.1129 | G8: 45768 | H8: 0.115895
C9: 45593 | D9: 0.117501 | E9: 45684 | F9: 0.111302 | G9: 45775 | H9: 0.116401
C10: 45600 | D10: 0.117501 | E10: 45691 | F10: 0.108499 | G10: 45782 | H10: 0.116099
C11: 45607 | D11: 0.117501 | E11: 45698 | F11: 0.105392 | G11: 45789 | H11: 0.115394
C12: 45614 | D12: 0.117501 | E12: 45705 | F12: 0.1035 | G12: 45796 | H12: 0.116498
C13: 45621 | D13: 0.117501 | E13: 45712 | F13: 0.1035 | G13: 45803 | H13: 0.116881
C14: 45628 | D14: 0.117097 | E14: 45719 | F14: 0.103399 | G14: 45810 | H14: 0.120197
C15: 45635 | D15: 0.116507 | E15: 45726 | F15: 0.1035 | G15: 45824 | H15: 0.121001
C16: 45643 | D16: 0.115691 | E16: 45733 | F16: 0.107497 | G16: 45831 | H16: 0.120891
C17: 45649 | D17: 0.114991 | E17: 45740 | F17: 0.108998 | G17: 45838 | H17: 0.120899
C18: 45656 | D18: 0.115
C20: Particulars | F20: 2025 Q1 | G20: 2025 Q2 | H20: 2025 Q3
C21: Average Annual Risk-Free Rate | F21: =AVERAGE(D6:D18) -> 0.11640692 | G21: =AVERAGE(F6:F18) -> 0.10801442 | H21: =AVERAGE(H6:H18) -> 0.1172535
C22: Continuously Compounding Annual Risk-Free Rate | F22: =4*LN(1+(F21/4)) -> 0.11474526 | G22: =4*LN(1+(G21/4)) -> 0.10658176 | H22: =4*LN(1+(H21/4)) -> 0.11556781
C23: Continuously Compounding Daily Risk-Free Rate | F23: =F22/364 -> 0.00031523424 | G23: =G22/364 -> 0.00029280704 | H23: =H22/364 -> 0.000317494
C24: Continuously Compounding Quarterly Risk-free Rate | F24: =F22/4 -> 0.028686316 | G24: =G22/4 -> 0.02664544 | H24: =H22/4 -> 0.028891954

Sheet Up & Down Probability
B2: Up & Down Probability
B4: Forecasted Period | C4: Trading Days | E4: 91 day Treasury Bill Rate
B5: Q1 2025 | C5: =Returns!L240 -> 61 | F5: F' Q1 2025 | G5: F' Q2 2025 | H5: F' Q3 2025
B6: Q2 2025 | C6: =Returns!L301 -> 55 | E6: Continuous Quarterly Rate | F6: ='91Day T-Bill'!F24 -> 0.028686316 | G6: ='91Day T-Bill'!G24 -> 0.02664544 | H6: ='91Day T-Bill'!H24 -> 0.028891954
B7: Q3 2025 | C7: =Returns!L356 -> 63
E9: Components | F9: =B5 -> Q1 2025 | G9: =B6 -> Q2 2025 | H9: =B7 -> Q3 2025
E10: Sqrt(T), √T | F10: =SQRT(C5) -> 7.8102497 | G10: =SQRT(C6) -> 7.4161985 | H10: =SQRT(C7) -> 7.9372539
E11: Portfolio SD, ϭ | F11: ='Forcast 2025Q1'!P7 -> 0.014489549 | G11: ='Forcast 2025Q2'!P7 -> 0.013984826 | H11: ='Forcast 2025Q3'!P7 -> 0.013584022
E12: ϭ*√T | F12: =F11*F10 -> 0.113167 | G12: =G11*G10 -> 0.10371425 | H12: =H11*H10 -> 0.10781983
E13: u | F13: =EXP(F12) -> 1.1198189 | G13: =EXP(G12) -> 1.1092834 | H13: =EXP(H12) -> 1.113847
E14: d | F14: =1/F13 -> 0.89300152 | G14: =1/G13 -> 0.90148286 | H14: =1/H13 -> 0.89778934
E15: a | F15: =EXP(F6) -> 1.0291017 | G15: =EXP(G6) -> 1.0270036 | H15: =EXP(H6) -> 1.0293134
E16: p | F16: =(F15-F14)/(F13-F14) -> 0.60004307 | G16: =(G15-G14)/(G13-G14) -> 0.60404427 | H16: =(H15-H14)/(H13-H14) -> 0.60874495
E17: 1-p | F17: =1-F16 -> 0.39995693 | G17: =1-G16 -> 0.39595573 | H17: =1-H16 -> 0.39125505

Sheet Put Option Dynamics
B2: Put Option Dynamics
B4: Quarter | C4: Number of Trading Days | D4: Historical Rolling SD | E4: Up Factor (u) | F4: Down factor (d) | G4: Quarterly Risk Free Rate (rt) | H4: a | I4: p | J4: 1-p | K4: Discount Factors (e^(-rt))
B5: ='Up & Down Probability'!B5 -> Q1 2025 | C5: ='Up & Down Probability'!C5 -> 61 | D5: ='Up & Down Probability'!F11 -> 0.014489549 | E5: ='Up & Down Probability'!F13 -> 1.1198189 | F5: ='Up & Down Probability'!F14 -> 0.89300152 | G5: ='Up & Down Probability'!F6 -> 0.028686316 | H5: ='Up & Down Probability'!F15 -> 1.0291017 | I5: ='Up & Down Probability'!F16 -> 0.60004307 | J5: ='Up & Down Probability'!F17 -> 0.39995693 | K5: =$C$11^(-G5) -> 0.97172123
B6: ='Up & Down Probability'!B6 -> Q2 2025 | C6: ='Up & Down Probability'!C6 -> 55 | D6: ='Up & Down Probability'!G11 -> 0.013984826 | E6: ='Up & Down Probability'!G13 -> 1.1092834 | F6: ='Up & Down Probability'!G14 -> 0.90148286 | G6: ='Up & Down Probability'!G6 -> 0.02664544 | H6: ='Up & Down Probability'!G15 -> 1.0270036 | I6: ='Up & Down Probability'!G16 -> 0.60404427 | J6: ='Up & Down Probability'!G17 -> 0.39595573 | K6: =$C$11^(-G6) -> 0.97370642
B7: ='Up & Down Probability'!B7 -> Q3 2025 | C7: ='Up & Down Probability'!C7 -> 63 | D7: ='Up & Down Probability'!H11 -> 0.013584022 | E7: ='Up & Down Probability'!H13 -> 1.113847 | F7: ='Up & Down Probability'!H14 -> 0.89778934 | G7: ='Up & Down Probability'!H6 -> 0.028891954 | H7: ='Up & Down Probability'!H15 -> 1.0293134 | I7: ='Up & Down Probability'!H16 -> 0.60874495 | J7: ='Up & Down Probability'!H17 -> 0.39125505 | K7: =$C$11^(-G7) -> 0.97152143
B9: Investment Amount | C9: =Assumptions!C4 -> 1000000
B10: Strike Price | C10: =Assumptions!C6 -> 1050000
B11: e | C11: 2.7182818
F13: =B5 -> Q1 2025 | H13: =B6 -> Q2 2025 | J13: =B7 -> Q3 2025
K15: =I18*E7 -> 1383617
K16: =MAX(0,$C$10-K15) -> 0
I18: =G23*E6 -> 1242196.6
I19: =(K16*$I47+K21*$J$7)*$K47 -> 0
K20: =I18*F7 -> 1115230.8
K21: =MAX(0,$C$10-K20) -> 0
G23: =E33*E5 -> 1119818.9
G24: =(I19*$I$6+I29*$J$6)*$K$6 -> 21056.926
K25: =I28*E7 -> 1124425.9
K26: =MAX(0,$C$10-K25) -> 0
I28: =G23*F6 -> 1009497.6
I29: =(K26*$I$7+K31*$J$7)*$K$7 -> 54616.052
K30: =I28*F7 -> 906316.15
K31: =MAX(0,$C$10-K30) -> 143683.85
E33: =C9 -> 1000000
E34: =(G24*$I$5+G44*$J$5)*$K$5 -> 58463.596
K35: =I38*E7 -> 1103367.7
K36: =MAX(0,$C$10-K35) -> 0
I38: =G43*E6 -> 990591.79
I39: =(K36*$I47+K41*$J$7)*$K$7 -> 61067.858
K40: =I38*F7 -> 889342.74
K41: =MAX(0,$C$10-K40) -> 160657.26
G43: =E33*F5 -> 893001.52
G44: =(I39*$I$6+I49*$J$6)*$K$6 -> 118837.61
K45: =I48*E7 -> 896675.35
K46: =MAX(0,$C$10-K45) -> 153324.65
I48: =G43*F6 -> 805025.57
I49: =(K46*$I$7+K51*$J$7)*$K$7 -> 215071.93
K50: =I48*F7 -> 722743.37
K51: =MAX(0,$C$10-K50) -> 327256.63

Sheet 100% Equity Portfolio
B2: 100% Equity Portfolio
B4: Quarter | C4: Number of Trading Days | D4: Historical Rolling SD | E4: Up Factor (u) | F4: Down factor (d)
B5: ='Put Option Dynamics'!B5 -> Q1 2025 | C5: ='Put Option Dynamics'!C5 -> 61 | D5: ='Put Option Dynamics'!D5 -> 0.014489549 | E5: ='Put Option Dynamics'!E5 -> 1.1198189 | F5: ='Put Option Dynamics'!F5 -> 0.89300152
B6: ='Put Option Dynamics'!B6 -> Q2 2025 | C6: ='Put Option Dynamics'!C6 -> 55 | D6: ='Put Option Dynamics'!D6 -> 0.013984826 | E6: ='Put Option Dynamics'!E6 -> 1.1092834 | F6: ='Put Option Dynamics'!F6 -> 0.90148286
B7: ='Put Option Dynamics'!B7 -> Q3 2025 | C7: ='Put Option Dynamics'!C7 -> 63 | D7: ='Put Option Dynamics'!D7 -> 0.013584022 | E7: ='Put Option Dynamics'!E7 -> 1.113847 | F7: ='Put Option Dynamics'!F7 -> 0.89778934
B9: Investment Amount | C9: ='Put Option Dynamics'!C9 -> 1000000
C14: =B5 -> Q1 2025 | E14: =B6 -> Q2 2025 | G14: =B7 -> Q3 2025
H16: =F18*E7 -> 1383617
F18: =D22*E6 -> 1242196.6
H20: =F18*F7 -> 1115230.8
D22: =B30*E5 -> 1119818.9
H24: =F26*E7 -> 1124425.9
F26: =D22*F6 -> 1009497.6
H28: =F26*F7 -> 906316.15
B30: =C9 -> 1000000
H32: =F34*E7 -> 1103367.7
F34: =D38*E6 -> 990591.79
H36: =F34*F7 -> 889342.74
D38: =B30*F5 -> 893001.52
H40: =F42*E7 -> 896675.35
F42: =D38*F6 -> 805025.57
H44: =F42*F7 -> 722743.37

Sheet Insured Portfolio
C2: Insured Portfolio
D4: Q1 2025 | F4: Q2 2025 | H4: Q3 2025
I6: ='Put Option Dynamics'!K15+'Put Option Dynamics'!K16 -> 1383617
G8: ='Put Option Dynamics'!I18+'Put Option Dynamics'!I19 -> 1242196.6
I10: ='Put Option Dynamics'!K20+'Put Option Dynamics'!K21 -> 1115230.8
E12: ='Put Option Dynamics'!G23+'Put Option Dynamics'!G24 -> 1140875.8
I14: ='Put Option Dynamics'!K25+'Put Option Dynamics'!K26 -> 1124425.9
G16: ='Put Option Dynamics'!I28+'Put Option Dynamics'!I29 -> 1064113.6
I18: ='Put Option Dynamics'!K30+'Put Option Dynamics'!K31 -> 1050000
C19: ='Put Option Dynamics'!E33+'Put Option Dynamics'!E34 -> 1058463.6
I22: ='Put Option Dynamics'!K35+'Put Option Dynamics'!K36 -> 1103367.7
G24: ='Put Option Dynamics'!I38+'Put Option Dynamics'!I39 -> 1051659.6
I26: ='Put Option Dynamics'!K40+'Put Option Dynamics'!K41 -> 1050000
E28: ='Put Option Dynamics'!G43+'Put Option Dynamics'!G44 -> 1011839.1
I30: ='Put Option Dynamics'!K45+'Put Option Dynamics'!K46 -> 1050000
E31: Floor price
G32: ='Put Option Dynamics'!I48+'Put Option Dynamics'!I49 -> 1020097.5
I34: ='Put Option Dynamics'!K50+'Put Option Dynamics'!K51 -> 1050000

Sheet Call Option Dynamics
B2: Call Option Dynamics
B4: Quarter | C4: Number of Trading Days | D4: Historical Rolling SD | E4: Up Factor (u) | F4: Down factor (d) | G4: Quarterly Risk Free Rate (rt) | H4: a | I4: p | J4: 1-p | K4: Discount Factors (e^(-rt))
B5: ='Put Option Dynamics'!B5 -> Q1 2025 | C5: ='Put Option Dynamics'!C5 -> 61 | D5: ='Put Option Dynamics'!D5 -> 0.014489549 | E5: ='Put Option Dynamics'!E5 -> 1.1198189 | F5: ='Put Option Dynamics'!F5 -> 0.89300152 | G5: ='Put Option Dynamics'!G5 -> 0.028686316 | H5: ='Put Option Dynamics'!H5 -> 1.0291017 | I5: ='Put Option Dynamics'!I5 -> 0.60004307 | ... K5: ='Put Option Dynamics'!K5 -> 0.97172123
B6: ='Put Option Dynamics'!B6 -> Q2 2025 | C6: ='Put Option Dynamics'!C6 -> 55 | D6: ='Put Option Dynamics'!D6 -> 0.013984826 | E6: ='Put Option Dynamics'!E6 -> 1.1092834 | F6: ='Put Option Dynamics'!F6 -> 0.90148286 | G6: ='Put Option Dynamics'!G6 -> 0.02664544 | H6: ='Put Option Dynamics'!H6 -> 1.0270036 | I6: ='Put Option Dynamics'!I6 -> 0.60404427 | ... K6: ='Put Option Dynamics'!K6 -> 0.97370642
B7: ='Put Option Dynamics'!B7 -> Q3 2025 | C7: ='Put Option Dynamics'!C7 -> 63 | D7: ='Put Option Dynamics'!D7 -> 0.013584022 | E7: ='Put Option Dynamics'!E7 -> 1.113847 | F7: ='Put Option Dynamics'!F7 -> 0.89778934 | G7: ='Put Option Dynamics'!G7 -> 0.028891954 | H7: ='Put Option Dynamics'!H7 -> 1.0293134 | I7: ='Put Option Dynamics'!I7 -> 0.60874495 | ... K7: ='Put Option Dynamics'!K7 -> 0.97152143
B9: Investment Amount | C9: ='Put Option Dynamics'!C9 -> 1000000
B10: Strike Price | C10: ='Put Option Dynamics'!C10 -> 1050000
F11: =B5 -> Q1 2025 | H11: =B6 -> Q2 2025 | J11: =B7 -> Q3 2025
K14: =I17*E7 -> 1383617
K15: =MAX(0,K14-$C$10) -> 333616.98
I17: =G21*E6 -> 1242196.6
I18: =(K15*$I$7+K20*$J$7)*$K$7 -> 222099.07
K19: =I17*F7 -> 1115230.8
K20: =MAX(0,K19-$C$10) -> 65230.836
G21: =E31*E5 -> 1119818.9
G22: =(I18*$I$6+I27*$J$6)*$K$6 -> 147600.37
K24: =I26*E7 -> 1124425.9
K25: =MAX(0,K24-$C$10) -> 74425.883
I26: =G21*F6 -> 1009497.6
I27: =(K25*$I$7+K30*$J$7)*$K$7 -> 44016.119
K29: =I26*F7 -> 906316.15
K30: =MAX(0,K29-$C$10) -> 0
E31: =C9 -> 1000000
E32: =(G22*$I$5+G42*$J$5)*$K$5 -> 93276.723
K34: =I37*E7 -> 1103367.7
K35: =MAX(0,K34-$C$10) -> 53367.737
I37: =G41*E6 -> 990591.79
I38: =(K35*$I$7+K41*$J$7)*$K$7 -> 31562.147
K39: =I37*F7 -> 889342.74
K40: =MAX(0,K39-$C$10) -> 0
G41: =E31*F5 -> 893001.52
G42: =(I38*$I$6+I47*$J$6)*$K$6 -> 18563.649
K44: =I46*E7 -> 896675.35
K45: =MAX(0,K44-$C$10) -> 0
I46: =G41*F6 -> 805025.57
I47: =(K45*$I$7+K50*$J$7)*$K$7 -> 0
K49: =I46*F7 -> 722743.37
K50: =MAX(0,K49-$C$10) -> 0

Sheet Delta 1
B2: Delta 1
B4: Quarter | C4: Number of Trading Days | D4: Historical Rolling SD | E4: Up Factor (u) | F4: Down factor (d) | G4: Risk Free Rate | H4: a | I4: p | J4: 1-p | K4: Discount Factors
B5: ='Call Option Dynamics'!B5 -> Q1 2025 | C5: ='Call Option Dynamics'!C5 -> 61 | D5: ='Call Option Dynamics'!D5 -> 0.014489549 | E5: ='Call Option Dynamics'!E5 -> 1.1198189 | F5: ='Call Option Dynamics'!F5 -> 0.89300152 | G5: ='Call Option Dynamics'!G5 -> 0.028686316 | H5: ='Call Option Dynamics'!H5 -> 1.0291017 | I5: ='Call Option Dynamics'!I5 -> 0.60004307 | ... K5: ='Call Option Dynamics'!K5 -> 0.97172123
B6: ='Call Option Dynamics'!B6 -> Q2 2025 | C6: ='Call Option Dynamics'!C6 -> 55 | D6: ='Call Option Dynamics'!D6 -> 0.013984826 | E6: ='Call Option Dynamics'!E6 -> 1.1092834 | F6: ='Call Option Dynamics'!F6 -> 0.90148286 | G6: ='Call Option Dynamics'!G6 -> 0.02664544 | H6: ='Call Option Dynamics'!H6 -> 1.0270036 | I6: ='Call Option Dynamics'!I6 -> 0.60404427 | ... K6: ='Call Option Dynamics'!K6 -> 0.97370642
B7: ='Call Option Dynamics'!B7 -> Q3 2025 | C7: ='Call Option Dynamics'!C7 -> 63 | D7: ='Call Option Dynamics'!D7 -> 0.013584022 | E7: ='Call Option Dynamics'!E7 -> 1.113847 | F7: ='Call Option Dynamics'!F7 -> 0.89778934 | G7: ='Call Option Dynamics'!G7 -> 0.028891954 | H7: ='Call Option Dynamics'!H7 -> 1.0293134 | I7: ='Call Option Dynamics'!I7 -> 0.60874495 | ... K7: ='Call Option Dynamics'!K7 -> 0.97152143
B9: Investment Amount | C9: ='Call Option Dynamics'!C9 -> 1000000
B10: Strike Price | C10: ='Call Option Dynamics'!C10 -> 1050000
E13: =B5 -> Q1 2025 | G13: =B6 -> Q2 2025 | I13: =B7 -> Q3 2025
J14: ='100% Equity Portfolio'!H16 -> 1383617
J15: N/A
H16: ='100% Equity Portfolio'!F18 -> 1242196.6
H17: =('Call Option Dynamics'!K15-'Call Option Dynamics'!K20)/('Call Option Dynamics'!K14-'Call Option Dynamics'!K19) -> 1
J19: ='100% Equity Portfolio'!H20 -> 1115230.8
F20: ='100% Equity Portfolio'!D22 -> 1119818.9 | J20: N/A
F21: =('Call Option Dynamics'!I18-'Call Option Dynamics'!I27)/('Call Option Dynamics'!I17-'Call Option Dynamics'!I26) -> 0.76529315
J24: ='100% Equity Portfolio'!H24 -> 1124425.9
J25: N/A
H26: ='100% Equity Portfolio'!F26 -> 1009497.6
H27: =('Call Option Dynamics'!K25-'Call Option Dynamics'!K30)/('Call Option Dynamics'!K24-'Call Option Dynamics'!K29) -> 0.34123137
J29: ='100% Equity Portfolio'!H28 -> 906316.15
J30: N/A
D31: ='100% Equity Portfolio'!B30 -> 1000000
D32: =('Call Option Dynamics'!G22-'Call Option Dynamics'!G42)/('Call Option Dynamics'!G21-'Call Option Dynamics'!G41) -> 0.56890131
J34: ='100% Equity Portfolio'!H32 -> 1103367.7
J35: N/A
H37: ='100% Equity Portfolio'!F34 -> 990591.79
H38: =('Call Option Dynamics'!K35-'Call Option Dynamics'!K40)/('Call Option Dynamics'!K34-'Call Option Dynamics'!K39) -> 0.24935283
J39: ='100% Equity Portfolio'!H36 -> 889342.74
J40: N/A
F42: ='100% Equity Portfolio'!D38 -> 893001.52
F43: =('Call Option Dynamics'!I38-'Call Option Dynamics'!I47)/('Call Option Dynamics'!I37-'Call Option Dynamics'!I46) -> 0.17008563
J44: ='100% Equity Portfolio'!H40 -> 896675.35
J45: N/A
H46: ='100% Equity Portfolio'!F42 -> 805025.57
H47: =('Call Option Dynamics'!K45-'Call Option Dynamics'!K50)/('Call Option Dynamics'!K44-'Call Option Dynamics'!K49) -> 0
J49: ='100% Equity Portfolio'!H44 -> 722743.37
J50: N/A

Sheet Delta 2
C2: Delta 2
D5: Q1 2025 | F5: Q2 2025 | H5: Q3 2025
I7: N/A
G9: =('Insured Portfolio'!I6-'Insured Portfolio'!I10)/('100% Equity Portfolio'!H16-'100% Equity Portfolio'!H20) -> 1
I11: N/A
E12: =('Insured Portfolio'!G8-'Insured Portfolio'!G16)/('100% Equity Portfolio'!F18-'100% Equity Portfolio'!F26) -> 0.76529315
I14: N/A
G16: =('Insured Portfolio'!I14-'Insured Portfolio'!I18)/('100% Equity Portfolio'!H24-'100% Equity Portfolio'!H28) -> 0.34123137
I18: N/A
C20: =('Insured Portfolio'!$E$12-'Insured Portfolio'!$E$28)/('100% Equity Portfolio'!$D$22-'100% Equity Portfolio'!$D$38) -> 0.56890131
I22: N/A
G24: =('Insured Portfolio'!I22-'Insured Portfolio'!I26)/('100% Equity Portfolio'!H32-'100% Equity Portfolio'!H36) -> 0.24935283
I26: N/A
E28: =('Insured Portfolio'!G24-'Insured Portfolio'!G32)/('100% Equity Portfolio'!F34-'100% Equity Portfolio'!H34) -> 0.031861911
I30: N/A
G32: =('Insured Portfolio'!I30-'Insured Portfolio'!I34)/('100% Equity Portfolio'!H40-'100% Equity Portfolio'!H44) -> 0
I34: N/A

Sheet Dynamic Asset Allocation
C3: Dynamic Asset Allocation
C6: Initial Stage | E6: Q1 2025 | H6: Q2 2025 | L6: Q3 2025
J10: Q2 2025 (A) | N10: Q3 2025 (A)
J11: 100% Equity Port. | K11: ='100% Equity Portfolio'!F18 -> 1242196.6 | N11: 100% Equity Port. | O11: ='100% Equity Portfolio'!H16 -> 1383617
J12: Insured Portfolio | N12: Insured Portfolio | T12: Quarter | U12: u | V12: d | W12: Quarterly Risk Free Rate (rt) | X12: a | Y12: p | Z12: (1-p)
J13: Equity | K13: =K11*G32 -> 950644.52 | N13: Equity | O13: =K16*O11 -> 1383617 | T13: ='Put Option Dynamics'!B5 -> Q1 2025 | U13: ='Put Option Dynamics'!E5 -> 1.1198189 | V13: ='Put Option Dynamics'!F5 -> 0.89300152 | W13: ='Put Option Dynamics'!G5 -> 0.028686316 | X13: ='Put Option Dynamics'!H5 -> 1.0291017 | Y13: ='Put Option Dynamics'!I5 -> 0.60004307 | Z13: ='Put Option Dynamics'!J5 -> 0.39995693
J14: T-bill | K14: =G38*V23 -> 453310.98 | N14: T-bill | O14: =K22*W23 -> 166500.63 | T14: ='Put Option Dynamics'!B6 -> Q2 2025 | U14: ='Put Option Dynamics'!E6 -> 1.1092834 | V14: ='Put Option Dynamics'!F6 -> 0.90148286 | W14: ='Put Option Dynamics'!G6 -> 0.02664544 | X14: ='Put Option Dynamics'!H6 -> 1.0270036 | Y14: ='Put Option Dynamics'!I6 -> 0.60404427 | Z14: ='Put Option Dynamics'!J6 -> 0.39595573
J15: Total Value | K15: =K13+K14 -> 1403955.5 | N15: Total Value | O15: =O13+O14 -> 1550117.6 | T15: ='Put Option Dynamics'!B7 -> Q3 2025 | U15: ='Put Option Dynamics'!E7 -> 1.113847 | V15: ='Put Option Dynamics'!F7 -> 0.89778934 | W15: ='Put Option Dynamics'!G7 -> 0.028891954 | X15: ='Put Option Dynamics'!H7 -> 1.0293134 | Y15: ='Put Option Dynamics'!I7 -> 0.60874495 | Z15: ='Put Option Dynamics'!J7 -> 0.39125505
J16: Delta Q2 | K16: ='Delta 1'!H17 -> 1
J17: Action To Be Taken | T17: e | U17: 2.7182818
J18: Buy Stock ( 1,242,196.57*(1.00-0.77)) | K18: =K11*(K16-G32) -> 291552.05 | N18: Q3 2025 (B)
J19: Sell T-Bill | K19: =K15-K13-K18-K14 -> -291552.05 | N19: 100% Equity Port. | O19: ='100% Equity Portfolio'!H20 -> 1115230.8
J20: New Portfolio | N20: Insured Portfolio
J21: Equity (1.00* 1,242,196.57) | K21: =K16*K11 -> 1242196.6 | N21: Equity | O21: =K16*O19 -> 1115230.8 | T21: 91 day T-Bill Rate
J22: T-Bill | K22: =K14+K19 -> 161758.93 | N22: T-bill | O22: =K22*W23 -> 166500.63 | U22: =T13 -> Q1 2025 | V22: =T14 -> Q2 2025 | W22: =T15 -> Q3 2025
J23: Total Value | K23: =K21+K22 -> 1403955.5 | N23: Total Value | O23: =O21+O22 -> 1281731.5 | T23: Compounding Quarterly Rate (e^(rt)) | U23: =U17^W13 -> 1.0291017 | V23: =U17^W14 -> 1.0270036 | W23: =U17^W15 -> 1.0293134
F26: Q1 2025 (A)
F27: 100% Equity Port. | G27: ='100% Equity Portfolio'!D22 -> 1119818.9
F28: Insured Portfolio
F29: Equity | G29: =G27*D60 -> 637066.45
F30: T-bill | G30: =D63*U23 -> 661315.1
F31: Total Value | G31: =G29+G30 -> 1298381.6
F32: Delta Q1 | G32: ='Delta 1'!F21 -> 0.76529315
F33: Action To be Taken
F34: Buy Stock ( 1,119,818.92*(0.77-0.57)) | G34: =G27*(G32-D60) -> 219923.29
F35: Sell T-Bill | G35: =G31-G29-G34-G30 -> -219923.29
F36: New Portfolio
F37: Equity (0.77* 1,119,818.92) | G37: =G32*G27 -> 856989.74
F38: T-Bill | G38: =G30+G35 -> 441391.81
F39: Total Value | G39: =G37+G38 -> 1298381.6
J41: Q2 2025 (B) | N41: Q3 2025 (C)
J42: 100% Equity Port. | K42: ='100% Equity Portfolio'!F26 -> 1009497.6 | N42: 100% Equity Port. | O42: ='100% Equity Portfolio'!H24 -> 1124425.9
J43: Insured Portfolio | N43: Insured Portfolio
J44: Equity | K44: =K42*G32 -> 772561.57 | N44: Equity | O44: =K47*O42 -> 383689.38
J45: T-bill | K45: =G38*V23 -> 453310.98 | N45: T-bill | O45: =K53*W23 -> 907237.12
J46: Total Value | K46: =K44+K45 -> 1225872.5 | N46: Total Value | O46: =O44+O45 -> 1290926.5
J47: Delta Q2 | K47: ='Delta 1'!H27 -> 0.34123137
J48: Action To Be Taken
J49: Sell Stock (1,009,497.57*(0.34-0.77)) | K49: =K42*(K47-G32) -> -428089.33 | N49: Q3 2025 (D)
J50: Buy T-Bill | K50: =K46-K44-K49-K45 -> 428089.33 | N50: 100% Equity Port. | O50: ='100% Equity Portfolio'!H28 -> 906316.15
J51: New Portfolio | N51: Insured Portfolio
J52: Equity (0.34* 1,009,497.57 ) | K52: =K47*K42 -> 344472.24 | N52: Equity | O52: =K47*O50 -> 309263.5
J53: T-Bill | K53: =K45+K50 -> 881400.31 | N53: T-bill | O53: =K53*W23 -> 907237.12
J54: Total Value | K54: =K52+K53 -> 1225872.5 | N54: Total Value | O54: =O52+O53 -> 1216500.6
C57: Q4 2024 (Initial value)
C58: 100% Equity Port. | D58: ='100% Equity Portfolio'!B30 -> 1000000
C59: Insured Portfolio | D59: 1211515.2
C60: Initial Delta | D60: ='Delta 1'!D32 -> 0.56890131
C61: New Portfolio
C62: Equity (0.57*1,000,000) | D62: =D60*D58 -> 568901.31
C63: T-Bill | D63: =D59-D62 -> 642613.92
C64: Total Value | D64: =D62+D63 -> 1211515.2
J66: Q2 2025 (C) | N66: Q3 2025 (E)
J67: 100% Equity Port. | K67: ='100% Equity Portfolio'!F34 -> 990591.79 | N67: 100% Equity Port. | O67: ='100% Equity Portfolio'!H32 -> 1103367.7
J68: Insured Portfolio | N68: Insured Portfolio
J69: Equity | K69: =K67*G88 -> 168485.43 | N69: Equity | O69: =O67*K72 -> 275127.87
J70: T-bill | K70: =G94*V23 -> 1044933.1 | N70: T-bill | O70: =K78*W23 -> 994740.5
J71: Total Value | K71: =K69+K70 -> 1213418.6 | N71: Total Value | O71: =O69+O70 -> 1269868.4
J72: Delta Q2 | K72: ='Delta 1'!H38 -> 0.24935283
J73: Action To Be Taken
J74: Buy Stock(990,591.79*(0.25-0.17)) | K74: =K67*(K72-G88) -> 78521.437 | N74: Q3 2025 (F)
J75: Sell T-Bill | K75: =K71-K69-K74-K70 -> -78521.437 | N75: 100% Equity Port. | O75: ='100% Equity Portfolio'!H36 -> 889342.74
J76: New Portfolio | N76: Insured Portfolio
J77: Equity (0.25*990,591.79) | K77: =K72*K67 -> 247006.86 | N77: Equity | O77: =O75*K72 -> 221760.13
J78: T-Bill | K78: =K70+K75 -> 966411.71 | N78: T-bill | O78: =K78*W23 -> 994740.5
J79: Total Value | K79: =K77+K78 -> 1213418.6 | N79: Total Value | O79: =O77+O78 -> 1216500.6
F82: Q1 2025 (B)
F83: 100% Equity Port. | G83: ='100% Equity Portfolio'!D38 -> 893001.52
F84: Insured Portfolio
F85: Equity | G85: =D60*G83 -> 508029.74
F86: T-bill | G86: =D63*U23 -> 661315.1
F87: Total Value | G87: =G85+G86 -> 1169344.8
F88: Delta Q1 | G88: ='Delta 1'!F43 -> 0.17008563
F89: Action To Be Taken
F90: Sell Stock ( 893,001.52*(0.17-0.57)) | G90: =G83*(G88-D60) -> -356143.01
F91: Buy T-Bill | G91: =G87-G85-G90-G86 -> 356143.01
F92: New Portfolio
F93: Equity (0.17* 893,001.52 ) | G93: =G88*G83 -> 151886.72
F94: T-Bill | G94: =G86+G91 -> 1017458.1
F95: Total Value | G95: =G93+G94 -> 1169344.8
J97: Q2 2025 (D) | N97: Q3 2025 (G)
J98: 100% Equity Port. | K98: ='100% Equity Portfolio'!F42 -> 805025.57 | N98: 100% Equity Port. | O98: ='100% Equity Portfolio'!H40 -> 896675.35
J99: Insured Portfolio | N99: Insured Portfolio
J100: Equity | K100: =K98*G88 -> 136923.28 | N100: Equity | O100: =O98*K103 -> 0
J101: T-bill | K101: =G94*V23 -> 1044933.1 | N101: T-bill | O101: =K109*W23 -> 1216500.6
J102: Total Value | K102: =K100+K101 -> 1181856.4 | N102: Total Value | O102: =O100+O101 -> 1216500.6
J103: Delta Q1 | K103: ='Delta 1'!H47 -> 0
J104: Action To Be Taken
J105: Sell Stock (805,025.57*(0-0.17)) | K105: =K98*(K103-G88) -> -136923.28 | N105: Q3 2025 (H)
J106: Buy T-Bill | K106: =K102-K100-K105-K101 -> 136923.28 | N106: 100% Equity Port. | O106: ='100% Equity Portfolio'!H44 -> 722743.37
J107: New Portfolio | N107: Insured Portfolio
J108: Equity (0*805,025.57) | K108: =K103*K98 -> 0 | N108: Equity | O108: =O106*K103 -> 0
J109: T-Bill | K109: =K101+K106 -> 1181856.4 | N109: T-bill | O109: =K109*W23 -> 1216500.6
J110: Total Value | K110: =K108+K109 -> 1181856.4 | N110: Total Value | O110: =O108+O109 -> 1216500.6
C112: Initial Stage | E112: Q1 2025 | H112: Q2 2025 | L112: Q3 2025
C117: Actually Related with DSEX Index | H117: Dynamic Asset Allocation
C118: Quarter | D118: Average DSEX Value | E118: Change in the Averge DSEX Value | H118: Particulars | I118: Q04 2024 | K118: Q01 2025 | M118: Q02 2025 | O118: Q03 2025
C119: ='DSEX Data'!G3 -> Q4 2024 | D119: ='DSEX Data'!H3 -> 5243.632 | H119: Equity Value (BDT) | L119: =G93 -> 151886.72 | N119: =M107 -> 0 | P119: =Q109 -> 0
C120: ='DSEX Data'!G4 -> Q1 2025 | D120: ='DSEX Data'!H4 -> 5190.0984 | E120: =D120-D119 -> -53.53362 | H120: T-Bill Value (BDT) | L120: =G94 -> 1017458.1 | N120: =K109 -> 1181856.4 | P120: =O101 -> 1216500.6
C121: ='DSEX Data'!G5 -> Q2 2025 | D121: ='DSEX Data'!H5 -> 4878.9333 | E121: =D121-D120 -> -311.16509 | H121: Total Value (BDT) | J121: =D58 -> 1000000 | L121: =SUM(L119:L120) -> 1169344.8 | N121: =SUM(N119:N120) -> 1181856.4 | P121: =SUM(P119:P120) -> 1216500.6
...

Sheet Static Asset Allocation
B2: Static Asset Allocation
B5: Particulars | C5: Value | G5: Risk Free Rate
B6: Initial portfolio value | C6: ='Call Option Dynamics'!C9 -> 1000000 | H6: Terms | I6: Q1 2025 | J6: Q2 2025 | K6: Q3 2025
B7: Equity investment | C7: =$C$6*0.5 -> 500000 | G7: Quarterly Rate | H7: rt | I7: ='Call Option Dynamics'!G5 -> 0.028686316 | J7: ='Call Option Dynamics'!G6 -> 0.02664544 | K7: ='Call Option Dynamics'!G7 -> 0.028891954
B8: Risk-free investment | C8: =$C$6*0.5 -> 500000 | G8: Compounding Rate | H8: e^rt | I8: ='Dynamic Asset Allocation'!U23 -> 1.0291017 | J8: ='Dynamic Asset Allocation'!V23 -> 1.0270036 | K8: ='Dynamic Asset Allocation'!W23 -> 1.0293134
G9: Discount Factor | H9: e^-rt | I9: ='Call Option Dynamics'!K5 -> 0.97172123 | J9: ='Call Option Dynamics'!K6 -> 0.97370642 | K9: ='Call Option Dynamics'!K7 -> 0.97152143
B11: Investment in Risky Assets
B12: Company | C12: Invested Amount | D12: Share Price at 30-12-2024 | E12: Number of Shares Purchased
B13: ='Stock Selection'!C5 -> UCB | C13: =$C$7*(1/8) -> 62500 | D13: =Data!G237 -> 9.2 | E13: =C13/D13 -> 6793.4783
B14: ='Stock Selection'!C6 -> IDLC | C14: =$C$7*(1/8) -> 62500 | D14: =Data!O237 -> 32.7 | E14: =C14/D14 -> 1911.315
B15: ='Stock Selection'!C7 -> GP | C15: =$C$7*(1/8) -> 62500 | D15: =Data!W237 -> 323.1 | E15: =C15/D15 -> 193.43856
B16: ='Stock Selection'!C8 -> BATASHOE | C16: =$C$7*(1/8) -> 62500 | D16: =Data!AE237 -> 905.4 | E16: =C16/D16 -> 69.030263
B17: ='Stock Selection'!C9 -> RENATA | C17: =$C$7*(1/8) -> 62500 | D17: =Data!AM237 -> 635.1 | E17: =C17/D17 -> 98.409699
B18: ='Stock Selection'!C10 -> WALTONHIL | C18: =$C$7*(1/8) -> 62500 | D18: =Data!AU237 -> 487.5 | E18: =C18/D18 -> 128.20513
B19: ='Stock Selection'!C11 -> RAKC | C19: =$C$7*(1/8) -> 62500 | D19: =Data!BC237 -> 22.6 | E19: =C19/D19 -> 2765.4867
B20: ='Stock Selection'!C12 -> OLYMPIC | C20: =$C$7*(1/8) -> 62500 | D20: =Data!BK237 -> 158 | E20: =C20/D20 -> 395.56962
B21: Total Investment | C21: =SUM(C13:C20) -> 500000
B23: Company Name | C23: Q1 2025 | E23: Q2 2025 | G23: Q3 2025
C24: Closing price | D24: Portfolio value | E24: Closing price | F24: Portfolio value | G24: Closing price | H24: Portfolio value
B25: =B13 -> UCB | C25: =Data!G298 -> 11 | D25: =C25*E13 -> 74728.261 | E25: =Data!G353 -> 9.9 | F25: =E25*E13 -> 67255.435 | G25: =Data!G416 -> 10.6 | H25: =G25*E13 -> 72010.87
B26: =B14 -> IDLC | C26: =Data!O298 -> 31.4 | D26: =C26*E14 -> 60015.291 | E26: =Data!O353 -> 29 | F26: =E26*E14 -> 55428.135 | G26: =Data!O416 -> 41.2 | H26: =G26*E14 -> 78746.177
B27: =B15 -> GP | C27: =Data!W298 -> 321.9 | D27: =C27*E15 -> 62267.874 | E27: =Data!W353 -> 303.1 | F27: =E27*E15 -> 58631.229 | G27: =Data!W416 -> 299 | H27: =G27*E15 -> 57838.131
B28: =B16 -> BATASHOE | C28: =Data!AE298 -> 834.7 | D28: =C28*E16 -> 57619.56 | E28: =Data!AE353 -> 802.7 | F28: =E28*E16 -> 55410.592 | G28: =Data!AE416 -> 877.7 | H28: =G28*E16 -> 60587.862
B29: =B17 -> RENATA | C29: =Data!AM298 -> 500.5 | D29: =C29*E17 -> 49254.054 | E29: =Data!AM353 -> 488.4 | F29: =E29*E17 -> 48063.297 | G29: =Data!AM416 -> 480.4 | H29: =G29*E17 -> 47276.02
B30: =B18 -> WALTONHIL | C30: =Data!AU298 -> 462.7 | D30: =C30*E18 -> 59320.513 | E30: =Data!AU353 -> 406.3 | F30: =E30*E18 -> 52089.744 | G30: =Data!AU416 -> 419.9 | H30: =G30*E18 -> 53833.333
B31: =B19 -> RAKC | C31: =Data!BC298 -> 22.6 | D31: =C31*E19 -> 62500 | E31: =Data!BC353 -> 19.2 | F31: =E31*E19 -> 53097.345 | G31: =Data!BC416 -> 25.1 | H31: =G31*E19 -> 69413.717
B32: =B20 -> OLYMPIC | C32: =Data!BK298 -> 147.2 | D32: =C32*E20 -> 58227.848 | E32: =Data!BK353 -> 153.5 | F32: =E32*E20 -> 60719.937 | G32: =Data!BK416 -> 154.7 | H32: =G32*E20 -> 61194.62
B33: Total Value of Equity | D33: =SUM(D25:D32) -> 483933.4 | F33: =SUM(F25:F32) -> 450695.71 | H33: =SUM(H25:H32) -> 500900.73
B35: Static Portfolio Value
C36: Q4 2024 | D36: Q1 2025 | E36: Q2 2025 | F36: Q3 2025
B37: Stock | C37: =C7 -> 500000 | D37: =D33 -> 483933.4 | E37: =F33 -> 450695.71 | F37: =H33 -> 500900.73
B38: Risk Free Asset | C38: =C8 -> 500000 | D38: =$C$8*I8 -> 514550.87 | E38: =D38*J8 -> 528445.59 | F38: =E38*K8 -> 543936.12
B39: Total | C39: =C37+C38 -> 1000000 | D39: =D37+D38 -> 998484.27 | E39: =E37+E38 -> 979141.31 | F39: =F37+F38 -> 1044836.8
B40: ROI | D40: =(D39-C39)/C39 -> -0.0015157337 | E40: =(E39-D39)/D39 -> -0.019372324 | F40: =(F39-E39)/E39 -> 0.067095056
B41: Changes in ROI | E41: =E40-D40 -> -0.01785659 | F41: =F40-E40 -> 0.086467379

Sheet 100% Equity and DAA
B2: 100% Equity and Dynamic Asset Allocation
B4: Particulars | C4: Value
B5: Initial portfolio value | C5: ='Static Asset Allocation'!C6 -> 1000000
B6: Equity investment | C6: =C5*100% -> 1000000
B7: Risk-free investment | C7: =C5*0% -> 0
B9: Investment in Risky Assets
B10: Company | C10: Invested Amount | D10: Share Price at 30-12-2024 | E10: Number of Shares Purchased
B11: ='Static Asset Allocation'!B13 -> UCB | C11: =$C$6*(1/8) -> 125000 | D11: ='Static Asset Allocation'!D13 -> 9.2 | E11: =C11/D11 -> 13586.957
B12: ='Static Asset Allocation'!B14 -> IDLC | C12: =$C$6*(1/8) -> 125000 | D12: ='Static Asset Allocation'!D14 -> 32.7 | E12: =C12/D12 -> 3822.63
B13: ='Static Asset Allocation'!B15 -> GP | C13: =$C$6*(1/8) -> 125000 | D13: ='Static Asset Allocation'!D15 -> 323.1 | E13: =C13/D13 -> 386.87713
B14: ='Static Asset Allocation'!B16 -> BATASHOE | C14: =$C$6*(1/8) -> 125000 | D14: ='Static Asset Allocation'!D16 -> 905.4 | E14: =C14/D14 -> 138.06053
B15: ='Static Asset Allocation'!B17 -> RENATA | C15: =$C$6*(1/8) -> 125000 | D15: ='Static Asset Allocation'!D17 -> 635.1 | E15: =C15/D15 -> 196.8194
B16: ='Static Asset Allocation'!B18 -> WALTONHIL | C16: =$C$6*(1/8) -> 125000 | D16: ='Static Asset Allocation'!D18 -> 487.5 | E16: =C16/D16 -> 256.41026
B17: ='Static Asset Allocation'!B19 -> RAKC | C17: =$C$6*(1/8) -> 125000 | D17: ='Static Asset Allocation'!D19 -> 22.6 | E17: =C17/D17 -> 5530.9735
B18: ='Static Asset Allocation'!B20 -> OLYMPIC | C18: =$C$6*(1/8) -> 125000 | D18: ='Static Asset Allocation'!D20 -> 158 | E18: =C18/D18 -> 791.13924
B19: Total Investment | C19: =SUM(C11:C18) -> 1000000
B21: Company Name | C21: Q1 2025 | E21: Q2 2025 | G21: Q3 2025
C22: Closing price | D22: Portfolio value | E22: Closing price | F22: Portfolio value | G22: Closing price | H22: Portfolio value
B23: =B11 -> UCB | C23: ='Static Asset Allocation'!C25 -> 11 | D23: =C23*E11 -> 149456.52 | E23: ='Static Asset Allocation'!E25 -> 9.9 | F23: =E23*E11 -> 134510.87 | G23: ='Static Asset Allocation'!G25 -> 10.6 | H23: =G23*E11 -> 144021.74
B24: =B12 -> IDLC | C24: ='Static Asset Allocation'!C26 -> 31.4 | D24: =C24*E12 -> 120030.58 | E24: ='Static Asset Allocation'!E26 -> 29 | F24: =E24*E12 -> 110856.27 | G24: ='Static Asset Allocation'!G26 -> 41.2 | H24: =G24*E12 -> 157492.35
B25: =B13 -> GP | C25: ='Static Asset Allocation'!C27 -> 321.9 | D25: =C25*E13 -> 124535.75 | E25: ='Static Asset Allocation'!E27 -> 303.1 | F25: =E25*E13 -> 117262.46 | G25: ='Static Asset Allocation'!G27 -> 299 | H25: =G25*E13 -> 115676.26
B26: =B14 -> BATASHOE | C26: ='Static Asset Allocation'!C28 -> 834.7 | D26: =C26*E14 -> 115239.12 | E26: ='Static Asset Allocation'!E28 -> 802.7 | F26: =E26*E14 -> 110821.18 | G26: ='Static Asset Allocation'!G28 -> 877.7 | H26: =G26*E14 -> 121175.72
B27: =B15 -> RENATA | C27: ='Static Asset Allocation'!C29 -> 500.5 | D27: =C27*E15 -> 98508.109 | E27: ='Static Asset Allocation'!E29 -> 488.4 | F27: =E27*E15 -> 96126.594 | G27: ='Static Asset Allocation'!G29 -> 480.4 | H27: =G27*E15 -> 94552.039
B28: =B16 -> WALTONHIL | C28: ='Static Asset Allocation'!C30 -> 462.7 | D28: =C28*E16 -> 118641.03 | E28: ='Static Asset Allocation'!E30 -> 406.3 | F28: =E28*E16 -> 104179.49 | G28: ='Static Asset Allocation'!G30 -> 419.9 | H28: =G28*E16 -> 107666.67
B29: =B17 -> RAKC | C29: ='Static Asset Allocation'!C31 -> 22.6 | D29: =C29*E17 -> 125000 | E29: ='Static Asset Allocation'!E31 -> 19.2 | F29: =E29*E17 -> 106194.69 | G29: ='Static Asset Allocation'!G31 -> 25.1 | H29: =G29*E17 -> 138827.43
B30: =B18 -> OLYMPIC | C30: ='Static Asset Allocation'!C32 -> 147.2 | D30: =C30*E18 -> 116455.7 | E30: ='Static Asset Allocation'!E32 -> 153.5 | F30: =E30*E18 -> 121439.87 | G30: ='Static Asset Allocation'!G32 -> 154.7 | H30: =G30*E18 -> 122389.24
B31: Total Value of Equity | D31: =SUM(D23:D30) -> 967866.8 | F31: =SUM(F23:F30) -> 901391.43 | H31: =SUM(H23:H30) -> 1001801.5
B33: 100% Equity Portfolio Value
C34: Q1 2025 | D34: Q2 2025 | E34: Q3 2025
B35: Stock | C35: =D31 -> 967866.8 | D35: =F31 -> 901391.43 | E35: =H31 -> 1001801.5
B36: Risk Free Asset | C36: 0 | D36: 0 | E36: 0
B37: Total | C37: =C35+C36 -> 967866.8 | D37: =D35+D36 -> 901391.43 | E37: =E35+E36 -> 1001801.5
B38: ROI | C38: =(C37-C6)/C6 -> -0.032133198 | D38: =(D37-C37)/C37 -> -0.068682361 | E38: =(E37-D37)/D37 -> 0.11139448
B39: Changes in ROI | D39: =D38-C38 -> -0.036549162 | E39: =E38-D38 -> 0.18007685
B41: Dynamic Asset Allocation
C42: Q1 2025 | D42: Q2 2025 | E42: Q3 2025
B43: Stock | C43: ='Dynamic Asset Allocation'!L119 -> 151886.72 | D43: ='Dynamic Asset Allocation'!N119 -> 0 | E43: ='Dynamic Asset Allocation'!P119 -> 0
B44: Risk Free Asset | C44: ='Dynamic Asset Allocation'!L120 -> 1017458.1 | D44: ='Dynamic Asset Allocation'!N120 -> 1181856.4 | E44: ='Dynamic Asset Allocation'!P120 -> 1216500.6
B45: Total | C45: =C43+C44 -> 1169344.8 | D45: =D43+D44 -> 1181856.4 | E45: =E43+E44 -> 1216500.6
B46: ROI | C46: =(C45-C5)/C5 -> 0.16934483 | D46: =(D45-C45)/C45 -> 0.010699659 | E46: =(E45-D45)/D45 -> 0.029313375
B47: Changes in ROI | D47: =D46-C46 -> -0.15864518 | E47: =E46-D46 -> 0.018613716

Sheet 100% Equity Investments
B2: 1. 100% Equity Investments without Rebalancing
B5: Quarter | D5: Q4 2024 | G5: Q1 2025 | I5: Q2 2025 | K5: Q3 2025
B6: Initial Equity Investments in BDT (100%) | F6: ='100% Equity Portfolio'!C9 -> 1000000 | H6: =H16 -> 967866.8 | J6: =J16 -> 901391.43 | L6: =L16 -> 1001801.5
B7: Firm | C7: Weight | D7: Fund Allocation (BDT) | E7: Closing Price (BDT) | F7: Number of Shares | G7: Closing Price (BDT) | H7: Equity Value (BDT) | I7: Closing Price (BDT) | J7: Equity Value (BDT) | K7: Closing Price (BDT) | L7: Equity Value (BDT)
B8: ='100% Equity and DAA'!B11 -> UCB | C8: =1/8 -> 0.125 | D8: =$F$6*C8 -> 125000 | E8: ='100% Equity and DAA'!D11 -> 9.2 | F8: =D8/E8 -> 13586.957 | G8: ='100% Equity and DAA'!C23 -> 11 | H8: =G8*F8 -> 149456.52 | I8: ='100% Equity and DAA'!E23 -> 9.9 | J8: =I8*F8 -> 134510.87 | K8: ='100% Equity and DAA'!G23 -> 10.6 | L8: =K8*F8 -> 144021.74
B9: ='100% Equity and DAA'!B12 -> IDLC | C9: =1/8 -> 0.125 | D9: =$F$6*C9 -> 125000 | E9: ='100% Equity and DAA'!D12 -> 32.7 | F9: =D9/E9 -> 3822.63 | G9: ='100% Equity and DAA'!C24 -> 31.4 | H9: =G9*F9 -> 120030.58 | I9: ='100% Equity and DAA'!E24 -> 29 | J9: =I9*F9 -> 110856.27 | K9: ='100% Equity and DAA'!G24 -> 41.2 | L9: =K9*F9 -> 157492.35
B10: ='100% Equity and DAA'!B13 -> GP | C10: =1/8 -> 0.125 | D10: =$F$6*C10 -> 125000 | E10: ='100% Equity and DAA'!D13 -> 323.1 | F10: =D10/E10 -> 386.87713 | G10: ='100% Equity and DAA'!C25 -> 321.9 | H10: =G10*F10 -> 124535.75 | I10: ='100% Equity and DAA'!E25 -> 303.1 | J10: =I10*F10 -> 117262.46 | K10: ='100% Equity and DAA'!G25 -> 299 | L10: =K10*F10 -> 115676.26
B11: ='100% Equity and DAA'!B14 -> BATASHOE | C11: =1/8 -> 0.125 | D11: =$F$6*C11 -> 125000 | E11: ='100% Equity and DAA'!D14 -> 905.4 | F11: =D11/E11 -> 138.06053 | G11: ='100% Equity and DAA'!C26 -> 834.7 | H11: =G11*F11 -> 115239.12 | I11: ='100% Equity and DAA'!E26 -> 802.7 | J11: =I11*F11 -> 110821.18 | K11: ='100% Equity and DAA'!G26 -> 877.7 | L11: =K11*F11 -> 121175.72
B12: ='100% Equity and DAA'!B15 -> RENATA | C12: =1/8 -> 0.125 | D12: =$F$6*C12 -> 125000 | E12: ='100% Equity and DAA'!D15 -> 635.1 | F12: =D12/E12 -> 196.8194 | G12: ='100% Equity and DAA'!C27 -> 500.5 | H12: =G12*F12 -> 98508.109 | I12: ='100% Equity and DAA'!E27 -> 488.4 | J12: =I12*F12 -> 96126.594 | K12: ='100% Equity and DAA'!G27 -> 480.4 | L12: =K12*F12 -> 94552.039
B13: ='100% Equity and DAA'!B16 -> WALTONHIL | C13: =1/8 -> 0.125 | D13: =$F$6*C13 -> 125000 | E13: ='100% Equity and DAA'!D16 -> 487.5 | F13: =D13/E13 -> 256.41026 | G13: ='100% Equity and DAA'!C28 -> 462.7 | H13: =G13*F13 -> 118641.03 | I13: ='100% Equity and DAA'!E28 -> 406.3 | J13: =I13*F13 -> 104179.49 | K13: ='100% Equity and DAA'!G28 -> 419.9 | L13: =K13*F13 -> 107666.67
B14: ='100% Equity and DAA'!B17 -> RAKC | C14: =1/8 -> 0.125 | D14: =$F$6*C14 -> 125000 | E14: ='100% Equity and DAA'!D17 -> 22.6 | F14: =D14/E14 -> 5530.9735 | G14: ='100% Equity and DAA'!C29 -> 22.6 | H14: =G14*F14 -> 125000 | I14: ='100% Equity and DAA'!E29 -> 19.2 | J14: =I14*F14 -> 106194.69 | K14: ='100% Equity and DAA'!G29 -> 25.1 | L14: =K14*F14 -> 138827.43
B15: ='100% Equity and DAA'!B18 -> OLYMPIC | C15: =1/8 -> 0.125 | D15: =$F$6*C15 -> 125000 | E15: ='100% Equity and DAA'!D18 -> 158 | F15: =D15/E15 -> 791.13924 | G15: ='100% Equity and DAA'!C30 -> 147.2 | H15: =G15*F15 -> 116455.7 | I15: ='100% Equity and DAA'!E30 -> 153.5 | J15: =I15*F15 -> 121439.87 | K15: ='100% Equity and DAA'!G30 -> 154.7 | L15: =K15*F15 -> 122389.24
B16: Total Equity Value | D16: =SUM(D8:D15) -> 1000000 | H16: =SUM(H8:H15) -> 967866.8 | J16: =SUM(J8:J15) -> 901391.43 | L16: =SUM(L8:L15) -> 1001801.5
B19: 100% Equity Investments without Rebalancing
B20: Particulars | C20: Q04 2024 | D20: Q01 2025 | E20: Q02 2025 | F20: Q03 2025
B21: Equity Value (BDT) | C21: =D16 -> 1000000 | D21: =H16 -> 967866.8 | E21: =J16 -> 901391.43 | F21: =L16 -> 1001801.5
B22: T-Bill Value (BDT) | C22: 0 | D22: 0 | E22: 0 | F22: 0
B23: Total Value (BDT) | C23: =SUM(C21:C22) -> 1000000 | D23: =SUM(D21:D22) -> 967866.8 | E23: =SUM(E21:E22) -> 901391.43 | F23: =SUM(F21:F22) -> 1001801.5
B24: Quarter to Quarter Return | D24: =LN(D23/C23)*4 -> -0.13064321 | E24: =LN(E23/D23)*4 -> -0.28461952 | F24: =LN(F23/E23)*4 -> 0.42246208
B25: Change in Quarter to Quarter Return | E25: =E24-D24 -> -0.15397631 | F25: =F24-E24 -> 0.70708159
B30: 2. 100% Equity Investments with Rebalancing
B33: Quarter | D33: Q04 2024 | G33: Q01 2025 | L33: Q02 2025 | Q33: Q03 2025
B34: Initial Equity Investments in BDT (100%) | F34: =F6 -> 1000000 | K34: =I44 -> 967866.8 | P34: =N44 -> 904122.36 | S34: =S44 -> 1006232.4
B35: Firm | C35: Weight | D35: Fund Allocation (BDT) | E35: Closing Price (BDT) | F35: Number of Shares | G35: Opening Number of Shares | H35: Closing Price (BDT) | I35: Equity Value (BDT) | J35: Fund Allocation (BDT) | K35: Closing Number of Shares | L35: Opening Number of Shares | M35: Closing Price (BDT) | N35: Equity Value (BDT) | O35: Fund Allocation (BDT) | P35: Closing Number of Shares | Q35: Opening Number of Shares | R35: Closing Price (BDT) | S35: Equity Value (BDT)
B36: =B8 -> UCB | C36: =1/8 -> 0.125 | D36: =$F$34*C36 -> 125000 | E36: ='100% Equity and DAA'!D11 -> 9.2 | F36: =D36/E36 -> 13586.957 | G36: =F36 -> 13586.957 | H36: ='100% Equity and DAA'!C23 -> 11 | I36: =H36*G36 -> 149456.52 | J36: =$K$34*C36 -> 120983.35 | K36: =J36/H36 -> 10998.486 | L36: =K36 -> 10998.486 | M36: ='100% Equity and DAA'!E23 -> 9.9 | N36: =L36*M36 -> 108885.02 | O36: =$P$34*C36 -> 113015.29 | P36: =O36/M36 -> 11415.686 | Q36: =P36 -> 11415.686 | R36: ='100% Equity and DAA'!G23 -> 10.6 | S36: =R36*Q36 -> 121006.27
B37: =B9 -> IDLC | C37: =1/8 -> 0.125 | D37: =$F$34*C37 -> 125000 | E37: ='100% Equity and DAA'!D12 -> 32.7 | F37: =D37/E37 -> 3822.63 | G37: =F37 -> 3822.63 | H37: ='100% Equity and DAA'!C24 -> 31.4 | I37: =H37*G37 -> 120030.58 | J37: =$K$34*C37 -> 120983.35 | K37: =J37/H37 -> 3852.9729 | L37: =K37 -> 3852.9729 | M37: ='100% Equity and DAA'!E24 -> 29 | N37: =L37*M37 -> 111736.22 | O37: =$P$34*C37 -> 113015.29 | P37: =O37/M37 -> 3897.0791 | Q37: =P37 -> 3897.0791 | R37: ='100% Equity and DAA'!G24 -> 41.2 | S37: =R37*Q37 -> 160559.66
B38: =B10 -> GP | C38: =1/8 -> 0.125 | D38: =$F$34*C38 -> 125000 | E38: ='100% Equity and DAA'!D13 -> 323.1 | F38: =D38/E38 -> 386.87713 | G38: =F38 -> 386.87713 | H38: ='100% Equity and DAA'!C25 -> 321.9 | I38: =H38*G38 -> 124535.75 | J38: =$K$34*C38 -> 120983.35 | K38: =J38/H38 -> 375.84141 | L38: =K38 -> 375.84141 | M38: ='100% Equity and DAA'!E25 -> 303.1 | N38: =L38*M38 -> 113917.53 | O38: =$P$34*C38 -> 113015.29 | P38: =O38/M38 -> 372.86471 | Q38: =P38 -> 372.86471 | R38: ='100% Equity and DAA'!G25 -> 299 | S38: =R38*Q38 -> 111486.55
B39: =B11 -> BATASHOE | C39: =1/8 -> 0.125 | D39: =$F$34*C39 -> 125000 | E39: ='100% Equity and DAA'!D14 -> 905.4 | F39: =D39/E39 -> 138.06053 | G39: =F39 -> 138.06053 | H39: ='100% Equity and DAA'!C26 -> 834.7 | I39: =H39*G39 -> 115239.12 | J39: =$K$34*C39 -> 120983.35 | K39: =J39/H39 -> 144.94231 | L39: =K39 -> 144.94231 | M39: ='100% Equity and DAA'!E26 -> 802.7 | N39: =L39*M39 -> 116345.2 | O39: =$P$34*C39 -> 113015.29 | P39: =O39/M39 -> 140.79394 | Q39: =P39 -> 140.79394 | R39: ='100% Equity and DAA'!G26 -> 877.7 | S39: =R39*Q39 -> 123574.84
B40: =B12 -> RENATA | C40: =1/8 -> 0.125 | D40: =$F$34*C40 -> 125000 | E40: ='100% Equity and DAA'!D15 -> 635.1 | F40: =D40/E40 -> 196.8194 | G40: =F40 -> 196.8194 | H40: ='100% Equity and DAA'!C27 -> 500.5 | I40: =H40*G40 -> 98508.109 | J40: =$K$34*C40 -> 120983.35 | K40: =J40/H40 -> 241.72498 | L40: =K40 -> 241.72498 | M40: ='100% Equity and DAA'!E27 -> 488.4 | N40: =L40*M40 -> 118058.48 | O40: =$P$34*C40 -> 113015.29 | P40: =O40/M40 -> 231.39905 | Q40: =P40 -> 231.39905 | R40: ='100% Equity and DAA'!G27 -> 480.4 | S40: =R40*Q40 -> 111164.1
B41: =B13 -> WALTONHIL | C41: =1/8 -> 0.125 | D41: =$F$34*C41 -> 125000 | E41: ='100% Equity and DAA'!D16 -> 487.5 | F41: =D41/E41 -> 256.41026 | G41: =F41 -> 256.41026 | H41: ='100% Equity and DAA'!C28 -> 462.7 | I41: =H41*G41 -> 118641.03 | J41: =$K$34*C41 -> 120983.35 | K41: =J41/H41 -> 261.47255 | L41: =K41 -> 261.47255 | M41: ='100% Equity and DAA'!E28 -> 406.3 | N41: =L41*M41 -> 106236.3 | O41: =$P$34*C41 -> 113015.29 | P41: =O41/M41 -> 278.15726 | Q41: =P41 -> 278.15726 | R41: ='100% Equity and DAA'!G28 -> 419.9 | S41: =R41*Q41 -> 116798.23
B42: =B14 -> RAKC | C42: =1/8 -> 0.125 | D42: =$F$34*C42 -> 125000 | E42: ='100% Equity and DAA'!D17 -> 22.6 | F42: =D42/E42 -> 5530.9735 | G42: =F42 -> 5530.9735 | H42: ='100% Equity and DAA'!C29 -> 22.6 | I42: =H42*G42 -> 125000 | J42: =$K$34*C42 -> 120983.35 | K42: =J42/H42 -> 5353.2456 | L42: =K42 -> 5353.2456 | M42: ='100% Equity and DAA'!E29 -> 19.2 | N42: =L42*M42 -> 102782.32 | O42: =$P$34*C42 -> 113015.29 | P42: =O42/M42 -> 5886.2133 | Q42: =P42 -> 5886.2133 | R42: ='100% Equity and DAA'!G29 -> 25.1 | S42: =R42*Q42 -> 147743.95
B43: =B15 -> OLYMPIC | C43: =1/8 -> 0.125 | D43: =$F$34*C43 -> 125000 | E43: ='100% Equity and DAA'!D18 -> 158 | F43: =D43/E43 -> 791.13924 | G43: =F43 -> 791.13924 | H43: ='100% Equity and DAA'!C30 -> 147.2 | I43: =H43*G43 -> 116455.7 | J43: =$K$34*C43 -> 120983.35 | K43: =J43/H43 -> 821.89776 | L43: =K43 -> 821.89776 | M43: ='100% Equity and DAA'!E30 -> 153.5 | N43: =L43*M43 -> 126161.31 | O43: =$P$34*C43 -> 113015.29 | P43: =O43/M43 -> 736.25599 | Q43: =P43 -> 736.25599 | R43: ='100% Equity and DAA'!G30 -> 154.7 | S43: =R43*Q43 -> 113898.8
B44: Total Equity Value | D44: =SUM(D36:D43) -> 1000000 | I44: =SUM(I36:I43) -> 967866.8 | J44: =SUM(J36:J43) -> 967866.8 | N44: =SUM(N36:N43) -> 904122.36 | O44: =SUM(O36:O43) -> 904122.36 | S44: =SUM(S36:S43) -> 1006232.4
B47: 100% Equity Investments with Rebalancing
B48: Particulars | C48: Q04 2024 | D48: Q01 2025 | E48: Q02 2025 | F48: Q03 2025
B49: Equity Value (BDT) | C49: =D44 -> 1000000 | D49: =I44 -> 967866.8 | E49: =N44 -> 904122.36 | F49: =S44 -> 1006232.4
B50: T-Bill Value (BDT) | C50: 0 | D50: 0 | E50: 0 | F50: 0
B51: Total Value (BDT) | C51: =SUM(C49:C50) -> 1000000 | D51: =SUM(D49:D50) -> 967866.8 | E51: =SUM(E49:E50) -> 904122.36 | F51: =SUM(F49:F50) -> 1006232.4
B52: Quarter to Quarter Return | D52: =LN(D51/C51)*4 -> -0.13064321 | E52: =LN(E51/D51)*4 -> -0.2725191 | F52: =LN(F51/E51)*4 -> 0.4280146
B53: Change in Quarter to Quarter Return | E53: =E52-D52 -> -0.14187589 | F53: =F52-E52 -> 0.70053371

Sheet Actual Path and Others
B2: Dynamic Equity Portfolio with Expected Price of Actual Route
B5: Quarter | D5: Q4 2024 | G5: Q1 2025 | L5: Q2 2025 | Q5: Q3 2025
B6: Investments in BDT (100%) | F6: ='100% Equity and DAA'!C5 -> 1000000 | K6: ='100% Equity Portfolio'!D38 -> 893001.52 | P6: ='100% Equity Portfolio'!F42 -> 805025.57
B7: Delta | F7: ='Delta 1'!D32 -> 0.56890131 | K7: ='Delta 1'!F43 -> 0.17008563 | P7: ='Delta 1'!H47 -> 0
B8: Firm | C8: Weight | D8: Fund Allocation (BDT) | E8: Closing Price (BDT) | F8: Number of Shares | G8: Opening Number of Shares | H8: Closing Price (BDT) | I8: Equity Value (BDT) | J8: Fund Allocation (BDT) | K8: Closing Number of Shares | L8: Opening Number of Shares | M8: Closing Price (BDT) | N8: Equity Value (BDT) | O8: Fund Allocation (BDT) | P8: Closing Number of Shares | Q8: Opening Number of Shares | R8: Closing Price (BDT) | S8: Equity Value (BDT)
B9: ='100% Equity Investments'!B8 -> UCB | C9: =1/8 -> 0.125 | D9: =$F$6*$F$7*C9 -> 71112.664 | E9: ='100% Equity and DAA'!D11 -> 9.2 | F9: =D9/E9 -> 7729.6374 | G9: =F9 -> 7729.6374 | H9: ='100% Equity and DAA'!C23 -> 11 | I9: =H9*G9 -> 85026.011 | J9: =$K$6*$K$7*C9 -> 18985.841 | K9: =J9/H9 -> 1725.9855 | L9: =K9 -> 1725.9855 | M9: ='100% Equity and DAA'!E23 -> 9.9 | N9: =L9*M9 -> 17087.257 | O9: =$P$6*$P$7*C9 -> 0 | P9: =O9/M9 -> 0 | Q9: =P9 -> 0 | R9: ='100% Equity and DAA'!G23 -> 10.6 | S9: =Q9*R9 -> 0
B10: ='100% Equity Investments'!B9 -> IDLC | C10: =1/8 -> 0.125 | D10: =$F$6*$F$7*C10 -> 71112.664 | E10: ='100% Equity and DAA'!D12 -> 32.7 | F10: =D10/E10 -> 2174.6992 | G10: =F10 -> 2174.6992 | H10: ='100% Equity and DAA'!C24 -> 31.4 | I10: =H10*G10 -> 68285.555 | J10: =$K$6*$K$7*C10 -> 18985.841 | K10: =J10/H10 -> 604.64461 | L10: =K10 -> 604.64461 | M10: ='100% Equity and DAA'!E24 -> 29 | N10: =L10*M10 -> 17534.694 | O10: =$P$6*$P$7*C10 -> 0 | P10: =O10/M10 -> 0 | Q10: =P10 -> 0 | R10: ='100% Equity and DAA'!G24 -> 41.2 | S10: =Q10*R10 -> 0
B11: ='100% Equity Investments'!B10 -> GP | C11: =1/8 -> 0.125 | D11: =$F$6*$F$7*C11 -> 71112.664 | E11: ='100% Equity and DAA'!D13 -> 323.1 | F11: =D11/E11 -> 220.09491 | G11: =F11 -> 220.09491 | H11: ='100% Equity and DAA'!C25 -> 321.9 | I11: =H11*G11 -> 70848.55 | J11: =$K$6*$K$7*C11 -> 18985.841 | K11: =J11/H11 -> 58.980555 | L11: =K11 -> 58.980555 | M11: ='100% Equity and DAA'!E25 -> 303.1 | N11: =L11*M11 -> 17877.006 | O11: =$P$6*$P$7*C11 -> 0 | P11: =O11/M11 -> 0 | Q11: =P11 -> 0 | R11: ='100% Equity and DAA'!G25 -> 299 | S11: =Q11*R11 -> 0
B12: ='100% Equity Investments'!B11 -> BATASHOE | C12: =1/8 -> 0.125 | D12: =$F$6*$F$7*C12 -> 71112.664 | E12: ='100% Equity and DAA'!D14 -> 905.4 | F12: =D12/E12 -> 78.542814 | G12: =F12 -> 78.542814 | H12: ='100% Equity and DAA'!C26 -> 834.7 | I12: =H12*G12 -> 65559.687 | J12: =$K$6*$K$7*C12 -> 18985.841 | K12: =J12/H12 -> 22.745706 | L12: =K12 -> 22.745706 | M12: ='100% Equity and DAA'!E26 -> 802.7 | N12: =L12*M12 -> 18257.978 | O12: =$P$6*$P$7*C12 -> 0 | P12: =O12/M12 -> 0 | Q12: =P12 -> 0 | R12: ='100% Equity and DAA'!G26 -> 877.7 | S12: =Q12*R12 -> 0
B13: ='100% Equity Investments'!B12 -> RENATA | C13: =1/8 -> 0.125 | D13: =$F$6*$F$7*C13 -> 71112.664 | E13: ='100% Equity and DAA'!D15 -> 635.1 | F13: =D13/E13 -> 111.97081 | G13: =F13 -> 111.97081 | H13: ='100% Equity and DAA'!C27 -> 500.5 | I13: =H13*G13 -> 56041.392 | J13: =$K$6*$K$7*C13 -> 18985.841 | K13: =J13/H13 -> 37.933747 | L13: =K13 -> 37.933747 | M13: ='100% Equity and DAA'!E27 -> 488.4 | N13: =L13*M13 -> 18526.842 | O13: =$P$6*$P$7*C13 -> 0 | P13: =O13/M13 -> 0 | Q13: =P13 -> 0 | R13: ='100% Equity and DAA'!G27 -> 480.4 | S13: =Q13*R13 -> 0
B14: ='100% Equity Investments'!B13 -> WALTONHIL | C14: =1/8 -> 0.125 | D14: =$F$6*$F$7*C14 -> 71112.664 | E14: ='100% Equity and DAA'!D16 -> 487.5 | F14: =D14/E14 -> 145.87213 | G14: =F14 -> 145.87213 | H14: ='100% Equity and DAA'!C28 -> 462.7 | I14: =H14*G14 -> 67495.035 | J14: =$K$6*$K$7*C14 -> 18985.841 | K14: =J14/H14 -> 41.032722 | L14: =K14 -> 41.032722 | M14: ='100% Equity and DAA'!E28 -> 406.3 | N14: =L14*M14 -> 16671.595 | O14: =$P$6*$P$7*C14 -> 0 | P14: =O14/M14 -> 0 | Q14: =P14 -> 0 | R14: ='100% Equity and DAA'!G28 -> 419.9 | S14: =Q14*R14 -> 0
B15: ='100% Equity Investments'!B14 -> RAKC | C15: =1/8 -> 0.125 | D15: =$F$6*$F$7*C15 -> 71112.664 | E15: ='100% Equity and DAA'!D17 -> 22.6 | F15: =D15/E15 -> 3146.578 | G15: =F15 -> 3146.578 | H15: ='100% Equity and DAA'!C29 -> 22.6 | I15: =H15*G15 -> 71112.664 | J15: =$K$6*$K$7*C15 -> 18985.841 | K15: =J15/H15 -> 840.08144 | L15: =K15 -> 840.08144 | M15: ='100% Equity and DAA'!E29 -> 19.2 | N15: =L15*M15 -> 16129.564 | O15: =$P$6*$P$7*C15 -> 0 | P15: =O15/M15 -> 0 | Q15: =P15 -> 0 | R15: ='100% Equity and DAA'!G29 -> 25.1 | S15: =Q15*R15 -> 0
B16: ='100% Equity Investments'!B15 -> OLYMPIC | C16: =1/8 -> 0.125 | D16: =$F$6*$F$7*C16 -> 71112.664 | E16: ='100% Equity and DAA'!D18 -> 158 | F16: =D16/E16 -> 450.08015 | G16: =F16 -> 450.08015 | H16: ='100% Equity and DAA'!C30 -> 147.2 | I16: =H16*G16 -> 66251.798 | J16: =$K$6*$K$7*C16 -> 18985.841 | K16: =J16/H16 -> 128.9799 | L16: =K16 -> 128.9799 | M16: ='100% Equity and DAA'!E30 -> 153.5 | N16: =L16*M16 -> 19798.414 | O16: =$P$6*$P$7*C16 -> 0 | P16: =O16/M16 -> 0 | Q16: =P16 -> 0 | R16: ='100% Equity and DAA'!G30 -> 154.7 | S16: =Q16*R16 -> 0
B17: Total Equity Value | D17: =SUM(D9:D16) -> 568901.31 | I17: =SUM(I9:I16) -> 550620.69 | J17: =SUM(J9:J16) -> 151886.72 | N17: =SUM(N9:N16) -> 141883.35 | O17: =SUM(O9:O16) -> 0 | S17: =SUM(S9:S16) -> 0
B20: Particulars | C20: Q1 2025 | D20: Q2 2025 | E20: Q3 2025 | H20: Actual Route of Insured Portfolio
B21: Initial Investments (BDT) | C21: =F6 -> 1000000 | D21: =K6 -> 893001.52 | E21: =P6 -> 805025.57 | H21: Quarter | I21: Q1 2025 | K21: Q2 2025 | M21: Q3 2025
B22: Delta | C22: =F7 -> 0.56890131 | D22: =K7 -> 0.17008563 | E22: =P7 -> 0
B23: Initial Equity Investments (BDT) | C23: =D17 -> 568901.31 | D23: =J17 -> 151886.72 | E23: =O17 -> 0 | N23: ='Insured Portfolio'!I6 -> 1383617
B24: Equity Value at the Quarter End (BDT) | C24: =I17 -> 550620.69 | D24: =N17 -> 141883.35 | E24: =S17 -> 0
B25: Actual Change | C25: Down | D25: Down | E25: Down | L25: ='Insured Portfolio'!G8 -> 1242196.6
N27: ='Insured Portfolio'!I10 -> 1115230.8
J29: ='Insured Portfolio'!E12 -> 1140875.8
N31: ='Insured Portfolio'!I14 -> 1124425.9
L33: ='Insured Portfolio'!G16 -> 1064113.6
N35: ='Insured Portfolio'!I18 -> 1050000
H37: ='Insured Portfolio'!C19 -> 1058463.6
N39: ='Insured Portfolio'!I22 -> 1103367.7
L41: ='Insured Portfolio'!G24 -> 1051659.6
N43: ='Insured Portfolio'!I26 -> 1050000
J45: ='Insured Portfolio'!E28 -> 1011839.1
N47: ='Insured Portfolio'!I30 -> 1050000
J49: Floor Price | L49: ='Insured Portfolio'!G32 -> 1020097.5
N51: ='Insured Portfolio'!I34 -> 1050000
B55: 2. Dynamic Asset Portfolio with Actual Price
B58: Particulars | D58: Q1 2025 | E58: Q2 2025 | F58: Q3 2025
B59: Continuously Compounding Quarterly Risk-Free Rate | D59: ='91Day T-Bill'!F24 -> 0.028686316 | E59: ='91Day T-Bill'!G24 -> 0.02664544 | F59: ='91Day T-Bill'!H24 -> 0.028891954
B62: Quarter | D62: Q4 2024 | G62: Q1 2025 | L62: Q2 2025 | Q62: Q3 2025
B63: Portfolio Value (BDT) | F63: =H37 -> 1058463.6 | K63: =I75+I76 -> 1054430.1 | P63: =N75+N76 -> 1067616.1 | S63: =S75+S76 -> 1098911.6
B64: 100% Equity Investments with Rebalancing (BDT) | F64: =F6 -> 1000000 | K64: ='100% Equity Investments'!H6 -> 967866.8 | P64: ='100% Equity Investments'!J6 -> 901391.43 | S64: ='100% Equity Investments'!L6 -> 1001801.5
B65: Delta | F65: =F7 -> 0.56890131 | K65: =K7 -> 0.17008563 | P65: =P7 -> 0
B66: Firm | C66: Weight | D66: Fund Allocation (BDT) | E66: Closing Price (BDT) | F66: Number of Shares | G66: Opening Number of Shares | H66: Closing Price (BDT) | I66: Equity Value (BDT) | J66: Fund Allocation (BDT) | K66: Closing Number of Shares | L66: Opening Number of Shares | M66: Closing Price (BDT) | N66: Equity Value (BDT) | O66: Fund Allocation (BDT) | P66: Closing Number of Shares | Q66: Opening Number of Shares | R66: Closing Price (BDT) | S66: Equity Value (BDT)
B67: =B9 -> UCB | C67: =1/8 -> 0.125 | D67: =$F$64*$F$65*C67 -> 71112.664 | E67: =E9 -> 9.2 | F67: =D67/E67 -> 7729.6374 | G67: =F67 -> 7729.6374 | H67: =H9 -> 11 | I67: =H67*G67 -> 85026.011 | J67: =$K$64*$K$65*C67 -> 20577.529 | K67: =J67/H67 -> 1870.6845 | L67: =K67 -> 1870.6845 | M67: =M9 -> 9.9 | N67: =L67*M67 -> 18519.776 | O67: =$P$64*$P$65*C67 -> 0 | P67: =O67/M67 -> 0 | Q67: =P67 -> 0 | R67: =R9 -> 10.6 | S67: =R67*Q67 -> 0
B68: =B10 -> IDLC | C68: =1/8 -> 0.125 | D68: =$F$64*$F$65*C68 -> 71112.664 | E68: =E10 -> 32.7 | F68: =D68/E68 -> 2174.6992 | G68: =F68 -> 2174.6992 | H68: =H10 -> 31.4 | I68: =H68*G68 -> 68285.555 | J68: =$K$64*$K$65*C68 -> 20577.529 | K68: =J68/H68 -> 655.33532 | L68: =K68 -> 655.33532 | M68: =M10 -> 29 | N68: =L68*M68 -> 19004.724 | O68: =$P$64*$P$65*C68 -> 0 | P68: =O68/M68 -> 0 | Q68: =P68 -> 0 | R68: =R10 -> 41.2 | S68: =R68*Q68 -> 0
B69: =B11 -> GP | C69: =1/8 -> 0.125 | D69: =$F$64*$F$65*C69 -> 71112.664 | E69: =E11 -> 323.1 | F69: =D69/E69 -> 220.09491 | G69: =F69 -> 220.09491 | H69: =H11 -> 321.9 | I69: =H69*G69 -> 70848.55 | J69: =$K$64*$K$65*C69 -> 20577.529 | K69: =J69/H69 -> 63.925223 | L69: =K69 -> 63.925223 | M69: =M11 -> 303.1 | N69: =L69*M69 -> 19375.735 | O69: =$P$64*$P$65*C69 -> 0 | P69: =O69/M69 -> 0 | Q69: =P69 -> 0 | R69: =R11 -> 299 | S69: =R69*Q69 -> 0
B70: =B12 -> BATASHOE | C70: =1/8 -> 0.125 | D70: =$F$64*$F$65*C70 -> 71112.664 | E70: =E12 -> 905.4 | F70: =D70/E70 -> 78.542814 | G70: =F70 -> 78.542814 | H70: =H12 -> 834.7 | I70: =H70*G70 -> 65559.687 | J70: =$K$64*$K$65*C70 -> 20577.529 | K70: =J70/H70 -> 24.652605 | L70: =K70 -> 24.652605 | M70: =M12 -> 802.7 | N70: =L70*M70 -> 19788.646 | O70: =$P$64*$P$65*C70 -> 0 | P70: =O70/M70 -> 0 | Q70: =P70 -> 0 | R70: =R12 -> 877.7 | S70: =R70*Q70 -> 0
B71: =B13 -> RENATA | C71: =1/8 -> 0.125 | D71: =$F$64*$F$65*C71 -> 71112.664 | E71: =E13 -> 635.1 | F71: =D71/E71 -> 111.97081 | G71: =F71 -> 111.97081 | H71: =H13 -> 500.5 | I71: =H71*G71 -> 56041.392 | J71: =$K$64*$K$65*C71 -> 20577.529 | K71: =J71/H71 -> 41.113944 | L71: =K71 -> 41.113944 | M71: =M13 -> 488.4 | N71: =L71*M71 -> 20080.05 | O71: =$P$64*$P$65*C71 -> 0 | P71: =O71/M71 -> 0 | Q71: =P71 -> 0 | R71: =R13 -> 480.4 | S71: =R71*Q71 -> 0
B72: =B14 -> WALTONHIL | C72: =1/8 -> 0.125 | D72: =$F$64*$F$65*C72 -> 71112.664 | E72: =E14 -> 487.5 | F72: =D72/E72 -> 145.87213 | G72: =F72 -> 145.87213 | H72: =H14 -> 462.7 | I72: =H72*G72 -> 67495.035 | J72: =$K$64*$K$65*C72 -> 20577.529 | K72: =J72/H72 -> 44.472723 | L72: =K72 -> 44.472723 | M72: =M14 -> 406.3 | N72: =L72*M72 -> 18069.268 | O72: =$P$64*$P$65*C72 -> 0 | P72: =O72/M72 -> 0 | Q72: =P72 -> 0 | R72: =R14 -> 419.9 | S72: =R72*Q72 -> 0
B73: =B15 -> RAKC | C73: =1/8 -> 0.125 | D73: =$F$64*$F$65*C73 -> 71112.664 | E73: =E15 -> 22.6 | F73: =D73/E73 -> 3146.578 | G73: =F73 -> 3146.578 | H73: =H15 -> 22.6 | I73: =H73*G73 -> 71112.664 | J73: =$K$64*$K$65*C73 -> 20577.529 | K73: =J73/H73 -> 910.51014 | L73: =K73 -> 910.51014 | M73: =M15 -> 19.2 | N73: =L73*M73 -> 17481.795 | O73: =$P$64*$P$65*C73 -> 0 | P73: =O73/M73 -> 0 | Q73: =P73 -> 0 | R73: =R15 -> 25.1 | S73: =R73*Q73 -> 0
B74: =B16 -> OLYMPIC | C74: =1/8 -> 0.125 | D74: =$F$64*$F$65*C74 -> 71112.664 | E74: =E16 -> 158 | F74: =D74/E74 -> 450.08015 | G74: =F74 -> 450.08015 | H74: =H16 -> 147.2 | I74: =H74*G74 -> 66251.798 | J74: =$K$64*$K$65*C74 -> 20577.529 | K74: =J74/H74 -> 139.793 | L74: =K74 -> 139.793 | M74: =M16 -> 153.5 | N74: =L74*M74 -> 21458.225 | O74: =$P$64*$P$65*C74 -> 0 | P74: =O74/M74 -> 0 | Q74: =P74 -> 0 | R74: =R16 -> 154.7 | S74: =R74*Q74 -> 0
B75: Total Equity Value | D75: =SUM(D67:D74) -> 568901.31 | I75: =SUM(I67:I74) -> 550620.69 | J75: =SUM(J67:J74) -> 164620.23 | N75: =SUM(N67:N74) -> 153778.22 | O75: =SUM(O67:O74) -> 0 | S75: =SUM(S67:S74) -> 0
B76: T-Bill Investments | D76: =F63-D75 -> 489562.28 | I76: =D76*EXP(D59) -> 503809.39 | J76: =K63-J75 -> 889809.85 | N76: =J76*EXP(E59) -> 913837.93 | O76: =P63-O75 -> 1067616.1 | S76: =O76*EXP(F59) -> 1098911.6
I79: Firm | J79: Q4 2024 | K79: Q1 2025 | M79: Q2 2025
J80: Number of Shares | K80: Closing Number of Shares | L80: Action | M80: Closing Number of Shares | N80: Action
B81: Particulars | C81: Q4 2024 | D81: Q1 2025 | E81: Q2 2025 | F81: Q3 2025 | I81: UCBL | J81: =F67 -> 7729.6374 | K81: =K67 -> 1870.6845 | L81: =J81-K81 -> 5858.9529 | M81: =P67 -> 0 | N81: =K81-M81 -> 1870.6845
B82: Dynamic Equity Portfolio (BDT) | C82: =D75 -> 568901.31 | D82: =I75 -> 550620.69 | E82: =N75 -> 153778.22 | F82: =S75 -> 0 | I82: IDLC | J82: =F68 -> 2174.6992 | K82: =K68 -> 655.33532 | L82: =J82-K82 -> 1519.3639 | M82: =P68 -> 0 | N82: =K82-M82 -> 655.33532
B83: Dynamic T-Bill Portfolio (BDT) | C83: =D76 -> 489562.28 | D83: =I76 -> 503809.39 | E83: =N76 -> 913837.93 | F83: =S76 -> 1098911.6 | I83: GP | J83: =F69 -> 220.09491 | K83: =K69 -> 63.925223 | L83: =J83-K83 -> 156.16968 | M83: =P69 -> 0 | N83: =K83-M83 -> 63.925223
B84: Portfolio Value (Dynamic Asset Portfolio with Actual Price) | C84: =SUM(C82:C83) -> 1058463.6 | D84: =SUM(D82:D83) -> 1054430.1 | E84: =SUM(E82:E83) -> 1067616.1 | F84: =SUM(F82:F83) -> 1098911.6 | I84: BATA | J84: =F70 -> 78.542814 | K84: =K70 -> 24.652605 | L84: =J84-K84 -> 53.890209 | M84: =P70 -> 0 | N84: =K84-M84 -> 24.652605
B85: Quarter to Quarter Return | D85: =LN(D84/C84)*4 -> -0.015271998 | E85: =LN(E84/D84)*4 -> 0.049711372 | F85: =LN(F84/E84)*4 -> 0.11556781 | I85: RNTL | J85: =F71 -> 111.97081 | K85: =K71 -> 41.113944 | L85: =J85-K85 -> 70.856869 | M85: =P71 -> 0 | N85: =K85-M85 -> 41.113944
I86: WALT | J86: =F72 -> 145.87213 | K86: =K72 -> 44.472723 | L86: =J86-K86 -> 101.39941 | M86: =P72 -> 0 | N86: =K86-M86 -> 44.472723
I87: RAKC | J87: =F73 -> 3146.578 | K87: =K73 -> 910.51014 | L87: =J87-K87 -> 2236.0679 | M87: =P73 -> 0 | N87: =K87-M87 -> 910.51014
I88: OLIS | J88: =F74 -> 450.08015 | K88: =K74 -> 139.793 | L88: =J88-K88 -> 310.28715 | M88: =P74 -> 0 | N88: =K88-M88 -> 139.793
I91: Firm | J91: Q4 2024 | L91: Q1 2025 | P91: Q2 2025
J92: Action | K92: Number of Shares | L92: Fund (BDT) | M92: Action | O92: Closing Number of Shares | P92: Fund (BDT) | Q92: Action | S92: Closing Number of Shares
I93: UCBL | J93: Buy | K93: =J81 -> 7729.6374 | L93: =J67 -> 20577.529 | M93: Sell | N93: =-(L81) -> -5858.9529 | O93: =K93+N93 -> 1870.6845 | P93: =O67 -> 0 | Q93: Sell | R93: =-(N81) -> -1870.6845 | S93: =O93+R93 -> 0
I94: IDLC | J94: Buy | K94: =J82 -> 2174.6992 | L94: =J68 -> 20577.529 | M94: Sell | N94: =-(L82) -> -1519.3639 | O94: =K94+N94 -> 655.33532 | P94: =O68 -> 0 | Q94: Sell | R94: =-(N82) -> -655.33532 | S94: =O94+R94 -> 0
I95: GP | J95: Buy | K95: =J83 -> 220.09491 | L95: =J69 -> 20577.529 | M95: Sell | N95: =-(L83) -> -156.16968 | O95: =K95+N95 -> 63.925223 | P95: =O69 -> 0 | Q95: Sell | R95: =-(N83) -> -63.925223 | S95: =O95+R95 -> 0
I96: BATA | J96: Buy | K96: =J84 -> 78.542814 | L96: =J70 -> 20577.529 | M96: Sell | N96: =-(L84) -> -53.890209 | O96: =K96+N96 -> 24.652605 | P96: =O70 -> 0 | Q96: Sell | R96: =-(N84) -> -24.652605 | S96: =O96+R96 -> 0
I97: RNTL | J97: Buy | K97: =J85 -> 111.97081 | L97: =J71 -> 20577.529 | M97: Sell | N97: =-(L85) -> -70.856869 | O97: =K97+N97 -> 41.113944 | P97: =O71 -> 0 | Q97: Sell | R97: =-(N85) -> -41.113944 | S97: =O97+R97 -> 0
I98: WALT | J98: Buy | K98: =J86 -> 145.87213 | L98: =J72 -> 20577.529 | M98: Sell | N98: =-(L86) -> -101.39941 | O98: =K98+N98 -> 44.472723 | P98: =O72 -> 0 | Q98: Sell | R98: =-(N86) -> -44.472723 | S98: =O98+R98 -> 0
I99: RAKC | J99: Buy | K99: =J87 -> 3146.578 | L99: =J73 -> 20577.529 | M99: Sell | N99: =-(L87) -> -2236.0679 | O99: =K99+N99 -> 910.51014 | P99: =O73 -> 0 | Q99: Sell | R99: =-(N87) -> -910.51014 | S99: =O99+R99 -> 0
I100: OLIS | J100: Buy | K100: =J88 -> 450.08015 | L100: =J74 -> 20577.529 | M100: Sell | N100: =-(L88) -> -310.28715 | O100: =K100+N100 -> 139.793 | P100: =O74 -> 0 | Q100: Sell | R100: =-(N88) -> -139.793 | S100: =O100+R100 -> 0
B106: 3. 50% Equity and 50% Risk-Free Investments without Rebalancing
B109: Quarter | D109: Q4 2024 | G109: Q1 2025 | I109: Q2 2025 | K109: Q3 2025
B110: Initial Investments in BDT (100%) | F110: =F6 -> 1000000 | H110: =H122+H123 -> 998484.27 | J110: =J122+J123 -> 979141.31 | L110: =L122+L123 -> 1044836.8
B111: Equity Weight | F111: 0.5
B112: T-Bill Weight | F112: 0.5
B113: Firm | C113: Weight | D113: Fund Allocation (BDT) | E113: Closing Price (BDT) | F113: Number of Shares | G113: Closing Price (BDT) | H113: Equity Value (BDT) | I113: Closing Price (BDT) | J113: Equity Value (BDT) | K113: Closing Price (BDT) | L113: Equity Value (BDT)
B114: =B67 -> UCB | C114: =1/8 -> 0.125 | D114: =$F$110*$F$111*C114 -> 62500 | E114: =E9 -> 9.2 | F114: =D114/E114 -> 6793.4783 | G114: =H9 -> 11 | H114: =G114*F114 -> 74728.261 | I114: =M9 -> 9.9 | J114: =I114*F114 -> 67255.435 | K114: =R9 -> 10.6 | L114: =K114*F114 -> 72010.87
B115: =B68 -> IDLC | C115: =1/8 -> 0.125 | D115: =$F$110*$F$111*C115 -> 62500 | E115: =E10 -> 32.7 | F115: =D115/E115 -> 1911.315 | G115: =H10 -> 31.4 | H115: =G115*F115 -> 60015.291 | I115: =M10 -> 29 | J115: =I115*F115 -> 55428.135 | K115: =R10 -> 41.2 | L115: =K115*F115 -> 78746.177
B116: =B69 -> GP | C116: =1/8 -> 0.125 | D116: =$F$110*$F$111*C116 -> 62500 | E116: =E11 -> 323.1 | F116: =D116/E116 -> 193.43856 | G116: =H11 -> 321.9 | H116: =G116*F116 -> 62267.874 | I116: =M11 -> 303.1 | J116: =I116*F116 -> 58631.229 | K116: =R11 -> 299 | L116: =K116*F116 -> 57838.131
B117: =B70 -> BATASHOE | C117: =1/8 -> 0.125 | D117: =$F$110*$F$111*C117 -> 62500 | E117: =E12 -> 905.4 | F117: =D117/E117 -> 69.030263 | G117: =H12 -> 834.7 | H117: =G117*F117 -> 57619.56 | I117: =M12 -> 802.7 | J117: =I117*F117 -> 55410.592 | K117: =R12 -> 877.7 | L117: =K117*F117 -> 60587.862
B118: =B71 -> RENATA | C118: =1/8 -> 0.125 | D118: =$F$110*$F$111*C118 -> 62500 | E118: =E13 -> 635.1 | F118: =D118/E118 -> 98.409699 | G118: =H13 -> 500.5 | H118: =G118*F118 -> 49254.054 | I118: =M13 -> 488.4 | J118: =I118*F118 -> 48063.297 | K118: =R13 -> 480.4 | L118: =K118*F118 -> 47276.02
B119: =B72 -> WALTONHIL | C119: =1/8 -> 0.125 | D119: =$F$110*$F$111*C119 -> 62500 | E119: =E14 -> 487.5 | F119: =D119/E119 -> 128.20513 | G119: =H14 -> 462.7 | H119: =G119*F119 -> 59320.513 | I119: =M14 -> 406.3 | J119: =I119*F119 -> 52089.744 | K119: =R14 -> 419.9 | L119: =K119*F119 -> 53833.333
B120: =B73 -> RAKC | C120: =1/8 -> 0.125 | D120: =$F$110*$F$111*C120 -> 62500 | E120: =E15 -> 22.6 | F120: =D120/E120 -> 2765.4867 | G120: =H15 -> 22.6 | H120: =G120*F120 -> 62500 | I120: =M15 -> 19.2 | J120: =I120*F120 -> 53097.345 | K120: =R15 -> 25.1 | L120: =K120*F120 -> 69413.717
B121: =B74 -> OLYMPIC | C121: =1/8 -> 0.125 | D121: =$F$110*$F$111*C121 -> 62500 | E121: =E16 -> 158 | F121: =D121/E121 -> 395.56962 | G121: =H16 -> 147.2 | H121: =G121*F121 -> 58227.848 | I121: =M16 -> 153.5 | J121: =I121*F121 -> 60719.937 | K121: =R16 -> 154.7 | L121: =K121*F121 -> 61194.62
B122: Total Equity Value | D122: =SUM(D114:D121) -> 500000 | H122: =SUM(H114:H121) -> 483933.4 | J122: =SUM(J114:J121) -> 450695.71 | L122: =SUM(L114:L121) -> 500900.73
B123: Total T-Bill Value | D123: =F110*F112 -> 500000 | H123: =D123*EXP(D59) -> 514550.87 | J123: =H123*EXP(E59) -> 528445.59 | L123: =J123*EXP(F59) -> 543936.12
